Workbook

Sheet Overall Summary
C3: Cash Balance | D3: Cash% | E3: Initial Deposit | F3: Realized Profit | G3: Unrealized Profit | H3: Paid fee | I3: Total | J3: Net Gain | K3: Return | M3: Target | O3: S&P 500
B4: SG Portfolio | C4: ='SG Portfolio'!D11 -> -33411.634 | D4: =C4/I4 -> -1.3361683 | E4: ='SG Portfolio'!D4 -> 23110 | F4: ='SG Portfolio'!G3 -> 6662.8437 | G4: ='SG Portfolio'!M225 -> -4767.286 | H4: ='SG Portfolio'!G5 -> 6156.7367 | I4: =SUM(E4:G4) -> 25005.558 | J4: =I4-E4 -> 1895.5577 | K4: =J4/E4 -> 0.082023266 | M4: =N4/E6 -> 0.19166667 | N4: =E6*COUNT(D11:Z11)/12*M5 -> 6250.25 | O4: Jan 2, 2020 | P4: 3244.67 | R4: Mar 1, 2020 | S4: 2192 | T4: Lowest
B5: FUTU Portfolio | C5: ='FUTU Portfolio'!D13 -> 5239.2215 | D5: =C5/I5 -> 1 | E5: ='FUTU Portfolio'!D6 -> 9500 | F5: ='FUTU Portfolio'!G5 -> -4260.7785 | G5: ='FUTU Portfolio'!M230 -> 0 | H5: ='FUTU Portfolio'!G7 -> 1249.2297 | I5: =SUM(E5:G5) -> 5239.2215 | J5: =I5-E5 -> -4260.7785 | K5: =J5/E5 -> -0.448503 | M5: 0.1 | N5: Annual Goal | O5: Current | P5: 4533 | Q5: =(P5-P4)/P4 -> 0.39706041 | R5: Current | S5: =P5 -> 4533 | T5: =(S5-S4)/S4 -> 1.0679745
B6: Entire Portfolio | C6: =C4+C5 -> -28172.413 | D6: =C6/I6 -> -0.9314802 | E6: =E4+E5 -> 32610 | F6: =F4+F5 -> 2402.0652 | G6: =G4+G5 -> -4767.286 | H6: =H4+H5 -> 7405.9664 | I6: =SUM(E6:G6) -> 30244.779 | J6: =I6-E6 -> -2365.2208 | K6: =J6/E6 -> -0.072530537
D11: 43891 | E11: 43922 | F11: 43952 | G11: 43983 | H11: 44013 | I11: 44044 | J11: 44075 | K11: 44105 | L11: 44136 | M11: 44166 | N11: 44197 | O11: 44228 | P11: 44256 | Q11: 44287 | R11: 44317 | S11: 44348 | T11: 44378 | U11: 44409 | V11: 44440 | W11: 44470 | X11: 44501 | Y11: 44531 | Z11: 44562 | AB11: Total
B12: SG Portfolio | C12: Regular Trade | D12: =SUM('SG Portfolio'!I9) -> 51.02 | E12: =SUM('SG Portfolio'!J9) -> 211.6 | F12: =SUM('SG Portfolio'!K9) -> 221.24 | G12: =SUM('SG Portfolio'!L9) -> 335.9444 | H12: =SUM('SG Portfolio'!M9) -> 177.16831 | I12: =SUM('SG Portfolio'!N9) -> 1068.36 | J12: =SUM('SG Portfolio'!O9) -> 113.36 | K12: =SUM('SG Portfolio'!P9) -> 232.24 | ... M12: =SUM('SG Portfolio'!R9) -> 165.62 | N12: =SUM('SG Portfolio'!S9)-SUM('Day Trade'!E139:E150) -> 626.22229 | O12: =SUM('SG Portfolio'!T9) -> -358.88 | P12: =SUM('SG Portfolio'!U9)-SUM('Day Trade'!E151:E158) -> 1253.07 | Q12: =SUM('SG Portfolio'!V9)-SUM('Day Trade'!E159:E162) -> 1698.91 | R12: =SUM('SG Portfolio'!W9)-'Day Trade'!E163 -> 1028.6518 | S12: =SUM('SG Portfolio'!X9) -> 1944.54 | T12: =SUM('SG Portfolio'!Y9)-SUM('Day Trade'!E164:E172) -> 3176.43 | U12: =SUM('SG Portfolio'!Z9)-SUM('Day Trade'!E173:E180) -> -4689.4895 | V12: =SUM('SG Portfolio'!AA9)-'Day Trade'!E181 -> 179.58 | W12: =SUM('SG Portfolio'!AB9) -> 835.32451 | X12: =SUM('SG Portfolio'!AC9) -> 524.06 | Y12: =SUM('SG Portfolio'!AD9)-'Day Trade'!E182 -> 561.47769 | Z12: =SUM('SG Portfolio'!AE9)-SUM('Day Trade'!E183:E187) -> -4311.1505 | AB12: =SUM(D12:AA12) -> 6081.0605
C13: Day Trade | D13: 0 | E13: 0 | F13: 0 | G13: 0 | H13: 0 | I13: 0 | J13: 0 | K13: 0 | L13: 0 | M13: 0 | N13: =SUM('Day Trade'!E139:E150) -> -1148.4441 | O13: 0 | P13: =SUM('Day Trade'!E151:E158) -> 1503.72 | Q13: =SUM('Day Trade'!E159:E162) -> 331.24 | R13: ='Day Trade'!E163 -> -56.76 | S13: 0 | T13: =SUM('Day Trade'!E164:E172) -> 913.14 | U13: =SUM('Day Trade'!E173:E180) -> 198.1 | V13: ='Day Trade'!E181 -> 113.24 | W13: 0 | X13: 0 | Y13: ='Day Trade'!E182 -> 76.84 | Z13: =SUM('Day Trade'!E183:E187) -> -1349.2927 | AB13: =SUM(D13:AA13) -> 581.78317
C14: Sub-total | D14: =D12+D13 -> 51.02 | E14: =E12+E13 -> 211.6 | F14: =F12+F13 -> 221.24 | G14: =G12+G13 -> 335.9444 | H14: =H12+H13 -> 177.16831 | I14: =I12+I13 -> 1068.36 | J14: =J12+J13 -> 113.36 | K14: =K12+K13 -> 232.24 | ... Z14: =Z12+Z13 -> -5660.4432 | AB14: =SUM(D14:AA14) -> 6662.8437
B15: FUTU Portfolio | C15: Regular Trade | D15: 0 | E15: 0 | F15: 0 | G15: 0 | H15: 0 | I15: 0 | J15: 0 | K15: 0 | L15: 0 | M15: 0 | N15: 0 | O15: 0 | P15: 0 | Q15: 0 | R15: 0 | S15: 0 | T15: ='FUTU Portfolio'!L11 -> -756.03 | U15: ='FUTU Portfolio'!M11 -> 0 | V15: ='FUTU Portfolio'!N11 -> 0 | W15: ='FUTU Portfolio'!O11 -> 125.86 | X15: ='FUTU Portfolio'!P11-SUM('FUTU Portfolio'!L27:L36) -> 86.58 | Y15: ='FUTU Portfolio'!Q11-SUM('FUTU Portfolio'!L37:L43,'FUTU Portfolio'!L45,'FUTU Portfolio'!L47:L52,'FUTU Portfolio'!L54:L56,'FUTU Portfolio'!L63:L64) -> -603.09 | Z15: ='FUTU Portfolio'!R11-SUM('FUTU Portfolio'!L66:L73,'FUTU Portfolio'!L76:L80,'FUTU Portfolio'!L82:L88,'FUTU Portfolio'!L91:L99,'FUTU Portfolio'!L101:'FUTU Portfolio'!L155,'FUTU Portfolio'!L156:L173,'FUTU Portfolio'!L175:L199) -> -2306.14 | AB15: =SUM(D15:AA15) -> -3452.82
C16: Day Trade | D16: 0 | E16: 0 | F16: 0 | G16: 0 | H16: 0 | I16: 0 | J16: 0 | K16: 0 | L16: 0 | M16: 0 | N16: 0 | O16: 0 | P16: 0 | Q16: 0 | R16: 0 | S16: 0 | T16: 0 | U16: 0 | V16: 0 | W16: 0 | X16: =SUM('FUTU Portfolio'!L27:L36) -> 232.19 | Y16: =SUM('FUTU Portfolio'!L37:L43,'FUTU Portfolio'!L45,'FUTU Portfolio'!L47:L52,'FUTU Portfolio'!L54:L56,'FUTU Portfolio'!L63:L64) -> 54.01 | Z16: =SUM('FUTU Portfolio'!L66:L73,'FUTU Portfolio'!L76:L80,'FUTU Portfolio'!L82:L88,'FUTU Portfolio'!L91:L99,'FUTU Portfolio'!L101:'FUTU Portfolio'!L155,'FUTU Portfolio'!L156:L173,'FUTU Portfolio'!L175:L199) -> -1094.1585 | AB16: =SUM(D16:AA16) -> -807.95849
C17: Sub-total | D17: =D15+D16 -> 0 | E17: =E15+E16 -> 0 | F17: =F15+F16 -> 0 | G17: =G15+G16 -> 0 | H17: =H15+H16 -> 0 | I17: =I15+I16 -> 0 | J17: =J15+J16 -> 0 | K17: =K15+K16 -> 0 | ... Z17: =Z15+Z16 -> -3400.2985 | AB17: =SUM(D17:AA17) -> -4260.7785
B18: Entire Portfolio | C18: Regular Trade | D18: =D12+D15 -> 51.02 | E18: =E12+E15 -> 211.6 | F18: =F12+F15 -> 221.24 | G18: =G12+G15 -> 335.9444 | H18: =H12+H15 -> 177.16831 | I18: =I12+I15 -> 1068.36 | J18: =J12+J15 -> 113.36 | K18: =K12+K15 -> 232.24 | ... Z18: =Z12+Z15 -> -6617.2905 | AB18: =SUM(D18:AA18) -> 2628.2405
C19: Day Trade | D19: =D13+D16 -> 0 | E19: =E13+E16 -> 0 | F19: =F13+F16 -> 0 | G19: =G13+G16 -> 0 | H19: =H13+H16 -> 0 | I19: =I13+I16 -> 0 | J19: =J13+J16 -> 0 | K19: =K13+K16 -> 0 | ... Z19: =Z13+Z16 -> -2443.4512 | AB19: =SUM(D19:AA19) -> -226.17531
C20: Sub-total | D20: =D18+D19 -> 51.02 | E20: =E18+E19 -> 211.6 | F20: =F18+F19 -> 221.24 | G20: =G18+G19 -> 335.9444 | H20: =H18+H19 -> 177.16831 | I20: =I18+I19 -> 1068.36 | J20: =J18+J19 -> 113.36 | K20: =K18+K19 -> 232.24 | ... Z20: =Z18+Z19 -> -9060.7417 | AB20: =SUM(D20:AA20) -> 2402.0652
D41: 43891 | E41: 43922 | F41: 43952 | G41: 43983 | H41: 44013 | I41: 44044 | J41: 44075 | K41: 44105 | L41: 44136 | M41: 44166 | N41: 44197 | O41: 44228 | P41: 44256 | Q41: 44287 | R41: 44317 | S41: 44348 | T41: 44378 | U41: 44409 | V41: 44440 | W41: 44470 | X41: 44501 | Y41: 44531 | Z41: 44562
C42: Hang Seng | D42: 23603 | E42: 24643 | F42: 22961 | G42: 24427 | H42: 24595 | I42: 25177 | J42: 23459 | K42: 24107 | L42: 26341 | M42: 27231 | N42: 28283 | O42: 28980 | P42: 28378 | Q42: 28724 | R42: 29151 | S42: 28827 | T42: 25961 | U42: 25878 | V42: 24575 | W42: 25377 | X42: 23475 | Y42: 23397 | Z42: 24429
C43: DJI | D43: 24345 | E43: 25383 | F43: 25812 | G43: 26428 | H43: 28430 | I43: 27781 | J43: 26501 | K43: 29638 | L43: 30606 | M43: 29982 | N43: 30932 | O43: 32981 | P43: 33874 | Q43: 34529 | R43: 34502 | S43: 34935 | T43: 35360 | U43: 33843 | V43: 35819 | W43: 34483 | X43: 36338 | Y43: 36113 | Z43: 36113
C44: NASDAQ | D44: 8889 | E44: 3489 | F44: 10058 | G44: 10745 | H44: 11775 | I44: 11167 | J44: 10911 | K44: 12198 | L44: 12888 | M44: 13070 | N44: 13192 | O44: 13246 | P44: 13962 | Q44: 13748 | R44: 14503 | S44: 14672 | T44: 15259 | U44: 14448 | V44: 15498 | W44: 15537 | X44: 15644 | Y44: 14806 | Z44: 14806
C45: S&P 500 | D45: 2912 | E45: 3044 | F45: 3100 | G45: 3271 | H45: 3500 | I45: 3363 | J45: 3269 | K45: 3621 | L45: 3756 | M45: 3714 | N45: 3811 | O45: 3972 | P45: 4181 | Q45: 4204 | R45: 4297 | S45: 4395 | T45: 4522 | U45: 4307 | V45: 4605 | W45: 4567 | X45: 4766 | Y45: 4659 | Z45: 4659

Sheet SG Portfolio
F2: Return
C3: Total Cash | D3: =D4+D5 -> 29772.844 | E3: Realized | F3: =G3/D4 -> 0.28830998 | G3: =AF15 -> 6662.8437 | H3: =G3/(G3+G5) -> 0.51973961 | J3: Target | L3: S&P 500
C4: Initial Deposit | D4: =4290+12110+6110+10610+3490-7000-3000-3500 -> 23110 | E4: Overall | F4: =G4/D4 -> 0.082023266 | G4: =G3+H20 -> 1895.5577 | H4: =G4/(G4+G5) -> 0.23540591 | J4: =K4/D4 -> 0.19166667 | K4: =D4*COUNT(I8:AE8)/12*J5 -> 4429.4167 | L4: Jan 2, 2020 | M4: 3244.67 | O4: Mar 1, 2020 | P4: 2192 | Q4: Lowest
C5: Realized Profit | D5: =G3 -> 6662.8437 | E5: Total paid fee | G5: =Table2[[#Totals],[Fee]]+'Day Trade'!J129+(308.12+122.12+96.9+204.1+144.28+91.68+232.1+140.27+106.68/7.7+7.44+34) -> 6156.7367 | H5: =G5/(G3+G5) -> 0.48026039 | J5: ='Overall Summary'!M5 -> 0.1 | K5: Annual Goal | L5: Current | M5: ='Overall Summary'!P5 -> 4533 | N5: =(M5-M4)/M4 -> 0.39706041 | O5: Current | P5: =M5 -> 4533 | Q5: =(P5-P4)/P4 -> 1.0679745
C8: Investment | D8: =D9+D10 -> 63184.478 | E8: =D8/D3 -> 2.1222184 | H8: Realized | I8: 43891 | J8: 43922 | K8: 43952 | L8: 43983 | M8: 44013 | N8: 44044 | O8: 44075 | P8: 44105 | Q8: 44136 | R8: 44166 | S8: 44197 | T8: 44228 | U8: 44256 | V8: 44287 | W8: 44317 | X8: 44348 | Y8: 44378 | Z8: 44409 | AA8: 44440 | AB8: 44470 | AC8: 44501 | AD8: 44531 | AE8: 44562
C9: HKEx | D9: =+$K$210+$K$214 -> 3618.7981 | E9: =D9/$D$8 -> 0.05727353 | H9: P/L (USD) | I9: =L31+L32+L33 -> 51.02 | J9: =L35+L36 -> 211.6 | K9: =L38 -> 221.24 | L9: =L39+L30 -> 335.9444 | M9: =L40+L41+L34 -> 177.16831 | N9: =L37+L42+L43+L46 -> 1068.36 | O9: =L44+L45+L48+L47 -> 113.36 | P9: =L49 -> 232.24 | Q9: =L50+L51+L52+L53+L54+L55+L56+L57+L58+L59 -> 1035.7615 | R9: =L60+L61+L62 -> 165.62 | S9: =L63+L64+L65+L66+L67+L68+L69+L70+L71+L72+L73+L74+L75+L76+L77+L78+L79+SUM('Day Trade'!E139:E150) -> -522.22181 | T9: =-308.12+L80 -> -358.88 | U9: =-122.12+SUM('Day Trade'!E151:E158)+SUM(L81:L100) -> 2756.79 | V9: =-96.9-(36.48+7.51)+L101+L102+L103+L104+L105+L106+L107+SUM('Day Trade'!E159:E162) -> 2030.15 | W9: =-204.1+L108+L109+L110+L111+'Day Trade'!E163 -> 971.89178 | X9: =-144.28+L112+L113+L114+L115+L116+L117 -> 1944.54 | Y9: =-91.68+L118+L119+L120+L121+L122+L123+L124+L125+L126+L127+L128+L129+L130+SUM('Day Trade'!E164:E172) -> 4089.57 | Z9: =-86.07+L131+L132+L133+L134+L135+L136+L137+L138+L139+L140+L141+L142+SUM('Day Trade'!E173:E180) -> -4491.3895 | AA9: =-232.1+L143+L144+L145+L146+L147+L148+L149+'Day Trade'!E181 -> 292.82 | AB9: =-140.27-106.68/7.7-7.44-34+L150+L151+L152+L153+L154+L155+L156+L157+L158+L159+L160+L161+L162+L163+L164 -> 835.32451 | AC9: =-2.38+L165+L166+L167+L168+L169 -> 524.06 | AD9: =-23.95+L170+L171+L172+L173+L174+'Day Trade'!E182 -> 638.31769 | AE9: =-11.83-(7.45+34)+SUM(L175:L202)+SUM('Day Trade'!E183:E187) -> -5660.4432
C10: USEx | D10: =+$K$212+$K$216+$K$218+$K$220 -> 59565.68 | E10: =D10/$D$8 -> 0.94272647 | J10: =IF(J9=0,0,(J9-I9)/I9) -> 3.1473932 | K10: =IF(K9=0,0,(K9-J9)/J9) -> 0.045557656 | L10: =IF(L9=0,0,(L9-K9)/K9) -> 0.51846139 | M10: =IF(M9=0,0,(M9-L9)/L9) -> -0.47262611 | N10: =IF(N9=0,0,(N9-M9)/M9) -> 5.0301982 | O10: =IF(O9=0,0,(O9-N9)/N9) -> -0.89389344 | P10: =IF(P9=0,0,(P9-O9)/O9) -> 1.0486944 | Q10: =IF(Q9=0,0,(Q9-P9)/P9) -> 3.4598757 | ... S10: =IF(S9=0,0,(S9-R9)/R9) -> -4.1531325 | T10: =IF(T9=0,0,(S9-T9)/S9) -> 0.31278243 | U10: =IF(U9=0,0,(T9-U9)/T9) -> 8.6816485 | V10: =IF(V9=0,0,(V9-U9)/U9) -> -0.26358192 | W10: =IF(W9=0,0,(W9-V9)/V9) -> -0.52127095 | X10: =IF(X9=0,0,(X9-W9)/W9) -> 1.0007783 | Y10: =IF(Y9=0,0,(Y9-X9)/X9) -> 1.1031041 | Z10: =IF(Z9=0,0,(Z9-Y9)/Y9) -> -2.0982547 | AA10: =IF(AA9=0,0,(AA9-Z9)/Z9) -> -1.0651959 | AB10: =IF(AB9=0,0,(AB9-AA9)/AA9) -> 1.8526894 | AC10: =IF(AC9=0,0,(AC9-AB9)/AB9) -> -0.37262706 | ... AE10: =IF(AE9=0,0,(AE9-AD9)/AD9) -> -9.8677524
C11: Cash Balance | D11: =D3-D8 -> -33411.634 | E11: =D11/D3 -> -1.1222184 | Q11: sub-total | R11: =SUM(I9:R9) -> 3612.3142 | AC11: sub-total | AD11: =SUM(S9:AD9) -> 8710.9727 | AE11: sub-total | AF11: =SUM(AE9) -> -5660.4432
C12: Margin | D12: =IF(D11<0,-D11,0) -> 33411.634 | E12: =TODAY()-1 -> 44648 | Q12: average month | R12: =AVERAGE(I9:R9) -> 361.23142 | AC12: average month | AD12: =AVERAGE(S9:AD9) -> 725.91439 | AE12: average month | AF12: =AVERAGE(AE9) -> -5660.4432
C13: Margin Interest | D13: =E13*'Fee and Margin'!I5 -> 6.4967067 | E13: =TODAY()-E12 -> 1 | Q13: sub-total gain | R13: 0.10906746 | AC13: sub-total gain | AD13: =AD11/D4 -> 0.37693521 | AE13: sub-total gain | AF13: =AF11/$D$4 -> -0.2449348
AE15: Total | AF15: =SUM(I9:AE9) -> 6662.8437
D16: Grade | E16: Amount | F16: Composition | G16: Unrealized P/L | J16: Return | K16: Realized Gain/Loss | L16: Exit Transactions | AE16: Monthly | AF16: =AF15/COUNT(I8:AD8) -> 302.85653
C17: Risk Profile | D17: A | E17: =+K214+K216+K210+K218 -> 39065.198 | F17: =E17/D8 -> 0.61827207 | G17: =IF(E17=0,0,H17/E17) -> 0.08941447 | H17: =+M214+M216+M210+M218 -> 3492.994 | J17: <5% | K17: =L30+L34+L36+L40+L44+L56+L58+L64+L68+L71+L73+L74+L83+L89+L90+L91+L92+L95+L96+L97+L100+L104+L106+L111+L113+L115+L116+L120+L121+L122+L123+L124+L127+L128+L129+'Day Trade'!E137 -> 3926.8368 | L17: 35 | M17: =L17/$L$21 -> 0.34653465 | AE17: Total gain | AF17: =SUM(I9:AE9)/$D$4 -> 0.28830998
D18: B | E18: =+K212+K220 -> 24119.28 | F18: =E18/D8 -> 0.38172793 | G18: =IF(E18=0,0,H18/E18) -> -0.34247623 | H18: =+M212+M220 -> -8260.28 | J18: >=5% | K18: =L32+L33+L35+L37+L38+L39+L41+L42+L43+L45+L46+L49+L50+L51+L52+L53+L54+L55+L57+L59+L60+L61+L62+L63+L65+L66+L67+L69+L70+L72+L76+L82+L93+L101+L102+L103+L107+L108+L112+L114+L117+L118+L119+L125+L130 -> 13577.643 | L18: 45 | M18: =L18/$L$21 -> 0.44554455
D19: C | E19: 0 | F19: =E19/D8 -> 0 | G19: =IF(E19=0,0,H19/E19) -> 0 | H19: 0 | J19: <0% | K19: =L31+L47+L75+L48+L77+L78+L79+L80+L81+L84+L85+L86+L87+L88+L94+L98+L99+L105+L109+L110+L126 -> -2930.2482 | L19: 21 | M19: =L19/$L$21 -> 0.20792079
D20: Total | E20: =SUM(E17:E19) -> 63184.478 | F20: =SUM(F17:F19) -> 1 | G20: =IF(E20=0,0,H20/E20) -> -0.075450272 | H20: =SUM(H17:H19) -> -4767.286 | J20: Interest expense | K20: =-308.12-122.12-96.9-(36.48+7.51)-204.1-144.28-91.68 -> -1011.19
H21: =H20/E20 -> -0.075450272 | J21: Total | K21: =SUM(K17:K20) -> 13563.041 | L21: =SUM(L17:L19) -> 101 | M21: =SUM(M17:M19) -> 1
D23: China Co. | E23: =+K212+K210+K214 -> 10831.318 | F23: =E23/(E23+E24) -> 0.23405039 | G23: =+M212+M210+M214 -> -4048.036 | H23: =IF(E23=0,0,G23/E23) -> -0.37373439 | J23: China Co. | K23: 3353.0583 | L23: 17 | M23: =K23/$K$25 -> 0.23946845
D24: US Co. | E24: =K216+K218 -> 35446.4 | F24: =E24/(E23+E24) -> 0.76594961 | G24: =M216+M218 -> 4570.51 | H24: =IF(E24=0,0,G24/E24) -> 0.12894144 | J24: US Co. | K24: 10649.03 | L24: 27 | M24: =K24/$K$25 -> 0.76053155
E25: =SUM(E23:E24) -> 46277.718 | F25: =SUM(F23:F24) -> 1 | G25: =SUM(G23:G24) -> 522.47397 | H25: =IF(E25=0,0,G25/E25) -> 0.011289968 | J25: Total | K25: =SUM(K23:K24) -> 14002.088 | M25: =SUM(M23:M24) -> 1
B28: Historical Transactions
B29: No. | C29: Stock Name | D29: Market | E29: Currency | F29: Buy Price | G29: Quantity | H29: Fee | I29: Average Price | J29: Investment | K29: Current Price | L29: Gain/Loss | M29: P/L % | N29: Exit Price | O29: Open Date | P29: Close Date | Q29: Holding Days
B30: 1 | C30: #VALUE! | D30: HK | E30: HKD | F30: 216 | G30: 100 | H30: =(I30-F30)*G30*2/7.73 -> 27.337646 | I30: 217.0566 | J30: =I30*G30 -> 21705.66 | K30: {=_FV(C30,"Price")} -> 113.5 | L30: =(N30-I30)*G30/7.73 -> 12.204398 | M30: =L30*7.8/J30 -> 0.0043856905 | N30: 218 | O30: 43885 | P30: 44004 | Q30: =Table2[[#This Row],[Close Date]]-Table2[[#This Row],[Open Date]] -> 119
B31: 2 | C31: #VALUE! | D31: NASDAQ | E31: USD | F31: 55.07 | G31: 10 | H31: 21.76 | I31: =((F31*G31)+H31)/G31 -> 57.246 | J31: =I31*G31 -> 572.46 | K31: {=_FV(C31,"Price")} -> 120.24 | L31: =(N31-I31)*G31 -> -105.46 | M31: =L31/J31 -> -0.18422248 | N31: 46.7 | O31: 43886 | P31: 43916 | Q31: =Table2[[#This Row],[Close Date]]-Table2[[#This Row],[Open Date]] -> 30
B32: 3 | C32: #VALUE! | D32: NASDAQ | E32: USD | F32: 85 | G32: 10 | H32: =10.88*2 -> 21.76 | I32: =((F32*G32)+H32)/G32 -> 87.176 | J32: =I32*G32 -> 871.76 | K32: {=_FV(C32,"Price")} -> 138.72 | L32: =(N32-I32)*G32 -> 48.24 | M32: =L32/J32 -> 0.055336331 | N32: 92 | O32: 43909 | P32: 43913 | Q32: =Table2[[#This Row],[Close Date]]-Table2[[#This Row],[Open Date]] -> 4
B33: 4 | C33: #VALUE! | D33: NASDAQ | E33: USD | F33: 47 | G33: 20 | H33: =10.88*2 -> 21.76 | I33: =((F33*G33)+H33)/G33 -> 48.088 | J33: =I33*G33 -> 961.76 | K33: {=_FV(C33,"Price")} -> 51.51 | L33: =(N33-I33)*G33 -> 108.24 | M33: =L33/J33 -> 0.11254367 | N33: 53.5 | O33: 43910 | P33: 43916 | Q33: =Table2[[#This Row],[Close Date]]-Table2[[#This Row],[Open Date]] -> 6
B34: 5 | C34: #VALUE! | D34: HK | E34: HKD | F34: 2.8 | G34: 1000 | H34: =85.22*2/7.73 -> 22.049159 | I34: 2.97 | J34: =I34*G34 -> 2970 | K34: {=_FV(C34,"Price")} -> 3.05 | L34: =(N34-I34)*G34/7.73 -> 6.4683053 | M34: =L34*7.8/J34 -> 0.016987468 | N34: 3.02 | O34: 43913 | P34: 44019 | Q34: =Table2[[#This Row],[Close Date]]-Table2[[#This Row],[Open Date]] -> 106
B35: 6 | C35: #VALUE! | D35: NASDAQ | E35: USD | F35: 65.7 | G35: 20 | H35: =10.88*2 -> 21.76 | I35: =((F35*G35)+H35)/G35 -> 66.788 | J35: =I35*G35 -> 1335.76 | K35: {=_FV(C35,"Price")} -> 158.45 | L35: =(N35-I35)*G35 -> 116.24 | M35: =L35/J35 -> 0.087021621 | N35: 72.6 | O35: 43915 | P35: 43930 | Q35: =Table2[[#This Row],[Close Date]]-Table2[[#This Row],[Open Date]] -> 15
B36: 7 | C36: #VALUE! | D36: NASDAQ | E36: USD | F36: =(156*10+194*2)/12 -> 162.33333 | G36: 12 | H36: =10.88*3 -> 32.64 | I36: =((F36*G36)+H36)/G36 -> 165.05333 | J36: =I36*G36 -> 1980.64 | K36: {=_FV(C36,"Price")} -> 223.59 | L36: =(N36-I36)*G36 -> 95.36 | M36: =L36/J36 -> 0.048146054 | N36: 173 | O36: 43915 | P36: 43930 | Q36: =Table2[[#This Row],[Close Date]]-Table2[[#This Row],[Open Date]] -> 15
B37: 8 | C37: #VALUE! | D37: NYSE | E37: USD | F37: =(185+174.5)/2 -> 179.75 | G37: 10 | H37: =10.88*2 -> 21.76 | I37: =((F37*G37)+H37)/G37 -> 181.926 | J37: =I37*G37 -> 1819.26 | K37: {=_FV(C37,"Price")} -> 359.57 | L37: =(N37-I37)*G37 -> 310.74 | M37: =L37/J37 -> 0.17080571 | N37: 213 | O37: 43945 | P37: 44060 | Q37: =Table2[[#This Row],[Close Date]]-Table2[[#This Row],[Open Date]] -> 115
B38: 9 | C38: #VALUE! | D38: NYSE | E38: USD | F38: 105.8 | G38: 15 | H38: =10.88*2 -> 21.76 | I38: =((F38*G38)+H38)/G38 -> 107.25067 | J38: =I38*G38 -> 1608.76 | K38: {=_FV(C38,"Price")} -> 138.72 | L38: =(N38-I38)*G38 -> 221.24 | M38: =L38/J38 -> 0.13752207 | N38: 122 | O38: 43977 | P38: 43979 | Q38: =Table2[[#This Row],[Close Date]]-Table2[[#This Row],[Open Date]] -> 2
B39: 10 | C39: #VALUE! | D39: NYSE | E39: USD | F39: 27.5 | G39: 50 | H39: =8.88*2 -> 17.76 | I39: =((F39*G39)+H39)/G39 -> 27.8552 | J39: =I39*G39 -> 1392.76 | K39: {=_FV(C39,"Price")} -> 55.93 | L39: =(N39-I39)*G39 -> 323.74 | M39: =L39/J39 -> 0.23244493 | N39: 34.33 | O39: 43991 | P39: 43993 | Q39: =Table2[[#This Row],[Close Date]]-Table2[[#This Row],[Open Date]] -> 2
B40: 11 | C40: #VALUE! | D40: NYSE | E40: USD | F40: =(57.5*20+48*25)/(20+25) -> 52.222222 | G40: =20+25 -> 45 | H40: =8.88*3 -> 26.64 | I40: =((F40*G40)+H40)/G40 -> 52.814222 | J40: =I40*G40 -> 2376.64 | K40: {=_FV(C40,"Price")} -> 78.54 | L40: =(N40-I40)*G40 -> 88.46 | M40: =L40/J40 -> 0.037220614 | N40: 54.78 | O40: 43999 | P40: 44029 | Q40: =Table2[[#This Row],[Close Date]]-Table2[[#This Row],[Open Date]] -> 30
B41: 12 | C41: #VALUE! | D41: NASDAQ | E41: USD | F41: 228 | G41: 5 | H41: =8.88*2 -> 17.76 | I41: =((F41*G41)+H41)/G41 -> 231.552 | J41: =I41*G41 -> 1157.76 | K41: {=_FV(C41,"Price")} -> 223.59 | L41: =(N41-I41)*G41 -> 82.24 | M41: =L41/J41 -> 0.07103372 | N41: 248 | O41: 44008 | P41: 44027 | Q41: =Table2[[#This Row],[Close Date]]-Table2[[#This Row],[Open Date]] -> 19
B42: 13 | C42: #VALUE! | D42: NASDAQ | E42: USD | F42: 16.68 | G42: 80 | H42: =8.88*2 -> 17.76 | I42: =((F42*G42)+H42)/G42 -> 16.902 | J42: =I42*G42 -> 1352.16 | K42: {=_FV(C42,"Price")} -> 26.48 | L42: =(N42-I42)*G42 -> 200.64 | M42: =L42/J42 -> 0.14838481 | N42: 19.41 | O42: 44043 | P42: 44054 | Q42: =Table2[[#This Row],[Close Date]]-Table2[[#This Row],[Open Date]] -> 11
B43: 14 | C43: #VALUE! | D43: NASDAQ | E43: USD | F43: 15 | G43: 40 | H43: =8.88*2 -> 17.76 | I43: =((F43*G43)+H43)/G43 -> 15.444 | J43: =I43*G43 -> 617.76 | K43: {=_FV(C43,"Price")} -> 26.48 | L43: =(N43-I43)*G43 -> 202.24 | M43: =L43/J43 -> 0.32737633 | N43: 20.5 | O43: 44056 | P43: 44071 | Q43: =Table2[[#This Row],[Close Date]]-Table2[[#This Row],[Open Date]] -> 15
B44: 15 | C44: #VALUE! | D44: NASDAQ | E44: USD | F44: 15 | G44: 40 | H44: =8.88*2 -> 17.76 | I44: =((F44*G44)+H44)/G44 -> 15.444 | J44: =I44*G44 -> 617.76 | K44: {=_FV(C44,"Price")} -> 26.48 | L44: =(N44-I44)*G44 -> 16.64 | M44: =L44/J44 -> 0.026936027 | N44: 15.86 | O44: 44056 | P44: 44084 | Q44: =Table2[[#This Row],[Close Date]]-Table2[[#This Row],[Open Date]] -> 28
B45: 16 | C45: #VALUE! | D45: NASDAQ | E45: USD | F45: 350 | G45: 2 | H45: =8.88*2 -> 17.76 | I45: =((F45*G45)+H45)/G45 -> 358.88 | J45: =I45*G45 -> 717.76 | K45: {=_FV(C45,"Price")} -> 1091.84 | L45: =(N45-I45)*G45 -> 202.24 | M45: =L45/J45 -> 0.28176549 | N45: 460 | O45: 44082 | P45: 44091 | Q45: =Table2[[#This Row],[Close Date]]-Table2[[#This Row],[Open Date]] -> 9
B46: 17 | C46: #VALUE! | D46: NYSE | E46: USD | F46: =(185+174.5)/2 -> 179.75 | G46: 10 | H46: =8.88*2 -> 17.76 | I46: =((F46*G46)+H46)/G46 -> 181.526 | J46: =I46*G46 -> 1815.26 | K46: {=_FV(C46,"Price")} -> 359.57 | L46: =(N46-I46)*G46 -> 354.74 | M46: =L46/J46 -> 0.19542104 | N46: 217 | O46: 43945 | P46: 44074 | Q46: =Table2[[#This Row],[Close Date]]-Table2[[#This Row],[Open Date]] -> 129
B47: 18 | C47: #VALUE! | D47: NASDAQ | E47: USD | F47: 49.5 | G47: 15 | H47: =8.88*2 -> 17.76 | I47: =((F47*G47)+H47)/G47 -> 50.684 | J47: =I47*G47 -> 760.26 | K47: {=_FV(C47,"Price")} -> 51.51 | L47: =(N47-I47)*G47 -> -17.76 | M47: =L47/J47 -> -0.023360429 | N47: 49.5 | O47: 44036 | P47: 44103 | Q47: =Table2[[#This Row],[Close Date]]-Table2[[#This Row],[Open Date]] -> 67
B48: 19 | C48: #VALUE! | D48: NASDAQ | E48: USD | F48: 123 | G48: 5 | H48: =8.88*2 -> 17.76 | I48: =((F48*G48)+H48)/G48 -> 126.552 | J48: =I48*G48 -> 632.76 | K48: {=_FV(C48,"Price")} -> 71.18 | L48: =(N48-I48)*G48 -> -87.76 | M48: =L48/J48 -> -0.13869398 | N48: 109 | O48: 44050 | P48: 44103 | Q48: =Table2[[#This Row],[Close Date]]-Table2[[#This Row],[Open Date]] -> 53
B49: 20 | C49: #VALUE! | D49: NYSE | E49: USD | F49: 258 | G49: 5 | H49: =8.88*2 -> 17.76 | I49: =((F49*G49)+H49)/G49 -> 261.552 | J49: =I49*G49 -> 1307.76 | K49: {=_FV(C49,"Price")} -> 115.09 | L49: =(N49-I49)*G49 -> 232.24 | M49: =L49/J49 -> 0.1775861 | N49: 308 | O49: 44061 | P49: 44124 | Q49: =Table2[[#This Row],[Close Date]]-Table2[[#This Row],[Open Date]] -> 63
B50: 21 | C50: #VALUE! | D50: NYSE | E50: USD | F50: 40.5 | G50: 15 | H50: =8.88*2 -> 17.76 | I50: =((F50*G50)+H50)/G50 -> 41.684 | J50: =I50*G50 -> 625.26 | K50: {=_FV(C50,"Price")} -> 64.8 | L50: =(N50-I50)*G50 -> 82.74 | M50: =L50/J50 -> 0.13232895 | N50: 47.2 | O50: 44091 | P50: 44139 | Q50: =Table2[[#This Row],[Close Date]]-Table2[[#This Row],[Open Date]] -> 48
B51: 22 | C51: #VALUE! | D51: NASDAQ | E51: USD | F51: 123 | G51: 5 | H51: =8.88*2 -> 17.76 | I51: =((F51*G51)+H51)/G51 -> 126.552 | J51: =I51*G51 -> 632.76 | K51: {=_FV(C51,"Price")} -> 71.18 | L51: =(N51-I51)*G51 -> 42.24 | M51: =L51/J51 -> 0.066755168 | N51: 135 | O51: 44050 | P51: 44141 | Q51: =Table2[[#This Row],[Close Date]]-Table2[[#This Row],[Open Date]] -> 91
B52: 23 | C52: #VALUE! | D52: NYSE | E52: USD | F52: 23 | G52: 40 | H52: =8.88*2 -> 17.76 | I52: =((F52*G52)+H52)/G52 -> 23.444 | J52: =I52*G52 -> 937.76 | K52: {=_FV(C52,"Price")} -> 27.13 | L52: =(N52-I52)*G52 -> 62.24 | M52: =L52/J52 -> 0.066370926 | N52: 25 | O52: 44070 | P52: 44141 | Q52: =Table2[[#This Row],[Close Date]]-Table2[[#This Row],[Open Date]] -> 71
B53: 24 | C53: #VALUE! | D53: NASDAQ | E53: USD | F53: 263 | G53: 3 | H53: =8.88*2 -> 17.76 | I53: =((F53*G53)+H53)/G53 -> 268.92 | J53: =I53*G53 -> 806.76 | K53: {=_FV(C53,"Price")} -> 223.59 | L53: =(N53-I53)*G53 -> 48.24 | M53: =L53/J53 -> 0.059794734 | N53: 285 | O53: 44113 | P53: 44141 | Q53: =Table2[[#This Row],[Close Date]]-Table2[[#This Row],[Open Date]] -> 28
B54: 25 | C54: #VALUE! | D54: NASDAQ | E54: USD | F54: 24.332 | G54: 50 | H54: 26.64 | I54: =((F54*G54)+H54)/G54 -> 24.8648 | J54: =I54*G54 -> 1243.24 | K54: {=_FV(C54,"Price")} -> 37.59 | L54: =(N54-I54)*G54 -> 156.76 | M54: =L54/J54 -> 0.12608989 | N54: 28 | O54: 44092 | P54: 44145 | Q54: =Table2[[#This Row],[Close Date]]-Table2[[#This Row],[Open Date]] -> 53
B55: 26 | C55: #VALUE! | D55: NYSE | E55: USD | F55: 13.5 | G55: 55 | H55: =8.88 -> 8.88 | I55: =((F55*G55)+H55)/G55 -> 13.661455 | J55: =I55*G55 -> 751.38 | K55: {=_FV(C55,"Price")} -> 6 | L55: =(N55-I55)*G55 -> 348.62 | M55: =L55/J55 -> 0.46397296 | N55: 20 | O55: 44137 | P55: 44152 | Q55: =Table2[[#This Row],[Close Date]]-Table2[[#This Row],[Open Date]] -> 15
B56: 27 | C56: #VALUE! | D56: NYSE | E56: USD | F56: 27.5 | G56: 30 | H56: =8.88*2 -> 17.76 | I56: =((F56*G56)+H56)/G56 -> 28.092 | J56: =I56*G56 -> 842.76 | K56: {=_FV(C56,"Price")} -> 23.87 | L56: =(N56-I56)*G56 -> 28.74 | M56: =L56/J56 -> 0.034102236 | N56: 29.05 | O56: 44118 | P56: 44154 | Q56: =Table2[[#This Row],[Close Date]]-Table2[[#This Row],[Open Date]] -> 36
B57: 28 | C57: #VALUE! | D57: NYSE | E57: USD | F57: 200 | G57: 5 | H57: =8.88*2 -> 17.76 | I57: =((F57*G57)+H57)/G57 -> 203.552 | J57: =I57*G57 -> 1017.76 | K57: {=_FV(C57,"Price")} -> 335.3 | L57: =(N57-I57)*G57 -> 97.24 | M57: =L57/J57 -> 0.095543154 | N57: 223 | O57: 44130 | P57: 44154 | Q57: =Table2[[#This Row],[Close Date]]-Table2[[#This Row],[Open Date]] -> 24
B58: 29 | C58: #VALUE! | D58: HK | E58: HKD | F58: 4.53 | G58: 2000 | H58: =10.88*2 -> 21.76 | I58: =((F58*G58)+H58*7.8)/G58 -> 4.614864 | J58: =I58*G58 -> 9229.728 | K58: {=_FV(C58,"Price")} -> 4.72 | L58: =(N58-I58)*G58/7.8 -> 16.701538 | M58: =L58*7.8/J58 -> 0.014114392 | N58: 4.68 | O58: 44050 | P58: 44155 | Q58: =Table2[[#This Row],[Close Date]]-Table2[[#This Row],[Open Date]] -> 105
B59: 30 | C59: #VALUE! | D59: NASDAQ | E59: USD | F59: 440 | G59: 2 | H59: =8.88*2 -> 17.76 | I59: =((F59*G59)+H59)/G59 -> 448.88 | J59: =I59*G59 -> 897.76 | K59: {=_FV(C59,"Price")} -> 1091.84 | L59: =(N59-I59)*G59 -> 152.24 | M59: =L59/J59 -> 0.16957762 | N59: 525 | O59: 44152 | P59: 44160 | Q59: =Table2[[#This Row],[Close Date]]-Table2[[#This Row],[Open Date]] -> 8
B60: 31 | C60: #VALUE! | D60: NYSE | E60: USD | F60: 38 | G60: 15 | H60: =8.88*2 -> 17.76 | I60: =((F60*G60)+H60)/G60 -> 39.184 | J60: =I60*G60 -> 587.76 | K60: {=_FV(C60,"Price")} -> 53.28 | L60: =(N60-I60)*G60 -> 43.74 | M60: =L60/J60 -> 0.07441813 | N60: 42.1 | O60: 44146 | P60: 44175 | Q60: =Table2[[#This Row],[Close Date]]-Table2[[#This Row],[Open Date]] -> 29
B61: 32 | C61: #VALUE! | D61: NASDAQ | E61: USD | F61: 127 | G61: 6 | H61: =8.88*2 -> 17.76 | I61: =((F61*G61)+H61)/G61 -> 129.96 | J61: =I61*G61 -> 779.76 | K61: {=_FV(C61,"Price")} -> 128.04 | L61: =(N61-I61)*G61 -> 59.64 | M61: =L61/J61 -> 0.076485072 | N61: 139.9 | O61: 44140 | P61: 44183 | Q61: =Table2[[#This Row],[Close Date]]-Table2[[#This Row],[Open Date]] -> 43
B62: 33 | C62: #VALUE! | D62: NASDAQ | E62: USD | F62: 625 | G62: 1 | H62: =8.88*2 -> 17.76 | I62: =((F62*G62)+H62)/G62 -> 642.76 | J62: =I62*G62 -> 642.76 | K62: {=_FV(C62,"Price")} -> 1091.84 | L62: =(N62-I62)*G62 -> 62.24 | M62: =L62/J62 -> 0.09683241 | N62: 705 | O62: 44169 | P62: 44201 | Q62: =Table2[[#This Row],[Close Date]]-Table2[[#This Row],[Open Date]] -> 32
B63: 34 | C63: #VALUE! | D63: NASDAQ | E63: USD | F63: 88 | G63: 8 | H63: =8.88*2 -> 17.76 | I63: =((F63*G63)+H63)/G63 -> 90.22 | J63: =I63*G63 -> 721.76 | K63: {=_FV(C63,"Price")} -> 93.82 | L63: =(N63-I63)*G63 -> 62.24 | M63: =L63/J63 -> 0.086233651 | N63: 98 | O63: 44151 | P63: 44202 | Q63: =Table2[[#This Row],[Close Date]]-Table2[[#This Row],[Open Date]] -> 51
B64: 35 | C64: #VALUE! | D64: NASDAQ | E64: USD | F64: 49.5 | G64: 10 | H64: =8.88*2 -> 17.76 | I64: =((F64*G64)+H64)/G64 -> 51.276 | J64: =I64*G64 -> 512.76 | K64: {=_FV(C64,"Price")} -> 51.51 | L64: =(N64-I64)*G64 -> 12.24 | M64: =L64/J64 -> 0.023870817 | N64: 52.5 | O64: 44036 | P64: 44203 | Q64: =Table2[[#This Row],[Close Date]]-Table2[[#This Row],[Open Date]] -> 167
B65: 36 | C65: #VALUE! | D65: NYSE | E65: USD | F65: 180 | G65: 4 | H65: =8.88*2 -> 17.76 | I65: =((F65*G65)+H65)/G65 -> 184.44 | J65: =I65*G65 -> 737.76 | K65: {=_FV(C65,"Price")} -> 69.82 | L65: =(N65-I65)*G65 -> 182.24 | M65: =L65/J65 -> 0.247018 | N65: 230 | O65: 44144 | P65: 44208 | Q65: =Table2[[#This Row],[Close Date]]-Table2[[#This Row],[Open Date]] -> 64
B66: 37 | C66: #VALUE! | D66: NYSE | E66: USD | F66: 19.5 | G66: 50 | H66: =8.88*2 -> 17.76 | I66: =((F66*G66)+H66)/G66 -> 19.8552 | J66: =I66*G66 -> 992.76 | K66: {=_FV(C66,"Price")} -> 5.25 | L66: =(N66-I66)*G66 -> 57.24 | M66: =L66/J66 -> 0.05765744 | N66: 21 | O66: 44168 | P66: 44208 | Q66: =Table2[[#This Row],[Close Date]]-Table2[[#This Row],[Open Date]] -> 40
B67: 38 | C67: #VALUE! | D67: NASDAQ | E67: USD | F67: 78 | G67: 10 | H67: =8.88*2 -> 17.76 | I67: =((F67*G67)+H67)/G67 -> 79.776 | J67: =I67*G67 -> 797.76 | K67: {=_FV(C67,"Price")} -> 80.01 | L67: =(N67-I67)*G67 -> 94.24 | M67: =L67/J67 -> 0.11813077 | N67: 89.2 | O67: 44147 | P67: 44208 | Q67: =Table2[[#This Row],[Close Date]]-Table2[[#This Row],[Open Date]] -> 61
B68: 39 | C68: #VALUE! | D68: NASDAQ | E68: USD | F68: 516 | G68: 2 | H68: =8.88*2 -> 17.76 | I68: =((F68*G68)+H68)/G68 -> 524.88 | J68: =I68*G68 -> 1049.76 | K68: {=_FV(C68,"Price")} -> 282.19 | L68: =(N68-I68)*G68 -> 34.24 | M68: =L68/J68 -> 0.032616979 | N68: 542 | O68: 44195 | P68: 44208 | Q68: =Table2[[#This Row],[Close Date]]-Table2[[#This Row],[Open Date]] -> 13
B69: 40 | C69: #VALUE! | D69: NYSE | E69: USD | F69: =(52+46)/2 -> 49 | G69: 20 | H69: =8.88*4 -> 35.52 | I69: =((F69*G69)+H69)/G69 -> 50.776 | J69: =I69*G69 -> 1015.52 | K69: {=_FV(C69,"Price")} -> 21.21 | L69: =(N69-I69)*G69 -> 244.48 | M69: =L69/J69 -> 0.24074366 | N69: 63 | O69: 44166 | P69: 44208 | Q69: =Table2[[#This Row],[Close Date]]-Table2[[#This Row],[Open Date]] -> 42
B70: 41 | C70: #VALUE! | D70: HK | E70: HKD | F70: 1.85 | G70: 4000 | H70: =60*2+(F70*G70+Table2[[#This Row],[Exit Price]]*G70)*(0.1%+0.002%+0.0027%+0.005%) -> 138.4296 | I70: =((F70*G70)+H70)/G70 -> 1.8846074 | J70: =I70*G70 -> 7538.4296 | K70: {=_FV(C70,"Price")} -> 3.1 | L70: =(N70-I70)*G70/7.8 -> 238.66287 | M70: =L70*7.8/J70 -> 0.24694406 | N70: 2.35 | O70: 44204 | P70: 44211 | Q70: =Table2[[#This Row],[Close Date]]-Table2[[#This Row],[Open Date]] -> 7
B71: 42 | C71: #VALUE! | D71: HK | E71: HKD | F71: 47.5 | G71: 500 | H71: =60*2+(F71*G71+Table2[[#This Row],[Exit Price]]*G71)*(0.1%+0.002%+0.0027%+0.005%) -> 173.2045 | I71: =((F71*G71)+H71)/G71 -> 47.846409 | J71: =I71*G71 -> 23923.204 | K71: {=_FV(C71,"Price")} -> 55.3 | L71: =(N71-I71)*G71/7.8 -> 105.99942 | M71: =L71/J71 -> 0.0044308204 | N71: 49.5 | O71: 44154 | P71: 44214 | Q71: =Table2[[#This Row],[Close Date]]-Table2[[#This Row],[Open Date]] -> 60
B72: 43 | C72: #VALUE! | D72: NASDAQ | E72: USD | F72: 60 | G72: 10 | H72: =8.88*2 -> 17.76 | I72: =((F72*G72)+H72)/G72 -> 61.776 | J72: =I72*G72 -> 617.76 | K72: {=_FV(C72,"Price")} -> 59.18 | L72: =(N72-I72)*G72 -> 37.24 | M72: =L72/J72 -> 0.06028231 | N72: 65.5 | O72: 44145 | P72: 44215 | Q72: =Table2[[#This Row],[Close Date]]-Table2[[#This Row],[Open Date]] -> 70
B73: 44 | C73: #VALUE! | D73: NYSE | E73: USD | F73: 67 | G73: 15 | H73: =8.88*2 -> 17.76 | I73: =((F73*G73)+H73)/G73 -> 68.184 | J73: =I73*G73 -> 1022.76 | K73: {=_FV(C73,"Price")} -> 3.19 | L73: =(N73-I73)*G73 -> 5.94 | M73: =L73/J73 -> 0.0058078141 | N73: 68.58 | O73: 44202 | P73: 44215 | Q73: =Table2[[#This Row],[Close Date]]-Table2[[#This Row],[Open Date]] -> 13
B74: 45 | C74: #VALUE! | D74: NASDAQ | E74: USD | F74: 515 | G74: 2 | H74: =8.88*2 -> 17.76 | I74: =((F74*G74)+H74)/G74 -> 523.88 | J74: =I74*G74 -> 1047.76 | K74: {=_FV(C74,"Price")} -> 693.4 | L74: =(N74-I74)*G74 -> 23.66 | M74: =L74/J74 -> 0.022581507 | N74: 535.71 | O74: 44156 | P74: 44215 | Q74: =Table2[[#This Row],[Close Date]]-Table2[[#This Row],[Open Date]] -> 59
B75: 46 | C75: #VALUE! | D75: NASDAQ | E75: USD | F75: 85.35 | G75: 30 | H75: 53.28 | I75: =((F75*G75)+H75)/G75 -> 87.126 | J75: =I75*G75 -> 2613.78 | K75: {=_FV(C75,"Price")} -> 21.25 | L75: =(N75-I75)*G75 -> -183.78 | M75: =L75/J75 -> -0.070311962 | N75: 81 | O75: 44070 | P75: 44221 | Q75: =Table2[[#This Row],[Close Date]]-Table2[[#This Row],[Open Date]] -> 151
B76: 47 | C76: #VALUE! | D76: NASDAQ | E76: USD | F76: 85.35 | G76: 10 | H76: 8.88 | I76: =((F76*G76)+H76)/G76 -> 86.238 | J76: =I76*G76 -> 862.38 | K76: {=_FV(C76,"Price")} -> 21.25 | L76: =(N76-I76)*G76 -> 77.62 | M76: =L76/J76 -> 0.090006726 | N76: 94 | O76: 44070 | P76: 44223 | Q76: =Table2[[#This Row],[Close Date]]-Table2[[#This Row],[Open Date]] -> 153
B77: 48 | C77: #VALUE! | D77: NYSE | E77: USD | F77: 273.33333 | G77: 12 | H77: 35.52 | I77: =((F77*G77)+H77)/G77 -> 276.29333 | J77: =I77*G77 -> 3315.52 | K77: {=_FV(C77,"Price")} -> 115.09 | L77: =(N77-I77)*G77 -> -190.84 | M77: =L77/J77 -> -0.057559598 | N77: 260.39 | O77: 44133 | P77: 44225 | Q77: =Table2[[#This Row],[Close Date]]-Table2[[#This Row],[Open Date]] -> 92
B78: 49 | C78: #VALUE! | D78: AMEX | E78: USD | F78: 179.98889 | G78: 18 | H78: 26.64 | I78: =((F78*G78)+H78)/G78 -> 181.46889 | J78: =I78*G78 -> 3266.44 | K78: {=_FV(C78,"Price")} -> 179.06 | L78: =(N78-I78)*G78 -> -158.56 | M78: =L78/J78 -> -0.048542144 | N78: 172.66 | O78: 44043 | P78: 44225 | Q78: =Table2[[#This Row],[Close Date]]-Table2[[#This Row],[Open Date]] -> 182
B79: 50 | C79: #VALUE! | D79: NASDAQ | E79: USD | F79: 466 | G79: 2 | H79: 17.76 | I79: =((F79*G79)+H79)/G79 -> 474.88 | J79: =I79*G79 -> 949.76 | K79: {=_FV(C79,"Price")} -> 450.01 | L79: =(N79-I79)*G79 -> -16.64 | M79: =L79/J79 -> -0.017520216 | N79: 466.56 | O79: 44202 | P79: 44225 | Q79: =Table2[[#This Row],[Close Date]]-Table2[[#This Row],[Open Date]] -> 23
B80: 51 | C80: #VALUE! | D80: NASDAQ | E80: USD | F80: 270 | G80: 4 | H80: =8.88*2+1 -> 18.76 | I80: =((F80*G80)+H80)/G80 -> 274.69 | J80: =I80*G80 -> 1098.76 | K80: {=_FV(C80,"Price")} -> 223.59 | L80: =(N80-I80)*G80 -> -50.76 | M80: =L80/J80 -> -0.046197532 | N80: 262 | O80: 44196 | P80: 44253 | Q80: =Table2[[#This Row],[Close Date]]-Table2[[#This Row],[Open Date]] -> 57
B81: 52 | C81: #VALUE! | D81: NASDAQ | E81: USD | F81: 268 | G81: 15 | H81: =8.88*2+1 -> 18.76 | I81: =((F81*G81)+H81)/G81 -> 269.25067 | J81: =I81*G81 -> 4038.76 | K81: {=_FV(C81,"Price")} -> 223.59 | L81: =(N81-I81)*G81 -> -63.76 | M81: =L81/J81 -> -0.015787024 | N81: 265 | O81: 44224 | P81: 44259 | Q81: =Table2[[#This Row],[Close Date]]-Table2[[#This Row],[Open Date]] -> 35
B82: 53 | C82: #VALUE! | D82: NYSE | E82: USD | F82: 13.5 | G82: =25 -> 25 | H82: =8.88*2 -> 17.76 | I82: =((F82*G82)+H82)/G82 -> 14.2104 | J82: =I82*G82 -> 355.26 | K82: {=_FV(C82,"Price")} -> 6 | L82: =(N82-I82)*G82 -> 22.99 | M82: =L82/J82 -> 0.064713168 | N82: 15.13 | O82: 44137 | P82: 44260 | Q82: =Table2[[#This Row],[Close Date]]-Table2[[#This Row],[Open Date]] -> 123
B83: 54 | C83: #VALUE! | D83: NASDAQ | E83: USD | F83: 262 | G83: 60 | H83: =8.88*2+1 -> 18.76 | I83: =((F83*G83)+H83)/G83 -> 262.31267 | J83: =I83*G83 -> 15738.76 | K83: {=_FV(C83,"Price")} -> 223.59 | L83: =(N83-I83)*G83 -> 161.24 | M83: =L83/J83 -> 0.010244772 | N83: 265 | O83: 44263 | P83: 44264 | Q83: =Table2[[#This Row],[Close Date]]-Table2[[#This Row],[Open Date]] -> 1
B84: 55 | C84: #VALUE! | D84: NASDAQ | E84: USD | F84: 270 | G84: 50 | H84: =8.88*2+1 -> 18.76 | I84: =((F84*G84)+H84)/G84 -> 270.3752 | J84: =I84*G84 -> 13518.76 | K84: {=_FV(C84,"Price")} -> 223.59 | L84: =(N84-I84)*G84 -> -243.76 | M84: =L84/J84 -> -0.01803124 | N84: 265.5 | O84: 44224 | P84: 44264 | Q84: =Table2[[#This Row],[Close Date]]-Table2[[#This Row],[Open Date]] -> 40
B85: 56 | C85: #VALUE! | D85: NASDAQ | E85: USD | F85: 272 | G85: 50 | H85: =8.88+1 -> 9.88 | I85: =((F85*G85)+H85)/G85 -> 272.1976 | J85: =I85*G85 -> 13609.88 | K85: {=_FV(C85,"Price")} -> 223.59 | L85: =(N85-I85)*G85 -> -309.88 | M85: =L85/J85 -> -0.022768753 | N85: 266 | O85: 44224 | P85: 44264 | Q85: =Table2[[#This Row],[Close Date]]-Table2[[#This Row],[Open Date]] -> 40
B86: 57 | C86: #VALUE! | D86: NASDAQ | E86: USD | F86: 268 | G86: 15 | H86: =8.88+1 -> 9.88 | I86: =((F86*G86)+H86)/G86 -> 268.65867 | J86: =I86*G86 -> 4029.88 | K86: {=_FV(C86,"Price")} -> 223.59 | L86: =(N86-I86)*G86 -> -39.88 | M86: =L86/J86 -> -0.0098960763 | N86: 266 | O86: 44224 | P86: 44264 | Q86: =Table2[[#This Row],[Close Date]]-Table2[[#This Row],[Open Date]] -> 40
B87: 58 | C87: #VALUE! | D87: NASDAQ | E87: USD | F87: 268 | G87: 20 | H87: =8.88+1 -> 9.88 | I87: =((F87*G87)+H87)/G87 -> 268.494 | J87: =I87*G87 -> 5369.88 | K87: {=_FV(C87,"Price")} -> 223.59 | L87: =(N87-I87)*G87 -> -9.88 | M87: =L87/J87 -> -0.0018398921 | N87: 268 | O87: 44224 | P87: 44264 | Q87: =Table2[[#This Row],[Close Date]]-Table2[[#This Row],[Open Date]] -> 40
B88: 59 | C88: #VALUE! | D88: NASDAQ | E88: USD | F88: 274 | G88: 30 | H88: =8.88+1 -> 9.88 | I88: =((F88*G88)+H88)/G88 -> 274.32933 | J88: =I88*G88 -> 8229.88 | K88: {=_FV(C88,"Price")} -> 223.59 | L88: =(N88-I88)*G88 -> -189.88 | M88: =L88/J88 -> -0.023072025 | N88: 268 | O88: 44224 | P88: 44264 | Q88: =Table2[[#This Row],[Close Date]]-Table2[[#This Row],[Open Date]] -> 40
B89: 60 | C89: #VALUE! | D89: NASDAQ | E89: USD | F89: 237.5 | G89: 60 | H89: =8.88*2+1 -> 18.76 | I89: =((F89*G89)+H89)/G89 -> 237.81267 | J89: =I89*G89 -> 14268.76 | K89: {=_FV(C89,"Price")} -> 115.09 | L89: =(N89-I89)*G89 -> 131.24 | M89: =L89/J89 -> 0.0091977158 | N89: 240 | O89: 44265 | P89: 44266 | Q89: =Table2[[#This Row],[Close Date]]-Table2[[#This Row],[Open Date]] -> 1
B90: 61 | C90: #VALUE! | D90: NASDAQ | E90: USD | F90: =(277*90+274*10)/100 -> 276.7 | G90: =90+10 -> 100 | H90: 18.76 | I90: =((F90*G90)+H90)/G90 -> 276.8876 | J90: =I90*G90 -> 27688.76 | K90: {=_FV(C90,"Price")} -> 223.59 | L90: =(N90-I90)*G90 -> 11.24 | M90: =L90/J90 -> 0.00040594089 | N90: 277 | O90: 44224 | P90: 44266 | Q90: =Table2[[#This Row],[Close Date]]-Table2[[#This Row],[Open Date]] -> 42
B91: 62 | C91: #VALUE! | D91: NASDAQ | E91: USD | F91: =(274+265)/2 -> 269.5 | G91: 50 | H91: 19.76 | I91: =((F91*G91)+H91)/G91 -> 269.8952 | J91: =I91*G91 -> 13494.76 | K91: {=_FV(C91,"Price")} -> 223.59 | L91: =(N91-I91)*G91 -> 605.24 | M91: =L91/J91 -> 0.044850001 | N91: 282 | O91: 44224 | P91: 44271 | Q91: =Table2[[#This Row],[Close Date]]-Table2[[#This Row],[Open Date]] -> 47
B92: 63 | C92: #VALUE! | D92: NASDAQ | E92: USD | F92: 227 | G92: 50 | H92: =8.88*2+1 -> 18.76 | I92: =((F92*G92)+H92)/G92 -> 227.3752 | J92: =I92*G92 -> 11368.76 | K92: {=_FV(C92,"Price")} -> 115.09 | L92: =(N92-I92)*G92 -> 81.24 | M92: =L92/J92 -> 0.0071458981 | N92: 229 | O92: 44271 | P92: 44272 | Q92: =Table2[[#This Row],[Close Date]]-Table2[[#This Row],[Open Date]] -> 1
B93: 64 | C93: #VALUE! | D93: NASDAQ | E93: USD | F93: =(274+265)/2 -> 269.5 | G93: 50 | H93: 19.76 | I93: =((F93*G93)+H93)/G93 -> 269.8952 | J93: =I93*G93 -> 13494.76 | K93: {=_FV(C93,"Price")} -> 223.59 | L93: =(N93-I93)*G93 -> 905.24 | M93: =L93/J93 -> 0.067080852 | N93: 288 | O93: 44224 | P93: 44274 | Q93: =Table2[[#This Row],[Close Date]]-Table2[[#This Row],[Open Date]] -> 50
B94: 65 | C94: #VALUE! | D94: NASDAQ | E94: USD | F94: 85.6 | G94: 15 | H94: =8.88*2+1 -> 18.76 | I94: =((F94*G94)+H94)/G94 -> 86.850667 | J94: =I94*G94 -> 1302.76 | K94: {=_FV(C94,"Price")} -> 71.18 | L94: =(N94-I94)*G94 -> -9.76 | M94: =L94/J94 -> -0.0074917867 | N94: 86.2 | O94: 44271 | P94: 44278 | Q94: =Table2[[#This Row],[Close Date]]-Table2[[#This Row],[Open Date]] -> 7
B95: 66 | C95: #VALUE! | D95: NASDAQ | E95: USD | F95: 257 | G95: 50 | H95: =H244 -> 9.64 | I95: =((F95*G95)+H95)/G95 -> 257.1928 | J95: =I95*G95 -> 12859.64 | K95: {=_FV(C95,"Price")} -> 147.45 | L95: =(N95-I95)*G95 -> 140.36 | M95: =L95/J95 -> 0.010914769 | N95: 260 | O95: 44277 | P95: 44278 | Q95: =Table2[[#This Row],[Close Date]]-Table2[[#This Row],[Open Date]] -> 1
B96: 67 | C96: #VALUE! | D96: NASDAQ | E96: USD | F96: 121 | G96: 100 | H96: =8.88*2+1 -> 18.76 | I96: =((F96*G96)+H96)/G96 -> 121.1876 | J96: =I96*G96 -> 12118.76 | K96: {=_FV(C96,"Price")} -> 175.6 | L96: =(N96-I96)*G96 -> 31.24 | M96: =L96/J96 -> 0.0025778215 | N96: 121.5 | O96: 44277 | P96: 44278 | Q96: =Table2[[#This Row],[Close Date]]-Table2[[#This Row],[Open Date]] -> 1
B97: 68 | C97: #VALUE! | D97: NASDAQ | E97: USD | F97: 80.8 | G97: 100 | H97: =6.88*2+1 -> 14.76 | I97: =((F97*G97)+H97)/G97 -> 80.9476 | J97: =I97*G97 -> 8094.76 | K97: {=_FV(C97,"Price")} -> 59.77 | L97: =(N97-I97)*G97 -> 105.24 | M97: =L97/J97 -> 0.013001003 | N97: 82 | O97: 44279 | P97: 44281 | Q97: =Table2[[#This Row],[Close Date]]-Table2[[#This Row],[Open Date]] -> 2
B98: 69 | C98: #VALUE! | D98: NASDAQ | E98: USD | F98: 96.25 | G98: 150 | H98: 21.64 | I98: =((F98*G98)+H98)/G98 -> 96.394267 | J98: =I98*G98 -> 14459.14 | K98: {=_FV(C98,"Price")} -> 28.54 | L98: =(N98-I98)*G98 -> -59.14 | M98: =L98/J98 -> -0.0040901464 | N98: 96 | O98: 44279 | P98: 44281 | Q98: =Table2[[#This Row],[Close Date]]-Table2[[#This Row],[Open Date]] -> 2
B99: 70 | C99: #VALUE! | D99: NASDAQ | E99: USD | F99: 96.25 | G99: 50 | H99: 6.88 | I99: =((F99*G99)+H99)/G99 -> 96.3876 | J99: =I99*G99 -> 4819.38 | K99: {=_FV(C99,"Price")} -> 28.54 | L99: =(N99-I99)*G99 -> -9.38 | M99: =L99/J99 -> -0.0019463084 | N99: 96.2 | O99: 44279 | P99: 44281 | Q99: =Table2[[#This Row],[Close Date]]-Table2[[#This Row],[Open Date]] -> 2
B100: 71 | C100: #VALUE! | D100: NASDAQ | E100: USD | F100: 132 | G100: 100 | H100: =6.88*2+1 -> 14.76 | I100: =((F100*G100)+H100)/G100 -> 132.1476 | J100: =I100*G100 -> 13214.76 | K100: {=_FV(C100,"Price")} -> 158.45 | L100: =(N100-I100)*G100 -> 115.24 | M100: =L100/J100 -> 0.0087205519 | N100: 133.3 | O100: 44284 | P100: 44286 | Q100: =Table2[[#This Row],[Close Date]]-Table2[[#This Row],[Open Date]] -> 2
B101: 72 | C101: #VALUE! | D101: NASDAQ | E101: USD | F101: 123.8 | G101: 100 | H101: =8.88*2+1 -> 18.76 | I101: =((F101*G101)+H101)/G101 -> 123.9876 | J101: =I101*G101 -> 12398.76 | K101: {=_FV(C101,"Price")} -> 175.6 | L101: =(N101-I101)*G101 -> 821.24 | M101: =L101/J101 -> 0.066235656 | N101: 132.2 | O101: 44273 | P101: 44295 | Q101: =Table2[[#This Row],[Close Date]]-Table2[[#This Row],[Open Date]] -> 22
B102: 73 | C102: #VALUE! | D102: NASDAQ | E102: USD | F102: 75.4 | G102: 100 | H102: =6.88*2+1 -> 14.76 | I102: =((F102*G102)+H102)/G102 -> 75.5476 | J102: =I102*G102 -> 7554.76 | K102: {=_FV(C102,"Price")} -> 120.24 | L102: =(N102-I102)*G102 -> 395.24 | M102: =L102/J102 -> 0.052316685 | N102: 79.5 | O102: 44285 | P102: 44299 | Q102: =Table2[[#This Row],[Close Date]]-Table2[[#This Row],[Open Date]] -> 14
B103: 74 | C103: #VALUE! | D103: NASDAQ | E103: USD | F103: 122 | G103: 50 | H103: =8.88*2+1 -> 18.76 | I103: =((F103*G103)+H103)/G103 -> 122.3752 | J103: =I103*G103 -> 6118.76 | K103: {=_FV(C103,"Price")} -> 175.6 | L103: =(N103-I103)*G103 -> 581.24 | M103: =L103/J103 -> 0.094993103 | N103: 134 | O103: 44273 | P103: 44299 | Q103: =Table2[[#This Row],[Close Date]]-Table2[[#This Row],[Open Date]] -> 26
B104: 75 | C104: #VALUE! | D104: NASDAQ | E104: USD | F104: 35.5 | G104: 100 | H104: =2.88*2+1 -> 6.76 | I104: =((F104*G104)+H104)/G104 -> 35.5676 | J104: =I104*G104 -> 3556.76 | K104: {=_FV(C104,"Price")} -> 21.21 | L104: =(N104-I104)*G104 -> 57.24 | M104: =L104/J104 -> 0.016093298 | N104: 36.14 | O104: 44300 | P104: 44305 | Q104: =Table2[[#This Row],[Close Date]]-Table2[[#This Row],[Open Date]] -> 5
B105: 76 | C105: #VALUE! | D105: NASDAQ | E105: USD | F105: 117.265 | G105: 200 | H105: 9.64 | I105: =((F105*G105)+H105)/G105 -> 117.3132 | J105: =I105*G105 -> 23462.64 | K105: {=_FV(C105,"Price")} -> 106.33 | L105: =(N105-I105)*G105 -> -456.64 | M105: =L105/J105 -> -0.01946243 | N105: 115.03 | O105: 44300 | P105: 44306 | Q105: =Table2[[#This Row],[Close Date]]-Table2[[#This Row],[Open Date]] -> 6
B106: 77 | C106: #VALUE! | D106: NASDAQ | E106: USD | F106: 132.5 | G106: 50 | H106: =2.88*2+1 -> 6.76 | I106: =((F106*G106)+H106)/G106 -> 132.6352 | J106: =I106*G106 -> 6631.76 | K106: {=_FV(C106,"Price")} -> 175.6 | L106: =(N106-I106)*G106 -> 28.24 | M106: =L106/J106 -> 0.0042582964 | N106: 133.2 | O106: 44306 | P106: 44307 | Q106: =Table2[[#This Row],[Close Date]]-Table2[[#This Row],[Open Date]] -> 1
B107: 78 | C107: #VALUE! | D107: NASDAQ | E107: USD | F107: 38.3 | G107: 100 | H107: =2.88*2+1 -> 6.76 | I107: =((F107*G107)+H107)/G107 -> 38.3676 | J107: =I107*G107 -> 3836.76 | K107: {=_FV(C107,"Price")} -> 21.21 | L107: =(N107-I107)*G107 -> 413.24 | M107: =L107/J107 -> 0.10770546 | N107: 42.5 | O107: 44300 | P107: 44313 | Q107: =Table2[[#This Row],[Close Date]]-Table2[[#This Row],[Open Date]] -> 13
...

Sheet FUTU Portfolio
C3: ACCOUNT BALANCE | D3: =D6+G6 -> 5239.2215
F4: Return
C5: Total Cash | D5: =D6+D7 -> 5239.2215 | E5: Realized | F5: =G5/D6 -> -0.448503 | G5: =R13 -> -4260.7785 | H5: =G5/(G5+G7) -> 1.4148131 | J5: Target | L5: S&P 500
C6: Initial Deposit | D6: =3000+2000+4500 -> 9500 | E6: Overall | F6: =G6/D6 -> -0.448503 | G6: =G5+M230 -> -4260.7785 | H6: =G6/(G6+G7) -> 1.4148131 | J6: =K6/D6 -> 0.083333333 | K6: =D6*COUNT(I10:R10)/12*J7 -> 791.66667 | L6: Jan 2, 2020 | M6: 3244.67 | O6: Mar 1, 2020 | P6: 2192 | Q6: Lowest
C7: Realized Profit | D7: =G5 -> -4260.7785 | E7: Total paid fee | G7: =Table29[[#Totals],[Fee]]+I230 -> 1249.2297 | H7: =G7/(G5+G7) -> -0.41481306 | J7: ='Overall Summary'!M5 -> 0.1 | K7: Annual Goal | L7: Current | M7: ='Overall Summary'!P5 -> 4533 | N7: =(M7-M6)/M6 -> 0.39706041 | O7: Current | P7: =M7 -> 4533 | Q7: =(P7-P6)/P6 -> 1.0679745
C10: Investment | D10: =D11+D12 -> 0 | E10: =D10/D5 -> 0 | H10: Realized | I10: 44287 | J10: 44317 | K10: 44348 | L10: 44378 | M10: 44409 | N10: 44440 | O10: 44470 | P10: 44501 | Q10: 44531 | R10: 44562
C11: HKEx | D11: 0 | E11: 0 | H11: P/L (USD) | I11: 0 | J11: 0 | K11: 0 | L11: =L20 -> -756.03 | M11: 0 | N11: 0 | O11: =L22+L23 -> 125.86 | P11: {=SUM(L21+L24+L25+L26+L27+L28:L36)} -> 318.77 | Q11: =SUM(L37:L64) -> -549.08 | R11: =-350/7+SUM(L65:L210) -> -3400.2985
C12: USEx | D12: =+$K$218+$K$220+$K$222+$K$224 -> 0 | E12: =D12/$D$10 -> #DIV/0! | I12: =IF(I11=0,0,(I11-#REF!)/#REF!) -> 0 | J12: =IF(J11=0,0,(J11-I11)/I11) -> 0 | K12: =IF(K11=0,0,(K11-J11)/J11) -> 0 | L12: =IF(L11=0,0,(L11-K11)/K11) -> #DIV/0! | M12: =IF(M11=0,0,(M11-L11)/L11) -> 0 | N12: =IF(N11=0,0,(N11-M11)/M11) -> 0 | O12: =IF(O11=0,0,(O11-N11)/N11) -> #DIV/0! | P12: =IF(P11=0,0,(P11-O11)/O11) -> 1.5327348 | Q12: =IF(Q11=0,0,(Q11-P11)/P11) -> -2.7224958 | R12: =IF(R11=0,0,(R11-Q11)/Q11) -> 5.1927196
C13: Cash Balance | D13: =D5-D10 -> 5239.2215 | E13: =D13/D5 -> 1 | Q13: sub-total | R13: =SUM(I11:R11) -> -4260.7785
C14: Margin | D14: =IF(D13<0,-D13,0) -> 0 | E14: =TODAY()-1 -> 44648 | Q14: average month | R14: =AVERAGE(I11:R11) -> -426.07785
C15: Margin Interest | D15: =E15*D14*4.85%/360 -> 0 | E15: =TODAY()-E14 -> 1 | Q15: sub-total gain | R15: =R13/$D$6 -> -0.448503
B18: Historical Transactions
B19: No. | C19: Stock Name | D19: Market | E19: Currency | F19: Buy Price | G19: Quantity | H19: Fee | I19: Average Price | J19: Investment | K19: Current Price | L19: Gain/Loss | M19: P/L % | N19: Exit Price | O19: Open Date | P19: Close Date | Q19: Holding Days
B20: 1 | C20: #VALUE! | D20: NASDAQ | E20: USD | F20: 6.91 | G20: 142 | H20: =2.42+2.43 -> 4.85 | I20: =((F20*G20)+H20)/G20 -> 6.9441549 | J20: =I20*G20 -> 986.07 | K20: {=_FV(C20,"Price")} -> 2.8 | L20: =(N20-I20)*G20 -> -756.03 | M20: =L20/J20 -> -0.76671027 | N20: 1.62 | O20: 44313 | P20: 44400 | Q20: =Table29[[#This Row],[Close Date]]-Table29[[#This Row],[Open Date]] -> 87
B21: 3 | C21: #VALUE! | D21: OTC | E21: USD | F21: 62 | G21: 10 | H21: =2.02+2.04 -> 4.06 | I21: =((F21*G21)+H21)/G21 -> 62.406 | J21: =I21*G21 -> 624.06 | K21: {=_FV(C21,"Price")} -> 47.42 | L21: =(N21-I21)*G21 -> 0.94 | M21: =L21/J21 -> 0.0015062654 | N21: 62.5 | O21: 44406 | P21: 44518 | Q21: =Table29[[#This Row],[Close Date]]-Table29[[#This Row],[Open Date]] -> 112
B22: 4 | C22: #VALUE! | D22: NASDAQ | E22: USD | F22: 155 | G22: 6 | H22: =2.01+2.03 -> 4.04 | I22: =((F22*G22)+H22)/G22 -> 155.67333 | J22: =I22*G22 -> 934.04 | K22: {=_FV(C22,"Price")} -> 156.5 | L22: =(N22-I22)*G22 -> 8.02 | M22: =L22/J22 -> 0.008586356 | N22: 157.01 | O22: 44449 | P22: 44470 | Q22: =Table29[[#This Row],[Close Date]]-Table29[[#This Row],[Open Date]] -> 21
B23: 5 | C23: #VALUE! | D23: NYSE | E23: USD | F23: 151.81 | G23: 10 | H23: =2.02+2.04 -> 4.06 | I23: =((F23*G23)+H23)/G23 -> 152.216 | J23: =I23*G23 -> 1522.16 | K23: {=_FV(C23,"Price")} -> 115.09 | L23: =(N23-I23)*G23 -> 117.84 | M23: =L23/J23 -> 0.077416303 | N23: 164 | O23: 44459 | P23: 44481 | Q23: =Table29[[#This Row],[Close Date]]-Table29[[#This Row],[Open Date]] -> 22
B24: 8 | C24: #VALUE! | D24: NYSE | E24: USD | F24: 6.35 | G24: 100 | H24: =2.29+2.31 -> 4.6 | I24: =((F24*G24)+H24)/G24 -> 6.396 | J24: =I24*G24 -> 639.6 | K24: {=_FV(C24,"Price")} -> 6 | L24: =(N24-I24)*G24 -> 43.4 | M24: =L24/J24 -> 0.067854909 | N24: 6.83 | O24: 44503 | P24: 44518 | Q24: =Table29[[#This Row],[Close Date]]-Table29[[#This Row],[Open Date]] -> 15
B25: 9 | C25: #VALUE! | D25: NASDAQ | E25: USD | F25: 36.5 | G25: 10 | H25: =2.02+2.04 -> 4.06 | I25: =((F25*G25)+H25)/G25 -> 36.906 | J25: =I25*G25 -> 369.06 | K25: {=_FV(C25,"Price")} -> 28.99 | L25: =(N25-I25)*G25 -> -19.06 | M25: =L25/J25 -> -0.051644719 | N25: 35 | O25: 44512 | P25: 44529 | Q25: =Table29[[#This Row],[Close Date]]-Table29[[#This Row],[Open Date]] -> 17
B26: 10 | C26: #VALUE! | D26: NYSE | E26: USD | F26: 55 | G26: 10 | H26: =2.02+2.04 -> 4.06 | I26: =((F26*G26)+H26)/G26 -> 55.406 | J26: =I26*G26 -> 554.06 | K26: {=_FV(C26,"Price")} -> 27.01 | L26: =(N26-I26)*G26 -> -34.06 | M26: =L26/J26 -> -0.061473487 | N26: 52 | O26: 44518 | P26: 44530 | Q26: =Table29[[#This Row],[Close Date]]-Table29[[#This Row],[Open Date]] -> 12
B27: 11 | C27: #VALUE! | D27: NYSE | E27: USD | F27: 54 | G27: 50 | H27: =2.14+2.16 -> 4.3 | I27: =((F27*G27)+H27)/G27 -> 54.086 | J27: =I27*G27 -> 2704.3 | K27: {=_FV(C27,"Price")} -> 27.13 | L27: =(N27-I27)*G27 -> 20.7 | M27: =L27/J27 -> 0.0076544762 | N27: 54.5 | O27: 44524 | P27: 44524 | Q27: =Table29[[#This Row],[Close Date]]-Table29[[#This Row],[Open Date]] -> 0
B28: 12 | C28: #VALUE! | D28: NYSE | E28: USD | F28: 50.8 | G28: 50 | H28: =2.14+2.16 -> 4.3 | I28: =((F28*G28)+H28)/G28 -> 50.886 | J28: =I28*G28 -> 2544.3 | K28: {=_FV(C28,"Price")} -> 27.13 | L28: =(N28-I28)*G28 -> 65.7 | M28: =L28/J28 -> 0.025822427 | N28: 52.2 | O28: 44526 | P28: 44526 | Q28: =Table29[[#This Row],[Close Date]]-Table29[[#This Row],[Open Date]] -> 0
B29: 13 | C29: #VALUE! | D29: NYSE | E29: USD | F29: 295 | G29: 10 | H29: =2.02+2.05 -> 4.07 | I29: =((F29*G29)+H29)/G29 -> 295.407 | J29: =I29*G29 -> 2954.07 | K29: {=_FV(C29,"Price")} -> 116.98 | L29: =(N29-I29)*G29 -> 23.93 | M29: =L29/J29 -> 0.0081006882 | N29: 297.8 | O29: 44526 | P29: 44526 | Q29: =Table29[[#This Row],[Close Date]]-Table29[[#This Row],[Open Date]] -> 0
B30: 14 | C30: #VALUE! | D30: NASDAQ | E30: USD | F30: 170 | G30: 20 | H30: =2.05+2.08 -> 4.13 | I30: =((F30*G30)+H30)/G30 -> 170.2065 | J30: =I30*G30 -> 3404.13 | K30: {=_FV(C30,"Price")} -> 156.5 | L30: =(N30-I30)*G30 -> 1.87 | M30: =L30/J30 -> 0.00054933272 | N30: 170.3 | O30: 44526 | P30: 44526 | Q30: =Table29[[#This Row],[Close Date]]-Table29[[#This Row],[Open Date]] -> 0
B31: 15 | C31: #VALUE! | D31: NYSE | E31: USD | F31: 39.9 | G31: 60 | H31: =2.17+2.19 -> 4.36 | I31: =((F31*G31)+H31)/G31 -> 39.972667 | J31: =I31*G31 -> 2398.36 | K31: {=_FV(C31,"Price")} -> 21.21 | L31: =(N31-I31)*G31 -> 13.64 | M31: =L31/J31 -> 0.0056872196 | N31: 40.2 | O31: 44526 | P31: 44526 | Q31: =Table29[[#This Row],[Close Date]]-Table29[[#This Row],[Open Date]] -> 0
B32: 16 | C32: #VALUE! | D32: NASDAQ | E32: USD | F32: 34.5 | G32: 90 | H32: =2.26+2.29 -> 4.55 | I32: =((F32*G32)+H32)/G32 -> 34.550556 | J32: =I32*G32 -> 3109.55 | K32: {=_FV(C32,"Price")} -> 26.48 | L32: =(N32-I32)*G32 -> 103.45 | M32: =L32/J32 -> 0.033268479 | N32: 35.7 | O32: 44529 | P32: 44529 | Q32: =Table29[[#This Row],[Close Date]]-Table29[[#This Row],[Open Date]] -> 0
B33: 17 | C33: #VALUE! | D33: NASDAQ | E33: USD | F33: 71.5 | G33: 50 | H33: =2.14+2.17 -> 4.31 | I33: =((F33*G33)+H33)/G33 -> 71.5862 | J33: =I33*G33 -> 3579.31 | K33: {=_FV(C33,"Price")} -> 43.67 | L33: =(N33-I33)*G33 -> 18.19 | M33: =L33/J33 -> 0.0050819851 | N33: 71.95 | O33: 44529 | P33: 44529 | Q33: =Table29[[#This Row],[Close Date]]-Table29[[#This Row],[Open Date]] -> 0
B34: 18 | C34: #VALUE! | D34: NASDAQ | E34: USD | F34: 331 | G34: 10 | H34: =2.02+2.05 -> 4.07 | I34: =((F34*G34)+H34)/G34 -> 331.407 | J34: =I34*G34 -> 3314.07 | K34: {=_FV(C34,"Price")} -> 282.19 | L34: =(N34-I34)*G34 -> -36.07 | M34: =L34/J34 -> -0.010883898 | N34: 327.8 | O34: 44529 | P34: 44529 | Q34: =Table29[[#This Row],[Close Date]]-Table29[[#This Row],[Open Date]] -> 0
B35: 19 | C35: #VALUE! | D35: NASDAQ | E35: USD | F35: 33.9 | G35: 100 | H35: =2.29+2.32 -> 4.61 | I35: =((F35*G35)+H35)/G35 -> 33.9461 | J35: =I35*G35 -> 3394.61 | K35: {=_FV(C35,"Price")} -> 26.48 | L35: =(N35-I35)*G35 -> 5.39 | M35: =L35/J35 -> 0.0015878113 | N35: 34 | O35: 44530 | P35: 44530 | Q35: =Table29[[#This Row],[Close Date]]-Table29[[#This Row],[Open Date]] -> 0
B36: 20 | C36: #VALUE! | D36: NYSE | E36: USD | F36: 38.8 | G36: 100 | H36: =2.32+2.29 -> 4.61 | I36: =((F36*G36)+H36)/G36 -> 38.8461 | J36: =I36*G36 -> 3884.61 | K36: {=_FV(C36,"Price")} -> 21.21 | L36: =(N36-I36)*G36 -> 15.39 | M36: =L36/J36 -> 0.0039617877 | N36: 39 | O36: 44530 | P36: 44530 | Q36: =Table29[[#This Row],[Close Date]]-Table29[[#This Row],[Open Date]] -> 0
B37: 21 | C37: #VALUE! | D37: NASDAQ | E37: USD | F37: 35.5 | G37: 120 | H37: =2.35+2.32+2.07 -> 6.74 | I37: =((F37*G37)+H37)/G37 -> 35.556167 | J37: =I37*G37 -> 4266.74 | K37: {=_FV(C37,"Price")} -> 26.48 | L37: =(N37-I37)*G37 -> 45.26 | M37: =L37/J37 -> 0.01060763 | N37: =(35.8*100+36.6*20)/120 -> 35.933333 | O37: 44531 | P37: 44531 | Q37: =Table29[[#This Row],[Close Date]]-Table29[[#This Row],[Open Date]] -> 0
B38: 22 | C38: #VALUE! | D38: NYSE | E38: USD | F38: 8.3 | G38: 400 | H38: =5.16+5.23 -> 10.39 | I38: =((F38*G38)+H38)/G38 -> 8.325975 | J38: =I38*G38 -> 3330.39 | K38: {=_FV(C38,"Price")} -> 3.02 | L38: =(N38-I38)*G38 -> 29.61 | M38: =L38/J38 -> 0.0088908506 | N38: 8.4 | O38: 44532 | P38: 44532 | Q38: =Table29[[#This Row],[Close Date]]-Table29[[#This Row],[Open Date]] -> 0
B39: 23 | C39: #VALUE! | D39: NASDAQ | E39: USD | F39: 28.9 | G39: 150 | H39: =2.14+2.48+2.29 -> 6.91 | I39: =((F39*G39)+H39)/G39 -> 28.946067 | J39: =I39*G39 -> 4341.91 | K39: {=_FV(C39,"Price")} -> 23.45 | L39: =(N39-I39)*G39 -> 12.59 | M39: =L39/J39 -> 0.0028996455 | N39: 29.03 | O39: 44532 | P39: 44532 | Q39: =Table29[[#This Row],[Close Date]]-Table29[[#This Row],[Open Date]] -> 0
B40: 24 | C40: #VALUE! | D40: NYSE | E40: USD | F40: 6.85 | G40: 670 | H40: =8.64+3.52+5.22 -> 17.38 | I40: =((F40*G40)+H40)/G40 -> 6.8759403 | J40: =I40*G40 -> 4606.88 | K40: {=_FV(C40,"Price")} -> 5.22 | L40: =(N40-I40)*G40 -> 15.72 | M40: =L40/J40 -> 0.0034122877 | N40: =(6.872*400+6.94*270)/670 -> 6.899403 | O40: 44532 | P40: 44532 | Q40: =Table29[[#This Row],[Close Date]]-Table29[[#This Row],[Open Date]] -> 0
B41: 25 | C41: #VALUE! | D41: NASDAQ | E41: USD | F41: 31.8 | G41: 100 | H41: =2.29+2.32 -> 4.61 | I41: =((F41*G41)+H41)/G41 -> 31.8461 | J41: =I41*G41 -> 3184.61 | K41: {=_FV(C41,"Price")} -> 26.48 | L41: =(N41-I41)*G41 -> 65.39 | M41: =L41/J41 -> 0.020533127 | N41: 32.5 | O41: 44533 | P41: 44533 | Q41: =Table29[[#This Row],[Close Date]]-Table29[[#This Row],[Open Date]] -> 0
B42: 26 | C42: #VALUE! | D42: NASDAQ | E42: USD | F42: 54.5 | G42: 80 | H42: =2.23+2.26 -> 4.49 | I42: =((F42*G42)+H42)/G42 -> 54.556125 | J42: =I42*G42 -> 4364.49 | K42: {=_FV(C42,"Price")} -> 43.67 | L42: =(N42-I42)*G42 -> 19.51 | M42: =L42/J42 -> 0.0044701672 | N42: 54.8 | O42: 44533 | P42: 44533 | Q42: =Table29[[#This Row],[Close Date]]-Table29[[#This Row],[Open Date]] -> 0
B43: 27 | C43: #VALUE! | D43: NYSE | E43: USD | F43: 6.1 | G43: 700 | H43: =9.13+9.03 -> 18.16 | I43: =((F43*G43)+H43)/G43 -> 6.1259429 | J43: =I43*G43 -> 4288.16 | K43: {=_FV(C43,"Price")} -> 5.22 | L43: =(N43-I43)*G43 -> 23.84 | M43: =L43/J43 -> 0.005559494 | N43: 6.16 | O43: 44533 | P43: 44533 | Q43: =Table29[[#This Row],[Close Date]]-Table29[[#This Row],[Open Date]] -> 0
B44: 28 | C44: #VALUE! | D44: NASDAQ | E44: USD | F44: =(150*30.18+28.9*8)/158 -> 30.11519 | G44: 158 | H44: =2.44+2.01+2.5 -> 6.95 | I44: =((F44*G44)+H44)/G44 -> 30.159177 | J44: =I44*G44 -> 4765.15 | K44: {=_FV(C44,"Price")} -> 26.48 | L44: =(N44-I44)*G44 -> -341.15 | M44: =L44/J44 -> -0.07159271 | N44: 28 | O44: 44533 | P44: 44536 | Q44: =Table29[[#This Row],[Close Date]]-Table29[[#This Row],[Open Date]] -> 3
B45: 29 | C45: #VALUE! | D45: NYSE | E45: USD | F45: 18.5 | G45: 200 | H45: =2.59+2.63 -> 5.22 | I45: =((F45*G45)+H45)/G45 -> 18.5261 | J45: =I45*G45 -> 3705.22 | K45: {=_FV(C45,"Price")} -> 12.31 | L45: =(N45-I45)*G45 -> 54.78 | M45: =L45/J45 -> 0.014784547 | N45: 18.8 | O45: 44536 | P45: 44536 | Q45: =Table29[[#This Row],[Close Date]]-Table29[[#This Row],[Open Date]] -> 0
B46: 30 | C46: #VALUE! | D46: NYSE | E46: USD | F46: 20 | G46: 220 | H46: =2.84+2.63+2.07+0.35 -> 7.89 | I46: =((F46*G46)+H46)/G46 -> 20.035864 | J46: =I46*G46 -> 4407.89 | K46: {=_FV(C46,"Price")} -> 12.31 | L46: =(N46-I46)*G46 -> -147.89 | M46: =L46/J46 -> -0.0335512 | N46: =(19.3*200+20*20)/220 -> 19.363636 | O46: 44536 | P46: 44537 | Q46: =Table29[[#This Row],[Close Date]]-Table29[[#This Row],[Open Date]] -> 1
B47: 31 | C47: #VALUE! | D47: NYSE | E47: USD | F47: 22.15 | G47: 190 | H47: =2.56+2.13+2.48+0.47 -> 7.64 | I47: =((F47*G47)+H47)/G47 -> 22.190211 | J47: =I47*G47 -> 4216.14 | K47: {=_FV(C47,"Price")} -> 12.31 | L47: =(N47-I47)*G47 -> -331.14 | M47: =L47/J47 -> -0.078541035 | N47: =(20.3*150+21*40)/190 -> 20.447368 | O47: 44538 | P47: 44538 | Q47: =Table29[[#This Row],[Close Date]]-Table29[[#This Row],[Open Date]] -> 0
B48: 32 | C48: #VALUE! | D48: NASDAQ | E48: USD | F48: 65 | G48: 60 | H48: =2.17+2.2 -> 4.37 | I48: =((F48*G48)+H48)/G48 -> 65.072833 | J48: =I48*G48 -> 3904.37 | K48: {=_FV(C48,"Price")} -> 43.67 | L48: =(N48-I48)*G48 -> -76.37 | M48: =L48/J48 -> -0.019560134 | N48: 63.8 | O48: 44539 | P48: 44539 | Q48: =Table29[[#This Row],[Close Date]]-Table29[[#This Row],[Open Date]] -> 0
B49: 33 | C49: #VALUE! | D49: NASDAQ | E49: USD | F49: 79.7 | G49: 46 | H49: =2.13+2.16 -> 4.29 | I49: =((F49*G49)+H49)/G49 -> 79.793261 | J49: =I49*G49 -> 3670.49 | K49: {=_FV(C49,"Price")} -> 59.77 | L49: =(N49-I49)*G49 -> 9.51 | M49: =L49/J49 -> 0.0025909347 | N49: 80 | O49: 44539 | P49: 44539 | Q49: =Table29[[#This Row],[Close Date]]-Table29[[#This Row],[Open Date]] -> 0
B50: 34 | C50: #VALUE! | D50: NYSE | E50: USD | F50: 52.5 | G50: 60 | H50: =2.13+2.16 -> 4.29 | I50: =((F50*G50)+H50)/G50 -> 52.5715 | J50: =I50*G50 -> 3154.29 | K50: {=_FV(C50,"Price")} -> 48.8 | L50: =(N50-I50)*G50 -> 25.71 | M50: =L50/J50 -> 0.0081508041 | N50: 53 | O50: 44540 | P50: 44540 | Q50: =Table29[[#This Row],[Close Date]]-Table29[[#This Row],[Open Date]] -> 0
B51: 35 | C51: #VALUE! | D51: NASDAQ | E51: USD | F51: 39.8 | G51: 85 | H51: =2.13+2.16 -> 4.29 | I51: =((F51*G51)+H51)/G51 -> 39.850471 | J51: =I51*G51 -> 3387.29 | K51: {=_FV(C51,"Price")} -> 28.07 | L51: =(N51-I51)*G51 -> 38.21 | M51: =L51/J51 -> 0.011280404 | N51: 40.3 | O51: 44540 | P51: 44540 | Q51: =Table29[[#This Row],[Close Date]]-Table29[[#This Row],[Open Date]] -> 0
B52: 36 | C52: #VALUE! | D52: NASDAQ | E52: USD | F52: 57.9 | G52: 78 | H52: =2.13+2.16 -> 4.29 | I52: =((F52*G52)+H52)/G52 -> 57.955 | J52: =I52*G52 -> 4520.49 | K52: {=_FV(C52,"Price")} -> 80.01 | L52: =(N52-I52)*G52 -> 19.11 | M52: =L52/J52 -> 0.0042274178 | N52: 58.2 | O52: 44540 | P52: 44540 | Q52: =Table29[[#This Row],[Close Date]]-Table29[[#This Row],[Open Date]] -> 0
B53: 37 | C53: #VALUE! | D53: NASDAQ | E53: USD | F53: 294 | G53: 15 | H53: =2.13+2.16+0.35*2 -> 4.99 | I53: =((F53*G53)+H53)/G53 -> 294.33267 | J53: =I53*G53 -> 4414.99 | K53: {=_FV(C53,"Price")} -> 282.19 | L53: =(N53-I53)*G53 -> -124.99 | M53: =L53/J53 -> -0.02831037 | N53: 286 | O53: 44543 | P53: 44545 | Q53: =Table29[[#This Row],[Close Date]]-Table29[[#This Row],[Open Date]] -> 2
B54: 38 | C54: #VALUE! | D54: NASDAQ | E54: USD | F54: 284 | G54: 14 | H54: =2.13+2.16 -> 4.29 | I54: =((F54*G54)+H54)/G54 -> 284.30643 | J54: =I54*G54 -> 3980.29 | K54: {=_FV(C54,"Price")} -> 282.19 | L54: =(N54-I54)*G54 -> 37.71 | M54: =L54/J54 -> 0.009474184 | N54: 287 | O54: 44545 | P54: 44545 | Q54: =Table29[[#This Row],[Close Date]]-Table29[[#This Row],[Open Date]] -> 0
B55: 39 | C55: #VALUE! | D55: NYSE | E55: USD | F55: 5.5 | G55: 200 | H55: =2.59+2.62 -> 5.21 | I55: =((F55*G55)+H55)/G55 -> 5.52605 | J55: =I55*G55 -> 1105.21 | K55: {=_FV(C55,"Price")} -> 6 | L55: =(N55-I55)*G55 -> 4.79 | M55: =L55/J55 -> 0.004334018 | N55: 5.55 | O55: 44545 | P55: 44545 | Q55: =Table29[[#This Row],[Close Date]]-Table29[[#This Row],[Open Date]] -> 0
B56: 40 | C56: #VALUE! | D56: NASDAQ | E56: USD | F56: 324.88 | G56: 28 | H56: =2.07+2.13 -> 4.2 | I56: =((F56*G56)+H56)/G56 -> 325.03 | J56: =I56*G56 -> 9100.84 | K56: {=_FV(C56,"Price")} -> 223.59 | L56: =(N56-I56)*G56 -> 4.76 | M56: =L56/J56 -> 0.00052302864 | N56: 325.2 | O56: 44550 | P56: 44550 | Q56: =Table29[[#This Row],[Close Date]]-Table29[[#This Row],[Open Date]] -> 0
B57: 41 | C57: #VALUE! | D57: NASDAQ | E57: USD | F57: 5.17 | G57: 300 | H57: =6.52+3.87+2.07 -> 12.46 | I57: =((F57*G57)+H57)/G57 -> 5.2115333 | J57: =I57*G57 -> 1563.46 | K57: {=_FV(C57,"Price")} -> 4.72 | L57: =(N57-I57)*G57 -> -78.46 | M57: =L57/J57 -> -0.050183567 | N57: 4.95 | O57: 44551 | P57: 44551 | Q57: =Table29[[#This Row],[Close Date]]-Table29[[#This Row],[Open Date]] -> 0
B58: 42 | C58: #VALUE! | D58: NASDAQ | E58: USD | F58: 4.9 | G58: 220 | H58: =2.84+0.63 -> 3.47 | I58: =((F58*G58)+H58)/G58 -> 4.9157727 | J58: =I58*G58 -> 1081.47 | K58: {=_FV(C58,"Price")} -> 4.72 | L58: =(N58-I58)*G58 -> 7.53 | M58: =L58/J58 -> 0.0069627452 | N58: 4.95 | O58: 44551 | P58: 44553 | Q58: =Table29[[#This Row],[Close Date]]-Table29[[#This Row],[Open Date]] -> 2
B59: 43 | C59: #VALUE! | D59: NASDAQ | E59: USD | F59: 92.7 | G59: 80 | H59: =2.07+2.23+1.43 -> 5.73 | I59: =((F59*G59)+H59)/G59 -> 92.771625 | J59: =I59*G59 -> 7421.73 | K59: {=_FV(C59,"Price")} -> 79.86 | L59: =(N59-I59)*G59 -> 18.27 | M59: =L59/J59 -> 0.0024616902 | N59: 93 | O59: 44553 | P59: 44558 | Q59: =Table29[[#This Row],[Close Date]]-Table29[[#This Row],[Open Date]] -> 5
B60: 44 | C60: #VALUE! | D60: NASDAQ | E60: USD | F60: 41 | G60: 50 | H60: =2.14+2.16+1.15 -> 5.45 | I60: =((F60*G60)+H60)/G60 -> 41.109 | J60: =I60*G60 -> 2055.45 | K60: {=_FV(C60,"Price")} -> 33.8 | L60: =(N60-I60)*G60 -> 19.55 | M60: =L60/J60 -> 0.0095112992 | N60: 41.5 | O60: 44558 | P60: 44560 | Q60: =Table29[[#This Row],[Close Date]]-Table29[[#This Row],[Open Date]] -> 2
B61: 45 | C61: #VALUE! | D61: NYSE | E61: USD | F61: 5.4 | G61: 200 | H61: =2.59+2.62 -> 5.21 | I61: =((F61*G61)+H61)/G61 -> 5.42605 | J61: =I61*G61 -> 1085.21 | K61: {=_FV(C61,"Price")} -> 6 | L61: =(N61-I61)*G61 -> 14.79 | M61: =L61/J61 -> 0.013628699 | N61: 5.5 | O61: 44559 | P61: 44560 | Q61: =Table29[[#This Row],[Close Date]]-Table29[[#This Row],[Open Date]] -> 1
B62: 46 | C62: #VALUE! | D62: NYSE | E62: USD | F62: 6.65 | G62: 680 | H62: =8.87+8.77+0.26+0.44 -> 18.34 | I62: =((F62*G62)+H62)/G62 -> 6.6769706 | J62: =I62*G62 -> 4540.34 | K62: {=_FV(C62,"Price")} -> 5.22 | L62: =(N62-I62)*G62 -> 29.26 | M62: =L62/J62 -> 0.0064444513 | N62: 6.72 | O62: 44560 | P62: 44561 | Q62: =Table29[[#This Row],[Close Date]]-Table29[[#This Row],[Open Date]] -> 1
B63: 47 | C63: #VALUE! | D63: NYSE | E63: USD | F63: 50.4 | G63: 80 | H63: =2.23+2.26 -> 4.49 | I63: =((F63*G63)+H63)/G63 -> 50.456125 | J63: =I63*G63 -> 4036.49 | K63: {=_FV(C63,"Price")} -> 27.13 | L63: =(N63-I63)*G63 -> 43.51 | M63: =L63/J63 -> 0.010779167 | N63: 51 | O63: 44561 | P63: 44561 | Q63: =Table29[[#This Row],[Close Date]]-Table29[[#This Row],[Open Date]] -> 0
B64: 48 | C64: #VALUE! | D64: NYSE | E64: USD | F64: 43.8 | G64: 80 | H64: =2.23+2.26 -> 4.49 | I64: =((F64*G64)+H64)/G64 -> 43.856125 | J64: =I64*G64 -> 3508.49 | K64: {=_FV(C64,"Price")} -> 27.01 | L64: =(N64-I64)*G64 -> 11.51 | M64: =L64/J64 -> 0.0032806136 | N64: 44 | O64: 44561 | P64: 44561 | Q64: =Table29[[#This Row],[Close Date]]-Table29[[#This Row],[Open Date]] -> 0
B65: 49 | C65: #VALUE! | D65: NYSE | E65: USD | F65: 6 | G65: 600 | H65: 16.35 | I65: =((F65*G65)+H65)/G65 -> 6.02725 | J65: =I65*G65 -> 3616.35 | K65: {=_FV(C65,"Price")} -> 6 | L65: =(N65-I65)*G65 -> -190.35 | M65: =L65/J65 -> -0.052635945 | N65: 5.71 | O65: 44546 | P65: 44564 | Q65: =Table29[[#This Row],[Close Date]]-Table29[[#This Row],[Open Date]] -> 18
B66: 50 | C66: #VALUE! | D66: NYSE | E66: USD | F66: 51.5 | G66: 150 | H66: =2.44+2.5 -> 4.94 | I66: =((F66*G66)+H66)/G66 -> 51.532933 | J66: =I66*G66 -> 7729.94 | K66: {=_FV(C66,"Price")} -> 27.13 | L66: =(N66-I66)*G66 -> -349.94 | M66: =L66/J66 -> -0.045270727 | N66: 49.2 | O66: 44564 | P66: 44564 | Q66: =Table29[[#This Row],[Close Date]]-Table29[[#This Row],[Open Date]] -> 0
B67: 51 | C67: #VALUE! | D67: NYSE | E67: USD | F67: 41.5 | G67: 200 | H67: =2.59+2.65 -> 5.24 | I67: =((F67*G67)+H67)/G67 -> 41.5262 | J67: =I67*G67 -> 8305.24 | K67: {=_FV(C67,"Price")} -> 33.8 | L67: =(N67-I67)*G67 -> 114.76 | M67: =L67/J67 -> 0.013817783 | N67: 42.1 | O67: 44564 | P67: 44564 | Q67: =Table29[[#This Row],[Close Date]]-Table29[[#This Row],[Open Date]] -> 0
B68: 52 | C68: #VALUE! | D68: NYSE | E68: USD | F68: 48.8 | G68: 150 | H68: =2.44+2.5 -> 4.94 | I68: =((F68*G68)+H68)/G68 -> 48.832933 | J68: =I68*G68 -> 7324.94 | K68: {=_FV(C68,"Price")} -> 27.13 | L68: =(N68-I68)*G68 -> 55.06 | M68: =L68/J68 -> 0.0075167851 | N68: 49.2 | O68: 44564 | P68: 44564 | Q68: =Table29[[#This Row],[Close Date]]-Table29[[#This Row],[Open Date]] -> 0
B69: 53 | C69: #VALUE! | D69: NYSE | E69: USD | F69: 101 | G69: 74 | H69: =2.26+2.21 -> 4.47 | I69: =((F69*G69)+H69)/G69 -> 101.06041 | J69: =I69*G69 -> 7478.47 | K69: {=_FV(C69,"Price")} -> 93.82 | L69: =(N69-I69)*G69 -> 19.95 | M69: =L69/J69 -> 0.002667658 | N69: 101.33 | O69: 44564 | P69: 44564 | Q69: =Table29[[#This Row],[Close Date]]-Table29[[#This Row],[Open Date]] -> 0
B70: 54 | C70: #VALUE! | D70: NYSE | E70: USD | F70: 56.9 | G70: 130 | H70: =2.44+2.38 -> 4.82 | I70: =((F70*G70)+H70)/G70 -> 56.937077 | J70: =I70*G70 -> 7401.82 | K70: {=_FV(C70,"Price")} -> 43.67 | L70: =(N70-I70)*G70 -> 8.18 | M70: =L70/J70 -> 0.0011051336 | N70: 57 | O70: 44564 | P70: 44564 | Q70: =Table29[[#This Row],[Close Date]]-Table29[[#This Row],[Open Date]] -> 0
B71: 55 | C71: #VALUE! | D71: NYSE | E71: USD | F71: 42.3 | G71: 300 | H71: =3.87+3.97 -> 7.84 | I71: =((F71*G71)+H71)/G71 -> 42.326133 | J71: =I71*G71 -> 12697.84 | K71: {=_FV(C71,"Price")} -> 33.8 | L71: =(N71-I71)*G71 -> 4.16 | M71: =L71/J71 -> 0.00032761478 | N71: 42.34 | O71: 44564 | P71: 44564 | Q71: =Table29[[#This Row],[Close Date]]-Table29[[#This Row],[Open Date]] -> 0
B72: 56 | C72: #VALUE! | D72: NYSE | E72: USD | F72: 5.2 | G72: 200 | H72: =2.59+2.62 -> 5.21 | I72: =((F72*G72)+H72)/G72 -> 5.22605 | J72: =I72*G72 -> 1045.21 | K72: {=_FV(C72,"Price")} -> 6 | L72: =(N72-I72)*G72 -> -21.21 | M72: =L72/J72 -> -0.020292573 | N72: 5.12 | O72: 44565 | P72: 44565 | Q72: =Table29[[#This Row],[Close Date]]-Table29[[#This Row],[Open Date]] -> 0
B73: 57 | C73: #VALUE! | D73: NYSE | E73: USD | F73: =(38.5*30+38.4*20)/50 -> 38.46 | G73: 50 | H73: =2.08+2.05+2.16 -> 6.29 | I73: =((F73*G73)+H73)/G73 -> 38.5858 | J73: =I73*G73 -> 1929.29 | K73: {=_FV(C73,"Price")} -> 33.8 | L73: =(N73-I73)*G73 -> 5.71 | M73: =L73/J73 -> 0.002959638 | N73: 38.7 | O73: 44565 | P73: 44565 | Q73: =Table29[[#This Row],[Close Date]]-Table29[[#This Row],[Open Date]] -> 0
B74: 58 | C74: #VALUE! | D74: NYSE | E74: USD | F74: 39.8 | G74: 100 | H74: =2.29 -> 2.29 | I74: =((F74*G74)+H74)/G74 -> 39.8229 | J74: =I74*G74 -> 3982.29 | K74: {=_FV(C74,"Price")} -> 33.8 | L74: =(N74-I74)*G74 -> -22.29 | M74: =L74/J74 -> -0.005597282 | N74: 39.6 | O74: 44565 | P74: 44567 | Q74: =Table29[[#This Row],[Close Date]]-Table29[[#This Row],[Open Date]] -> 2
B75: 59 | C75: #VALUE! | D75: NYSE | E75: USD | F75: =(51.8*50+50.2*50)/100 -> 51 | G75: 100 | H75: =2.14+2.14+2.33 -> 6.61 | I75: =((F75*G75)+H75)/G75 -> 51.0661 | J75: =I75*G75 -> 5106.61 | K75: {=_FV(C75,"Price")} -> 43.67 | L75: =(N75-I75)*G75 -> 35.39 | M75: =L75/J75 -> 0.0069302336 | N75: 51.42 | O75: 44565 | P75: 44566 | Q75: =Table29[[#This Row],[Close Date]]-Table29[[#This Row],[Open Date]] -> 1
B76: 60 | C76: #VALUE! | D76: NYSE | E76: USD | F76: 64.99 | G76: 112 | H76: =2.33+2.38 -> 4.71 | I76: =((F76*G76)+H76)/G76 -> 65.032054 | J76: =I76*G76 -> 7283.59 | K76: {=_FV(C76,"Price")} -> 59.77 | L76: =(N76-I76)*G76 -> -93.19 | M76: =L76/J76 -> -0.012794515 | N76: 64.2 | O76: 44566 | P76: 44566 | Q76: =Table29[[#This Row],[Close Date]]-Table29[[#This Row],[Open Date]] -> 0
B77: 61 | C77: #VALUE! | D77: NYSE | E77: USD | F77: 64.6 | G77: 108 | H77: =2.36+2.31 -> 4.67 | I77: =((F77*G77)+H77)/G77 -> 64.643241 | J77: =I77*G77 -> 6981.47 | K77: {=_FV(C77,"Price")} -> 59.77 | L77: =(N77-I77)*G77 -> 11.53 | M77: =L77/J77 -> 0.0016515147 | N77: 64.75 | O77: 44566 | P77: 44566 | Q77: =Table29[[#This Row],[Close Date]]-Table29[[#This Row],[Open Date]] -> 0
B78: 62 | C78: #VALUE! | D78: NYSE | E78: USD | F78: 64.5 | G78: 84 | H78: =2.24+2.28 -> 4.52 | I78: =((F78*G78)+H78)/G78 -> 64.55381 | J78: =I78*G78 -> 5422.52 | K78: {=_FV(C78,"Price")} -> 59.77 | L78: =(N78-I78)*G78 -> 20.68 | M78: =L78/J78 -> 0.003813725 | N78: 64.8 | O78: 44566 | P78: 44566 | Q78: =Table29[[#This Row],[Close Date]]-Table29[[#This Row],[Open Date]] -> 0
B79: 63 | C79: #VALUE! | D79: NYSE | E79: USD | F79: 37.8 | G79: 50 | H79: =2.14+2.16 -> 4.3 | I79: =((F79*G79)+H79)/G79 -> 37.886 | J79: =I79*G79 -> 1894.3 | K79: {=_FV(C79,"Price")} -> 33.8 | L79: =(N79-I79)*G79 -> 5.7 | M79: =L79/J79 -> 0.0030090271 | N79: 38 | O79: 44566 | P79: 44566 | Q79: =Table29[[#This Row],[Close Date]]-Table29[[#This Row],[Open Date]] -> 0
B80: 64 | C80: #VALUE! | D80: NYSE | E80: USD | F80: 65.1 | G80: 108 | H80: =2.31+2.36 -> 4.67 | I80: =((F80*G80)+H80)/G80 -> 65.143241 | J80: =I80*G80 -> 7035.47 | K80: {=_FV(C80,"Price")} -> 59.77 | L80: =(N80-I80)*G80 -> 18.01 | M80: =L80/J80 -> 0.0025598858 | N80: 65.31 | O80: 44566 | P80: 44566 | Q80: =Table29[[#This Row],[Close Date]]-Table29[[#This Row],[Open Date]] -> 0
B81: 65 | C81: #VALUE! | D81: NYSE | E81: USD | F81: 211.42 | G81: 5 | H81: =2.01+2.03 -> 4.04 | I81: =((F81*G81)+H81)/G81 -> 212.228 | J81: =I81*G81 -> 1061.14 | K81: {=_FV(C81,"Price")} -> 147.45 | L81: =(N81-I81)*G81 -> -302.64 | M81: =L81/J81 -> -0.28520271 | N81: 151.7 | O81: 44315 | P81: 44567 | Q81: =Table29[[#This Row],[Close Date]]-Table29[[#This Row],[Open Date]] -> 252
B82: 66 | C82: #VALUE! | D82: NYSE | E82: USD | F82: 29.9 | G82: 200 | H82: =2.59+2.64 -> 5.23 | I82: =((F82*G82)+H82)/G82 -> 29.92615 | J82: =I82*G82 -> 5985.23 | K82: {=_FV(C82,"Price")} -> 21.21 | L82: =(N82-I82)*G82 -> 14.77 | M82: =L82/J82 -> 0.0024677414 | N82: 30 | O82: 44567 | P82: 44567 | Q82: =Table29[[#This Row],[Close Date]]-Table29[[#This Row],[Open Date]] -> 0
B83: 67 | C83: #VALUE! | D83: NYSE | E83: USD | F83: 29.8 | G83: 24 | H83: =2.08+2.06 -> 4.14 | I83: =((F83*G83)+H83)/G83 -> 29.9725 | J83: =I83*G83 -> 719.34 | K83: {=_FV(C83,"Price")} -> 21.21 | L83: =(N83-I83)*G83 -> 2.82 | M83: =L83/J83 -> 0.0039202602 | N83: 30.09 | O83: 44567 | P83: 44567 | Q83: =Table29[[#This Row],[Close Date]]-Table29[[#This Row],[Open Date]] -> 0
B84: 68 | C84: #VALUE! | D84: NYSE | E84: USD | F84: 29.895 | G84: 200 | H84: =2.64+2.59 -> 5.23 | I84: =((F84*G84)+H84)/G84 -> 29.92115 | J84: =I84*G84 -> 5984.23 | K84: {=_FV(C84,"Price")} -> 21.21 | L84: =(N84-I84)*G84 -> 15.77 | M84: =L84/J84 -> 0.0026352597 | N84: 30 | O84: 44567 | P84: 44567 | Q84: =Table29[[#This Row],[Close Date]]-Table29[[#This Row],[Open Date]] -> 0
B85: 69 | C85: #VALUE! | D85: NYSE | E85: USD | F85: 276.89 | G85: 30 | H85: =2.08+2.13 -> 4.21 | I85: =((F85*G85)+H85)/G85 -> 277.03033 | J85: =I85*G85 -> 8310.91 | K85: {=_FV(C85,"Price")} -> 282.19 | L85: =(N85-I85)*G85 -> 15.89 | M85: =L85/J85 -> 0.0019119447 | N85: 277.56 | O85: 44567 | P85: 44567 | Q85: =Table29[[#This Row],[Close Date]]-Table29[[#This Row],[Open Date]] -> 0
B86: 70 | C86: #VALUE! | D86: NYSE | E86: USD | F86: 37.5 | G86: 50 | H86: =2.14+2.16 -> 4.3 | I86: =((F86*G86)+H86)/G86 -> 37.586 | J86: =I86*G86 -> 1879.3 | K86: {=_FV(C86,"Price")} -> 33.8 | L86: =(N86-I86)*G86 -> 0.7 | M86: =L86/J86 -> 0.00037247911 | N86: 37.6 | O86: 44567 | P86: 44567 | Q86: =Table29[[#This Row],[Close Date]]-Table29[[#This Row],[Open Date]] -> 0
B87: 71 | C87: #VALUE! | D87: NYSE | E87: USD | F87: 66.7 | G87: 100 | H87: =2.32+2.16 -> 4.48 | I87: =((F87*G87)+H87)/G87 -> 66.7448 | J87: =I87*G87 -> 6674.48 | K87: {=_FV(C87,"Price")} -> 59.77 | L87: =(N87-I87)*G87 -> -124.48 | M87: =L87/J87 -> -0.018650142 | N87: 65.5 | O87: 44567 | P87: 44567 | Q87: =Table29[[#This Row],[Close Date]]-Table29[[#This Row],[Open Date]] -> 0
B88: 72 | C88: #VALUE! | D88: NYSE | E88: USD | F88: 67.2 | G88: 161 | H88: =2.47+2.17+2.05+2.33 -> 9.02 | I88: =((F88*G88)+H88)/G88 -> 67.256025 | J88: =I88*G88 -> 10828.22 | K88: {=_FV(C88,"Price")} -> 59.77 | L88: =(N88-I88)*G88 -> 25.18 | M88: =L88/J88 -> 0.0023254053 | N88: =(67.2*100+67.6*12+67.8*49)/161 -> 67.412422 | O88: 44567 | P88: 44567 | Q88: =Table29[[#This Row],[Close Date]]-Table29[[#This Row],[Open Date]] -> 0
B89: 73 | C89: #VALUE! | D89: NYSE | E89: USD | F89: 47 | G89: 15 | H89: =2.04+2.06 -> 4.1 | I89: =((F89*G89)+H89)/G89 -> 47.273333 | J89: =I89*G89 -> 709.1 | K89: {=_FV(C89,"Price")} -> 26.45 | L89: =(N89-I89)*G89 -> -220.4 | M89: =L89/J89 -> -0.31081653 | N89: 32.58 | O89: 44496 | P89: 44568 | Q89: =Table29[[#This Row],[Close Date]]-Table29[[#This Row],[Open Date]] -> 72
B90: 74 | C90: #VALUE! | D90: NYSE | E90: USD | F90: 243 | G90: 4 | H90: =2+2.02 -> 4.02 | I90: =((F90*G90)+H90)/G90 -> 244.005 | J90: =I90*G90 -> 976.02 | K90: {=_FV(C90,"Price")} -> 116.17 | L90: =(N90-I90)*G90 -> -212.52 | M90: =L90/J90 -> -0.21774144 | N90: 190.875 | O90: 44490 | P90: 44568 | Q90: =Table29[[#This Row],[Close Date]]-Table29[[#This Row],[Open Date]] -> 78
B91: 75 | C91: #VALUE! | D91: NYSE | E91: USD | F91: 64.1 | G91: 16 | H91: =2.04+2.06 -> 4.1 | I91: =((F91*G91)+H91)/G91 -> 64.35625 | J91: =I91*G91 -> 1029.7 | K91: {=_FV(C91,"Price")} -> 80.01 | L91: =(N91-I91)*G91 -> -1.7 | M91: =L91/J91 -> -0.0016509663 | N91: 64.25 | O91: 44568 | P91: 44568 | Q91: =Table29[[#This Row],[Close Date]]-Table29[[#This Row],[Open Date]] -> 0
B92: 76 | C92: #VALUE! | D92: NYSE | E92: USD | F92: 282 | G92: 40 | H92: =2.18+2.11 -> 4.29 | I92: =((F92*G92)+H92)/G92 -> 282.10725 | J92: =I92*G92 -> 11284.29 | K92: {=_FV(C92,"Price")} -> 282.19 | L92: =(N92-I92)*G92 -> 35.71 | M92: =L92/J92 -> 0.0031645766 | N92: 283 | O92: 44568 | P92: 44568 | Q92: =Table29[[#This Row],[Close Date]]-Table29[[#This Row],[Open Date]] -> 0
B93: 77 | C93: #VALUE! | D93: NYSE | E93: USD | F93: 201.8 | G93: 73 | H93: =2.21+2.3 -> 4.51 | I93: =((F93*G93)+H93)/G93 -> 201.86178 | J93: =I93*G93 -> 14735.91 | K93: {=_FV(C93,"Price")} -> 194.92 | L93: =(N93-I93)*G93 -> 52.43 | M93: =L93/J93 -> 0.003557975 | N93: 202.58 | O93: 44568 | P93: 44568 | Q93: =Table29[[#This Row],[Close Date]]-Table29[[#This Row],[Open Date]] -> 0
B94: 78 | C94: #VALUE! | D94: NYSE | E94: USD | F94: 53.895 | G94: 200 | H94: =2.59+2.66 -> 5.25 | I94: =((F94*G94)+H94)/G94 -> 53.92125 | J94: =I94*G94 -> 10784.25 | K94: {=_FV(C94,"Price")} -> 43.67 | L94: =(N94-I94)*G94 -> -184.25 | M94: =L94/J94 -> -0.017085101 | N94: 53 | O94: 44568 | P94: 44568 | Q94: =Table29[[#This Row],[Close Date]]-Table29[[#This Row],[Open Date]] -> 0
B95: 79 | C95: #VALUE! | D95: NYSE | E95: USD | F95: 200.78 | G95: 72 | H95: =2.21+2.29 -> 4.5 | I95: =((F95*G95)+H95)/G95 -> 200.8425 | J95: =I95*G95 -> 14460.66 | K95: {=_FV(C95,"Price")} -> 194.92 | L95: =(N95-I95)*G95 -> 8.82 | M95: =L95/J95 -> 0.00060993067 | N95: 200.965 | O95: 44568 | P95: 44568 | Q95: =Table29[[#This Row],[Close Date]]-Table29[[#This Row],[Open Date]] -> 0
B96: 80 | C96: #VALUE! | D96: NYSE | E96: USD | F96: 56.2 | G96: 214 | H96: =2.85+2.21 -> 5.06 | I96: =((F96*G96)+H96)/G96 -> 56.223645 | J96: =I96*G96 -> 12031.86 | K96: {=_FV(C96,"Price")} -> 43.67 | L96: =(N96-I96)*G96 -> 16.34 | M96: =L96/J96 -> 0.001358061 | N96: 56.3 | O96: 44568 | P96: 44568 | Q96: =Table29[[#This Row],[Close Date]]-Table29[[#This Row],[Open Date]] -> 0
B97: 81 | C97: #VALUE! | D97: NYSE | E97: USD | F97: 132.8 | G97: 90 | H97: =2.26+2.33 -> 4.59 | I97: =((F97*G97)+H97)/G97 -> 132.851 | J97: =I97*G97 -> 11956.59 | K97: {=_FV(C97,"Price")} -> 115.09 | L97: =(N97-I97)*G97 -> 13.41 | M97: =L97/J97 -> 0.0011215572 | N97: 133 | O97: 44568 | P97: 44568 | Q97: =Table29[[#This Row],[Close Date]]-Table29[[#This Row],[Open Date]] -> 0
B98: 82 | C98: #VALUE! | D98: NYSE | E98: USD | F98: 56 | G98: 215 | H98: =2.87+2.78 -> 5.65 | I98: =((F98*G98)+H98)/G98 -> 56.026279 | J98: =I98*G98 -> 12045.65 | K98: {=_FV(C98,"Price")} -> 43.67 | L98: =(N98-I98)*G98 -> -48.65 | M98: =L98/J98 -> -0.0040388024 | N98: 55.8 | O98: 44568 | P98: 44568 | Q98: =Table29[[#This Row],[Close Date]]-Table29[[#This Row],[Open Date]] -> 0
B99: 83 | C99: #VALUE! | D99: NYSE | E99: USD | F99: 99.73 | G99: 122 | H99: =2.36+2.43 -> 4.79 | I99: =((F99*G99)+H99)/G99 -> 99.769262 | J99: =I99*G99 -> 12171.85 | K99: {=_FV(C99,"Price")} -> 93.82 | L99: =(N99-I99)*G99 -> -102.39 | M99: =L99/J99 -> -0.0084120327 | N99: 98.93 | O99: 44568 | P99: 44568 | Q99: =Table29[[#This Row],[Close Date]]-Table29[[#This Row],[Open Date]] -> 0
B100: 84 | C100: #VALUE! | D100: NYSE | E100: USD | F100: 57.35 | G100: 211 | H100: =2.81 -> 2.81 | I100: =((F100*G100)+H100)/G100 -> 57.363318 | J100: =I100*G100 -> 12103.66 | K100: {=_FV(C100,"Price")} -> 43.67 | L100: =(N100-I100)*G100 -> -224.36 | M100: =L100/J100 -> -0.018536542 | N100: 56.3 | O100: 44568 | P100: 44571 | Q100: =Table29[[#This Row],[Close Date]]-Table29[[#This Row],[Open Date]] -> 3
B101: 85 | C101: #VALUE! | D101: NYSE | E101: USD | F101: 130.8 | G101: 105 | H101: =2.39+2.31 -> 4.7 | I101: =((F101*G101)+H101)/G101 -> 130.84476 | J101: =I101*G101 -> 13738.7 | K101: {=_FV(C101,"Price")} -> 120.24 | L101: =(N101-I101)*G101 -> -57.2 | M101: =L101/J101 -> -0.0041634216 | N101: 130.3 | O101: 44571 | P101: 44571 | Q101: =Table29[[#This Row],[Close Date]]-Table29[[#This Row],[Open Date]] -> 0
B102: 86 | C102: #VALUE! | D102: NYSE | E102: USD | F102: 100.36 | G102: 112 | H102: =2.33+2.4 -> 4.73 | I102: =((F102*G102)+H102)/G102 -> 100.40223 | J102: =I102*G102 -> 11245.05 | K102: {=_FV(C102,"Price")} -> 93.82 | L102: =(N102-I102)*G102 -> 89.35 | M102: =L102/J102 -> 0.0079457183 | N102: 101.2 | O102: 44571 | P102: 44571 | Q102: =Table29[[#This Row],[Close Date]]-Table29[[#This Row],[Open Date]] -> 0
B103: 87 | C103: #VALUE! | D103: NYSE | E103: USD | F103: 69.5 | G103: 166 | H103: =2.49+2.57 -> 5.06 | I103: =((F103*G103)+H103)/G103 -> 69.530482 | J103: =I103*G103 -> 11542.06 | K103: {=_FV(C103,"Price")} -> 59.77 | L103: =(N103-I103)*G103 -> 160.94 | M103: =L103/J103 -> 0.013943785 | N103: 70.5 | O103: 44571 | P103: 44571 | Q103: =Table29[[#This Row],[Close Date]]-Table29[[#This Row],[Open Date]] -> 0
B104: 88 | C104: #VALUE! | D104: NYSE | E104: USD | F104: 99 | G104: 121 | H104: =2.35+2.42 -> 4.77 | I104: =((F104*G104)+H104)/G104 -> 99.039421 | J104: =I104*G104 -> 11983.77 | K104: {=_FV(C104,"Price")} -> 93.82 | L104: =(N104-I104)*G104 -> 7.33 | M104: =L104/J104 -> 0.0006116606 | N104: 99.1 | O104: 44571 | P104: 44571 | Q104: =Table29[[#This Row],[Close Date]]-Table29[[#This Row],[Open Date]] -> 0
B105: 89 | C105: #VALUE! | D105: NYSE | E105: USD | F105: 56.39 | G105: 215 | H105: =2.78+2.87 -> 5.65 | I105: =((F105*G105)+H105)/G105 -> 56.416279 | J105: =I105*G105 -> 12129.5 | K105: {=_FV(C105,"Price")} -> 43.67 | L105: =(N105-I105)*G105 -> -132.5 | M105: =L105/J105 -> -0.010923781 | N105: 55.8 | O105: 44571 | P105: 44571 | Q105: =Table29[[#This Row],[Close Date]]-Table29[[#This Row],[Open Date]] -> 0
B106: 90 | C106: #VALUE! | D106: NYSE | E106: USD | F106: 56.3 | G106: 208 | H106: =2.76+2.68 -> 5.44 | I106: =((F106*G106)+H106)/G106 -> 56.326154 | J106: =I106*G106 -> 11715.84 | K106: {=_FV(C106,"Price")} -> 43.67 | L106: =(N106-I106)*G106 -> 45.52 | M106: =L106/J106 -> 0.0038853381 | N106: 56.545 | O106: 44571 | P106: 44571 | Q106: =Table29[[#This Row],[Close Date]]-Table29[[#This Row],[Open Date]] -> 0
...

Sheet Day Trade
C3: No. | D3: Date | E3: Stock | F3: Currency | G3: Grade | H3: Buy | I3: Quantity | J3: Fee | K3: Average Price | L3: Total Investment | M3: Sell Price | N3: Gain | O3: P % | P3: Stop Price | Q3: Loss | R3: L %
C4: 1 | D4: 01/12/2021 | E4: #VALUE! | F4: USD | G4: A | H4: 255 | I4: 100 | J4: =8.88*2+1 -> 18.76 | K4: =((H4*I4)+J4)/I4 -> 255.1876 | L4: =K4*I4 -> 25518.76 | M4: 255.37 | N4: =(M4-K4)*I4 -> 18.24 | O4: =N4/L4 -> 0.00071476827
C5: 2 | E5: #VALUE! | F5: USD | G5: A | H5: 255 | I5: 100 | J5: =8.88*2+1 -> 18.76 | K5: =((H5*I5)+J5)/I5 -> 255.1876 | L5: =K5*I5 -> 25518.76 | M5: 255.61 | N5: =(M5-K5)*I5 -> 42.24 | O5: =N5/L5 -> 0.0016552528
C6: 3 | E6: #VALUE! | F6: USD | G6: A | H6: 255.5 | I6: 100 | J6: =8.88*2+1 -> 18.76 | K6: =((H6*I6)+J6)/I6 -> 255.6876 | L6: =K6*I6 -> 25568.76 | P6: 253.11 | Q6: =(P6-K6)*I6 -> -257.76 | R6: =Q6/L6 -> -0.010081052
C7: 4 | E7: #VALUE! | F7: USD | G7: A | H7: 254 | I7: 150 | J7: =8.88*2+1 -> 18.76 | K7: =((H7*I7)+J7)/I7 -> 254.12507 | L7: =K7*I7 -> 38118.76 | P7: 251.98 | Q7: =(P7-K7)*I7 -> -321.76 | R7: =Q7/L7 -> -0.0084409881
C8: 5 | E8: #VALUE! | F8: USD | G8: C | H8: 63 | I8: 200 | J8: =8.88*4+2 -> 37.52 | K8: =((H8*I8)+J8)/I8 -> 63.1876 | L8: =K8*I8 -> 12637.52 | P8: 63 | Q8: =(P8-K8)*I8 -> -37.52 | R8: =Q8/L8 -> -0.0029689369
C9: 6 | D9: 01/13/2021 | E9: #VALUE! | F9: USD | G9: A | H9: 228.13 | I9: 150 | J9: =8.88*2+1 -> 18.76 | K9: =((H9*I9)+J9)/I9 -> 228.25507 | L9: =K9*I9 -> 34238.26 | M9: 229 | N9: =(M9-K9)*I9 -> 111.74 | O9: =N9/L9 -> 0.0032636004
C10: 7 | E10: #VALUE! | F10: USD | G10: A | H10: 227.15 | I10: 150 | J10: =8.88*2+1 -> 18.76 | K10: =((H10*I10)+J10)/I10 -> 227.27507 | L10: =K10*I10 -> 34091.26 | M10: 227.59 | N10: =(M10-K10)*I10 -> 47.24 | O10: =N10/L10 -> 0.0013856924
C11: 8 | E11: #VALUE! | F11: USD | G11: A | H11: 227.95 | I11: 150 | J11: =8.88*2+1 -> 18.76 | K11: =((H11*I11)+J11)/I11 -> 228.07507 | L11: =K11*I11 -> 34211.26 | M11: 228.66 | N11: =(M11-K11)*I11 -> 87.74 | O11: =N11/L11 -> 0.0025646527
C12: 9 | E12: #VALUE! | F12: USD | G12: A | H12: 228.45 | I12: 150 | J12: =8.88*2+1 -> 18.76 | K12: =((H12*I12)+J12)/I12 -> 228.57507 | L12: =K12*I12 -> 34286.26 | M12: 228.6 | N12: =(M12-K12)*I12 -> 3.74 | O12: =N12/L12 -> 0.0001090816
C13: 10 | D13: 01/14/2021 | E13: #VALUE! | F13: HKD | G13: A | H13: 234.2 | I13: 1500 | J13: =(H13*I13+M13*I13)*0.12%+(H13*I13+M13*I13)*(0.1%+0.002%+0.0027%+0.005%) -> 806.9361 | K13: =((H13*I13)+J13)/I13 -> 234.73796 | L13: =K13*I13 -> 352106.94 | P13: 234.6 | Q13: =(P13-K13)*I13 -> -206.9361 | R13: =Q13/L13 -> -0.0005877081
C14: 11 | E14: #VALUE! | F14: USD | G14: A | H14: 243.81 | I14: 150 | J14: =8.88*2+1 -> 18.76 | K14: =((H14*I14)+J14)/I14 -> 243.93507 | L14: =K14*I14 -> 36590.26 | M14: 244 | N14: =(M14-K14)*I14 -> 9.74 | O14: =N14/L14 -> 0.00026619106
C15: 12 | E15: #VALUE! | F15: USD | G15: A | H15: 242 | I15: 50 | J15: =8.88*2+1 -> 18.76 | K15: =((H15*I15)+J15)/I15 -> 242.3752 | L15: =K15*I15 -> 12118.76 | M15: 244 | N15: =(M15-K15)*I15 -> 81.24 | O15: =N15/L15 -> 0.0067036561
C16: 13 | D16: 01/15/2021 | E16: #VALUE! | F16: HKD | G16: A | H16: 242.8 | I16: 1000 | J16: =(H16*I16+P16*I16)*0.12%+(H16*I16+P16*I16)*(0.1%+0.002%+0.0027%+0.005%) -> 1108.9916 | K16: =((H16*I16)+J16)/I16 -> 243.90899 | L16: =K16*I16 -> 243908.99 | P16: 240 | Q16: =(P16-K16)*I16/7.8 -> -501.15277 | R16: =Q16/L16 -> -0.0020546712
C17: 14 | E17: #VALUE! | F17: HKD | G17: A | H17: 240 | I17: 600 | J17: =(H17*I17+P17*I17)*0.12%+(H17*I17+P17*I17)*(0.1%+0.002%+0.0027%+0.005%) -> 662.63856 | K17: =((H17*I17)+J17)/I17 -> 241.1044 | L17: =K17*I17 -> 144662.64 | P17: 240.8 | Q17: =(P17-K17)*I17/7.8 -> -23.4152 | R17: =Q17/L17 -> -0.00016186073
C18: 15 | E18: #VALUE! | F18: HKD | G18: A | H18: 239.8 | I18: 500 | J18: =(H18*I18+P18*I18)*0.12%+(H18*I18+P18*I18)*(0.1%+0.002%+0.0027%+0.005%) -> 551.9691 | K18: =((H18*I18)+J18)/I18 -> 240.90394 | L18: =K18*I18 -> 120451.97 | P18: 240.8 | Q18: =(P18-K18)*I18/7.8 -> -6.6627051 | R18: =Q18/L18 -> -5.5314207e-05
C19: 16 | E19: #VALUE! | F19: USD | G19: A | H19: 243.9 | I19: 100 | J19: =8.88*2+1 -> 18.76 | K19: =((H19*I19)+J19)/I19 -> 244.0876 | L19: =K19*I19 -> 24408.76 | M19: 244.21 | N19: =(M19-K19)*I19 -> 12.24 | O19: =N19/L19 -> 0.00050145931
C20: 17 | E20: #VALUE! | F20: USD | G20: B | H20: 391.15 | I20: 60 | J20: =8.88*2+1 -> 18.76 | K20: =((H20*I20)+J20)/I20 -> 391.46267 | L20: =K20*I20 -> 23487.76 | M20: 391.58 | N20: =(M20-K20)*I20 -> 7.04 | O20: =N20/L20 -> 0.00029973058
C21: 18 | E21: #VALUE! | F21: USD | G21: A | H21: 243.02 | I21: 100 | J21: =8.88*2+1 -> 18.76 | K21: =((H21*I21)+J21)/I21 -> 243.2076 | L21: =K21*I21 -> 24320.76 | M21: 243.72 | N21: =(M21-K21)*I21 -> 51.24 | O21: =N21/L21 -> 0.0021068421
C22: 19 | E22: #VALUE! | F22: USD | G22: B | H22: 394.1 | I22: 60 | J22: =8.88*2+1 -> 18.76 | K22: =((H22*I22)+J22)/I22 -> 394.41267 | L22: =K22*I22 -> 23664.76 | P22: 383.03 | Q22: =(P22-K22)*I22 -> -682.96 | R22: =Q22/L22 -> -0.02885979
C23: 20 | E23: #VALUE! | F23: USD | G23: B | H23: 390.9 | I23: 60 | J23: =8.88*2+1 -> 18.76 | K23: =((H23*I23)+J23)/I23 -> 391.21267 | L23: =K23*I23 -> 23472.76 | P23: 383.03 | Q23: =(P23-K23)*I23 -> -490.96 | R23: =Q23/L23 -> -0.02091616
C24: 21 | E24: #VALUE! | F24: USD | G24: B | H24: 385.55 | I24: 70 | J24: =8.88*2+1 -> 18.76 | K24: =((H24*I24)+J24)/I24 -> 385.818 | L24: =K24*I24 -> 27007.26 | M24: 386 | N24: =(M24-K24)*I24 -> 12.74 | O24: =N24/L24 -> 0.00047172501
C25: 22 | D25: 01/18/2021 | E25: #VALUE! | F25: HKD | G25: A | H25: 241.8 | I25: 800 | J25: =(H25*I25+P25*I25)*0.12%+(H25*I25+P25*I25)*(0.1%+0.002%+0.0027%+0.005%) -> 889.3984 | K25: =((H25*I25)+J25)/I25 -> 242.91175 | L25: =K25*I25 -> 194329.4 | P25: 242.2 | Q25: =(P25-K25)*I25/7.8 -> -72.999795 | R25: =Q25/L25 -> -0.00037564978
C26: 23 | E26: #VALUE! | F26: HKD | G26: A | H26: 240.4 | I26: 900 | J26: =(H26*I26+M26*I26)*0.12%+(H26*I26+M26*I26)*(0.1%+0.002%+0.0027%+0.005%) -> 997.67898 | K26: =((H26*I26)+J26)/I26 -> 241.50853 | L26: =K26*I26 -> 217357.68 | M26: 242.2 | N26: =(M26-K26)*I26/7.8 -> 79.784746 | O26: =N26/L26 -> 0.00036706661
C27: 24 | D27: 01/19/2021 | E27: #VALUE! | F27: HKD | G27: A | H27: 243.4 | I27: 800 | J27: =(H27*I27+P27*I27)*0.12%+(H27*I27+P27*I27)*(0.1%+0.002%+0.0027%+0.005%) -> 896.01376 | K27: =((H27*I27)+J27)/I27 -> 244.52002 | L27: =K27*I27 -> 195616.01 | P27: 244.2 | Q27: =(P27-K27)*I27/7.8 -> -32.822277 | R27: =Q27/L27 -> -0.00016778931
C28: 25 | E28: #VALUE! | F28: USD | G28: C | H28: 57 | I28: 100 | J28: =8.88*2+1 -> 18.76 | K28: =((H28*I28)+J28)/I28 -> 57.1876 | L28: =K28*I28 -> 5718.76 | M28: 58.2 | N28: =(M28-K28)*I28 -> 101.24 | O28: =N28/L28 -> 0.017703138
C29: 26 | D29: 01/20/2021 | E29: #VALUE! | F29: USD | G29: A | H29: 265 | I29: 100 | J29: =8.88*2+1 -> 18.76 | K29: =((H29*I29)+J29)/I29 -> 265.1876 | L29: =K29*I29 -> 26518.76 | M29: 266.2 | N29: =(M29-K29)*I29 -> 101.24 | O29: =N29/L29 -> 0.0038176747
C30: 27 | E30: #VALUE! | F30: USD | G30: C | H30: 58 | I30: 100 | J30: =8.88*2+1 -> 18.76 | K30: =((H30*I30)+J30)/I30 -> 58.1876 | L30: =K30*I30 -> 5818.76 | P30: 58 | Q30: =(P30-K30)*I30 -> -18.76 | R30: =Q30/L30 -> -0.0032240546
C31: 28 | E31: #VALUE! | F31: USD | G31: A | H31: 267.5 | I31: 80 | J31: =8.88*2+1 -> 18.76 | K31: =((H31*I31)+J31)/I31 -> 267.7345 | L31: =K31*I31 -> 21418.76 | M31: 268 | N31: =(M31-K31)*I31 -> 21.24 | O31: =N31/L31 -> 0.00099165405
C32: 29 | E32: #VALUE! | F32: USD | G32: A | H32: 267 | I32: 100 | J32: =8.88*2+1 -> 18.76 | K32: =((H32*I32)+J32)/I32 -> 267.1876 | L32: =K32*I32 -> 26718.76 | M32: 268 | N32: =(M32-K32)*I32 -> 81.24 | O32: =N32/L32 -> 0.0030405603
C33: 30 | D33: 01/21/2021 | E33: #VALUE! | F33: USD | G33: A | H33: 271.5 | I33: 100 | J33: =8.88*2+1 -> 18.76 | K33: =((H33*I33)+J33)/I33 -> 271.6876 | L33: =K33*I33 -> 27168.76 | M33: 273 | N33: =(M33-K33)*I33 -> 131.24 | O33: =N33/L33 -> 0.004830548
C34: 31 | E34: #VALUE! | F34: USD | G34: A | H34: 259.5 | I34: 100 | J34: =8.88*2+1 -> 18.76 | K34: =((H34*I34)+J34)/I34 -> 259.6876 | L34: =K34*I34 -> 25968.76 | M34: 260 | N34: =(M34-K34)*I34 -> 31.24 | O34: =N34/L34 -> 0.0012029839
C35: 32 | D35: 01/22/2021 | E35: #VALUE! | F35: USD | G35: C | H35: 59.19 | I35: 50 | J35: =8.88*2+1 -> 18.76 | K35: =((H35*I35)+J35)/I35 -> 59.5652 | L35: =K35*I35 -> 2978.26 | M35: 61 | N35: =(M35-K35)*I35 -> 71.74 | O35: =N35/L35 -> 0.02408789
C36: 33 | E36: #VALUE! | F36: USD | G36: C | H36: 59.19 | I36: 50 | J36: =8.88+1 -> 9.88 | K36: =((H36*I36)+J36)/I36 -> 59.3876 | L36: =K36*I36 -> 2969.38 | M36: 61.25 | N36: =(M36-K36)*I36 -> 93.12 | O36: =N36/L36 -> 0.031360082
C37: 34 | E37: #VALUE! | F37: USD | G37: A | H37: 276 | I37: 100 | J37: =8.88*2+1 -> 18.76 | K37: =((H37*I37)+J37)/I37 -> 276.1876 | L37: =K37*I37 -> 27618.76 | M37: 277 | N37: =(M37-K37)*I37 -> 81.24 | O37: =N37/L37 -> 0.0029414789
C38: 35 | E38: #VALUE! | F38: USD | G38: C | H38: 61.5 | I38: 100 | J38: =8.88*2+1 -> 18.76 | K38: =((H38*I38)+J38)/I38 -> 61.6876 | L38: =K38*I38 -> 6168.76 | P38: 61 | Q38: =(P38-K38)*I38 -> -68.76 | R38: =Q38/L38 -> -0.011146486
C39: 36 | D39: 01/25/2021 | E39: #VALUE! | F39: USD | G39: A | H39: =(276.5+274.8)/2 -> 275.65 | I39: 200 | J39: =8.88*3+1 -> 27.64 | K39: =((H39*I39)+J39)/I39 -> 275.7882 | L39: =K39*I39 -> 55157.64 | P39: 273 | Q39: =(P39-K39)*I39 -> -557.64 | R39: =Q39/L39 -> -0.010109932
C40: 37 | E40: #VALUE! | F40: USD | G40: A | H40: =(274.5+274)/2 -> 274.25 | I40: 200 | J40: =8.88*3+1 -> 27.64 | K40: =((H40*I40)+J40)/I40 -> 274.3882 | L40: =K40*I40 -> 54877.64 | M40: 274.53 | N40: =(M40-K40)*I40 -> 28.36 | O40: =N40/L40 -> 0.00051678607
C41: 38 | E41: #VALUE! | F41: USD | G41: C | H41: 59.9 | I41: 300 | J41: =8.88*3+1 -> 27.64 | K41: =((H41*I41)+J41)/I41 -> 59.992133 | L41: =K41*I41 -> 17997.64 | P41: =(59.6+60)/2 -> 59.8 | Q41: =(P41-K41)*I41 -> -57.64 | R41: =Q41/L41 -> -0.0032026421
C42: 39 | E42: #VALUE! | F42: USD | G42: A | H42: 260 | I42: 100 | J42: =8.88*2+1 -> 18.76 | K42: =((H42*I42)+J42)/I42 -> 260.1876 | L42: =K42*I42 -> 26018.76 | M42: 260.5 | N42: =(M42-K42)*I42 -> 31.24 | O42: =N42/L42 -> 0.0012006721
C43: 40 | E43: #VALUE! | F43: USD | G43: B | H43: 93.8 | I43: 200 | J43: =8.88*2+1 -> 18.76 | K43: =((H43*I43)+J43)/I43 -> 93.8938 | L43: =K43*I43 -> 18778.76 | M43: 94 | N43: =(M43-K43)*I43 -> 21.24 | O43: =N43/L43 -> 0.0011310651
C44: 41 | D44: 01/26/2021 | E44: #VALUE! | F44: USD | G44: C | H44: 59 | I44: 150 | J44: =8.88*2+1 -> 18.76 | K44: =((H44*I44)+J44)/I44 -> 59.125067 | L44: =K44*I44 -> 8868.76 | M44: 60.2 | N44: =(M44-K44)*I44 -> 161.24 | O44: =N44/L44 -> 0.01818067
C45: 42 | D45: 01/27/2021 | E45: #VALUE! | F45: USD | G45: B | H45: 86.8 | I45: 150 | J45: =8.88*2+1 -> 18.76 | K45: =((H45*I45)+J45)/I45 -> 86.925067 | L45: =K45*I45 -> 13038.76 | M45: 90.5 | N45: =(M45-K45)*I45 -> 536.24 | O45: =N45/L45 -> 0.04112661
C46: 43 | E46: #VALUE! | F46: USD | G46: A | H46: =(276.8+271+269.5)/3 -> 272.43333 | I46: 300 | J46: =8.88*4+2 -> 37.52 | K46: =((H46*I46)+J46)/I46 -> 272.5584 | L46: =K46*I46 -> 81767.52 | M46: 273 | N46: =(M46-K46)*I46 -> 132.48 | O46: =N46/L46 -> 0.0016202032
C47: 44 | D47: 03/22/2021 | E47: #VALUE! | F47: USD | G47: B | H47: 83.8 | I47: 100 | J47: =8.88*2+1 -> 18.76 | K47: =((H47*I47)+J47)/I47 -> 83.9876 | L47: =K47*I47 -> 8398.76 | M47: 85.1 | N47: =(M47-K47)*I47 -> 111.24 | O47: =N47/L47 -> 0.013244812
C48: 45 | D48: 03/23/2021 | E48: #VALUE! | F48: USD | G48: A | H48: 250.8 | I48: 50 | J48: =8.88*2+1 -> 18.76 | K48: =((H48*I48)+J48)/I48 -> 251.1752 | L48: =K48*I48 -> 12558.76 | M48: 252 | N48: =(M48-K48)*I48 -> 41.24 | O48: =N48/L48 -> 0.0032837637
C49: 46 | D49: 03/24/2021 | E49: #VALUE! | F49: USD | G49: A | H49: 110.8 | I49: 100 | J49: =8.88*2+1 -> 18.76 | K49: =((H49*I49)+J49)/I49 -> 110.9876 | L49: =K49*I49 -> 11098.76 | M49: 112 | N49: =(M49-K49)*I49 -> 101.24 | O49: =N49/L49 -> 0.0091217397
C50: 47 | D50: 03/25/2021 | E50: #VALUE! | F50: USD | G50: B | H50: 79 | I50: 100 | J50: =6.88*2+1 -> 14.76 | K50: =((H50*I50)+J50)/I50 -> 79.1476 | L50: =K50*I50 -> 7914.76 | M50: 79.47 | N50: =(M50-K50)*I50 -> 32.24 | O50: =N50/L50 -> 0.0040734021
C51: 48 | E51: #VALUE! | F51: USD | G51: B | H51: 78 | I51: 100 | J51: =6.88*2+1 -> 14.76 | K51: =((H51*I51)+J51)/I51 -> 78.1476 | L51: =K51*I51 -> 7814.76 | M51: 78.23 | N51: =(M51-K51)*I51 -> 8.24 | O51: =N51/L51 -> 0.001054415
C52: 49 | E52: #VALUE! | F52: USD | G52: B | H52: 78.5 | I52: 100 | J52: =6.88*2+1 -> 14.76 | K52: =((H52*I52)+J52)/I52 -> 78.6476 | L52: =K52*I52 -> 7864.76 | M52: 78.81 | N52: =(M52-K52)*I52 -> 16.24 | O52: =N52/L52 -> 0.0020649073
C53: 50 | E53: #VALUE! | F53: USD | G53: B | H53: 95 | I53: 100 | J53: =6.88*2+1 -> 14.76 | K53: =((H53*I53)+J53)/I53 -> 95.1476 | L53: =K53*I53 -> 9514.76 | M53: 95.5 | N53: =(M53-K53)*I53 -> 35.24 | O53: =N53/L53 -> 0.0037037193
C54: 51 | D54: 03/26/2021 | E54: #VALUE! | F54: USD | G54: A | H54: 190 | I54: 50 | J54: =6.88*2+1 -> 14.76 | K54: =((H54*I54)+J54)/I54 -> 190.2952 | L54: =K54*I54 -> 9514.76 | M54: 195 | N54: =(M54-K54)*I54 -> 235.24 | O54: =N54/L54 -> 0.024723692
C55: 52 | E55: #VALUE! | F55: USD | G55: A | H55: =(192*50+188*50+50+183*100+175*100)/Table6[[#This Row],[Quantity]] -> 182.83333 | I55: =50+50+100+100 -> 300 | J55: =6.88*5+1 -> 35.4 | K55: =((H55*I55)+J55)/I55 -> 182.95133 | L55: =K55*I55 -> 54885.4 | M55: 185 | N55: =(M55-K55)*I55 -> 614.6 | O55: =N55/L55 -> 0.011197878
C56: 53 | E56: #VALUE! | F56: USD | G56: A | H56: 177.1 | I56: 50 | J56: =6.88*2+1 -> 14.76 | K56: =((H56*I56)+J56)/I56 -> 177.3952 | L56: =K56*I56 -> 8869.76 | M56: 182 | N56: =(M56-K56)*I56 -> 230.24 | O56: =N56/L56 -> 0.025957861
C57: 54 | D57: 03/29/2021 | E57: #VALUE! | F57: USD | G57: B | H57: 81 | I57: 100 | J57: =6.88*2+1 -> 14.76 | K57: =((H57*I57)+J57)/I57 -> 81.1476 | L57: =K57*I57 -> 8114.76 | M57: 81.21 | N57: =(M57-K57)*I57 -> 6.24 | O57: =N57/L57 -> 0.00076896914
C58: 55 | D58: 03/30/2021 | E58: #VALUE! | F58: USD | G58: B | H58: 83 | I58: 100 | J58: =6.88*2+1 -> 14.76 | K58: =((H58*I58)+J58)/I58 -> 83.1476 | L58: =K58*I58 -> 8314.76 | M58: 83.16 | N58: =(M58-K58)*I58 -> 1.24 | O58: =N58/L58 -> 0.00014913239
C59: 56 | E59: #VALUE! | F59: USD | G59: A | H59: 129.8 | I59: 100 | J59: =6.88*2+1 -> 14.76 | K59: =((H59*I59)+J59)/I59 -> 129.9476 | L59: =K59*I59 -> 12994.76 | M59: 130.2 | N59: =(M59-K59)*I59 -> 25.24 | O59: =N59/L59 -> 0.0019423214
C60: 57 | D60: 03/31/2021 | E60: #VALUE! | F60: USD | G60: C | H60: 37.8 | I60: 50 | J60: =6.88*2+1 -> 14.76 | K60: =((H60*I60)+J60)/I60 -> 38.0952 | L60: =K60*I60 -> 1904.76 | M60: 39 | N60: =(M60-K60)*I60 -> 45.24 | O60: =N60/L60 -> 0.023751024
C61: 58 | D61: 04/12/2021 | E61: #VALUE! | F61: USD | G61: B | H61: 36.945 | I61: 100 | J61: =2.88*2+1 -> 6.76 | K61: =((H61*I61)+J61)/I61 -> 37.0126 | L61: =K61*I61 -> 3701.26 | M61: 37.13 | N61: =(M61-K61)*I61 -> 11.74 | O61: =N61/L61 -> 0.0031718928
C62: 59 | E62: #VALUE! | F62: USD | G62: B | H62: 34.507 | I62: 100 | J62: =2.88*2+1 -> 6.76 | K62: =((H62*I62)+J62)/I62 -> 34.5746 | L62: =K62*I62 -> 3457.46 | M62: 35.69 | N62: =(M62-K62)*I62 -> 111.54 | O62: =N62/L62 -> 0.032260677
C63: 60 | D63: 04/13/2021 | E63: #VALUE! | F63: USD | G63: B | H63: 78.29 | I63: 100 | J63: =2.88*2+1 -> 6.76 | K63: =((H63*I63)+J63)/I63 -> 78.3576 | L63: =K63*I63 -> 7835.76 | P63: 78.1 | Q63: =(P63-K63)*I63 -> -25.76 | R63: =Q63/L63 -> -0.0032874922
C64: 61 | D64: 04/22/2021 | E64: #VALUE! | F64: USD | G64: A | H64: 133.16 | I64: 100 | J64: =2.88*2+1 -> 6.76 | K64: =((H64*I64)+J64)/I64 -> 133.2276 | L64: =K64*I64 -> 13322.76 | M64: 133.5 | N64: =(M64-K64)*I64 -> 27.24 | O64: =N64/L64 -> 0.0020446214
C65: 62 | D65: 04/26/2021 | E65: #VALUE! | F65: USD | G65: B | H65: 32.4 | I65: 200 | J65: =2.88*2+1 -> 6.76 | K65: =((H65*I65)+J65)/I65 -> 32.4338 | L65: =K65*I65 -> 6486.76 | M65: 33.2 | N65: =(M65-K65)*I65 -> 153.24 | O65: =N65/L65 -> 0.023623504
C66: 63 | E66: #VALUE! | F66: USD | G66: A | H66: 302 | I66: 100 | J66: =2.88*2+1 -> 6.76 | K66: =((H66*I66)+J66)/I66 -> 302.0676 | L66: =K66*I66 -> 30206.76 | M66: 302.6 | N66: =(M66-K66)*I66 -> 53.24 | O66: =N66/L66 -> 0.0017625194
C67: 64 | D67: 05/25/2021 | E67: #VALUE! | F67: USD | G67: A | H67: 127 | I67: 100 | J67: =2.88*2+1 -> 6.76 | K67: =((H67*I67)+J67)/I67 -> 127.0676 | L67: =K67*I67 -> 12706.76 | P67: 126.5 | Q67: =(P67-K67)*I67 -> -56.76 | R67: =Q67/L67 -> -0.0044669137
C68: 65 | D68: 07/19/2021 | E68: #VALUE! | F68: USD | G68: B | H68: 73 | I68: 100 | J68: =2.88*2+1 -> 6.76 | K68: =((H68*I68)+J68)/I68 -> 73.0676 | L68: =K68*I68 -> 7306.76 | M68: 73.16 | N68: =(M68-K68)*I68 -> 9.24 | O68: =N68/L68 -> 0.0012645824
C69: 66 | E69: #VALUE! | F69: USD | G69: B | H69: 38.6 | I69: 100 | J69: =2.88*2+1 -> 6.76 | K69: =((H69*I69)+J69)/I69 -> 38.6676 | L69: =K69*I69 -> 3866.76 | M69: 38.77 | N69: =(M69-K69)*I69 -> 10.24 | O69: =N69/L69 -> 0.0026482119
C70: 67 | E70: #VALUE! | F70: USD | G70: B | H70: 38.8 | I70: 100 | J70: =2.88*2+1 -> 6.76 | K70: =((H70*I70)+J70)/I70 -> 38.8676 | L70: =K70*I70 -> 3886.76 | M70: 39.01 | N70: =(M70-K70)*I70 -> 14.24 | O70: =N70/L70 -> 0.0036637199
C71: 68 | E71: #VALUE! | F71: USD | G71: B | H71: 73.6 | I71: 100 | J71: =2.88*2+1 -> 6.76 | K71: =((H71*I71)+J71)/I71 -> 73.6676 | L71: =K71*I71 -> 7366.76 | M71: 73.85 | N71: =(M71-K71)*I71 -> 18.24 | O71: =N71/L71 -> 0.0024759867
C72: 69 | E72: #VALUE! | F72: USD | G72: A | H72: 73.9 | I72: 150 | J72: =2.88*2+1 -> 6.76 | K72: =((H72*I72)+J72)/I72 -> 73.945067 | L72: =K72*I72 -> 11091.76 | M72: 74.2 | N72: =(M72-K72)*I72 -> 38.24 | O72: =N72/L72 -> 0.0034476043
C73: 70 | D73: 07/20/2021 | E73: #VALUE! | F73: USD | G73: B | H73: 72.9 | I73: 100 | J73: =2.88*2+1 -> 6.76 | K73: =((H73*I73)+J73)/I73 -> 72.9676 | L73: =K73*I73 -> 7296.76 | M73: 73.5 | N73: =(M73-K73)*I73 -> 53.24 | O73: =N73/L73 -> 0.0072963891
C74: 71 | E74: #VALUE! | F74: USD | G74: B | H74: 43 | I74: 100 | J74: =2.88*2+1 -> 6.76 | K74: =((H74*I74)+J74)/I74 -> 43.0676 | L74: =K74*I74 -> 4306.76 | M74: 43.4 | N74: =(M74-K74)*I74 -> 33.24 | O74: =N74/L74 -> 0.007718099
C75: 72 | E75: #VALUE! | F75: USD | G75: B | H75: 73.2 | I75: 100 | J75: =2.88*2+1 -> 6.76 | K75: =((H75*I75)+J75)/I75 -> 73.2676 | L75: =K75*I75 -> 7326.76 | M75: 73.6 | N75: =(M75-K75)*I75 -> 33.24 | O75: =N75/L75 -> 0.0045367939
C76: 73 | E76: #VALUE! | F76: USD | G76: B | H76: 43.5 | I76: 100 | J76: =2.88*2+1 -> 6.76 | K76: =((H76*I76)+J76)/I76 -> 43.5676 | L76: =K76*I76 -> 4356.76 | M76: 43.8 | N76: =(M76-K76)*I76 -> 23.24 | O76: =N76/L76 -> 0.0053342392
C77: 74 | D77: 07/21/2021 | E77: #VALUE! | F77: USD | G77: A | H77: 179 | I77: 60 | J77: =2.88*2+1 -> 6.76 | K77: =((H77*I77)+J77)/I77 -> 179.11267 | L77: =K77*I77 -> 10746.76 | M77: 181 | N77: =(M77-K77)*I77 -> 113.24 | O77: =N77/L77 -> 0.010537129
C78: 75 | D78: 07/22/2021 | E78: #VALUE! | F78: USD | G78: A | H78: 74.9 | I78: 100 | J78: =2.88*2+1 -> 6.76 | K78: =((H78*I78)+J78)/I78 -> 74.9676 | L78: =K78*I78 -> 7496.76 | M78: 75.27 | N78: =(M78-K78)*I78 -> 30.24 | O78: =N78/L78 -> 0.0040337426
C79: 76 | E79: #VALUE! | F79: USD | G79: B | H79: 45.8 | I79: 100 | J79: =2.88*2+1 -> 6.76 | K79: =((H79*I79)+J79)/I79 -> 45.8676 | L79: =K79*I79 -> 4586.76 | M79: 46.5 | N79: =(M79-K79)*I79 -> 63.24 | O79: =N79/L79 -> 0.01378751
C80: 77 | D80: 07/23/2021 | E80: #VALUE! | F80: USD | G80: A | H80: 169.4 | I80: 60 | J80: =2.88*2+1 -> 6.76 | K80: =((H80*I80)+J80)/I80 -> 169.51267 | L80: =K80*I80 -> 10170.76 | M80: 170 | N80: =(M80-K80)*I80 -> 29.24 | O80: =N80/L80 -> 0.0028749081
C81: 78 | E81: #VALUE! | F81: USD | G81: B | H81: 43.4 | I81: 100 | J81: =2.88*2+1 -> 6.76 | K81: =((H81*I81)+J81)/I81 -> 43.4676 | L81: =K81*I81 -> 4346.76 | M81: 44 | N81: =(M81-K81)*I81 -> 53.24 | O81: =N81/L81 -> 0.012248203
C82: 79 | E82: #VALUE! | F82: USD | G82: A | H82: 373 | I82: 100 | J82: =2.88*2+1 -> 6.76 | K82: =((H82*I82)+J82)/I82 -> 373.0676 | L82: =K82*I82 -> 37306.76 | M82: 373.3 | N82: =(M82-K82)*I82 -> 23.24 | O82: =N82/L82 -> 0.0006229434
C83: 80 | D83: 07/26/2021 | E83: #VALUE! | F83: USD | G83: B | H83: 43 | I83: 100 | J83: =2.88*2+1 -> 6.76 | K83: =((H83*I83)+J83)/I83 -> 43.0676 | L83: =K83*I83 -> 4306.76 | M83: 44.4 | N83: =(M83-K83)*I83 -> 133.24 | O83: =N83/L83 -> 0.03093741
C84: 81 | E84: #VALUE! | F84: USD | G84: B | H84: 67.8 | I84: 50 | J84: =2.88*2+1 -> 6.76 | K84: =((H84*I84)+J84)/I84 -> 67.9352 | L84: =K84*I84 -> 3396.76 | M84: 68.8 | N84: =(M84-K84)*I84 -> 43.24 | O84: =N84/L84 -> 0.012729778
C85: 82 | E85: #VALUE! | F85: USD | G85: A | H85: 191.75 | I85: 100 | J85: =2.88*2+1 -> 6.76 | K85: =((H85*I85)+J85)/I85 -> 191.8176 | L85: =K85*I85 -> 19181.76 | M85: 192.1 | N85: =(M85-K85)*I85 -> 28.24 | O85: =N85/L85 -> 0.001472232
C86: 83 | D86: 07/28/2021 | E86: #VALUE! | F86: USD | G86: A | H86: 371.5 | I86: 50 | J86: =2.88*2+1 -> 6.76 | K86: =((H86*I86)+J86)/I86 -> 371.6352 | L86: =K86*I86 -> 18581.76 | M86: 373 | N86: =(M86-K86)*I86 -> 68.24 | O86: =N86/L86 -> 0.0036724185
C87: 84 | E87: #VALUE! | F87: USD | G87: A | H87: 371.5 | I87: 50 | J87: =2.88+1 -> 3.88 | K87: =((H87*I87)+J87)/I87 -> 371.5776 | L87: =K87*I87 -> 18578.88 | M87: 371.81 | N87: =(M87-K87)*I87 -> 11.62 | O87: =N87/L87 -> 0.00062544136
C88: 85 | D88: 07/29/2021 | E88: #VALUE! | F88: USD | G88: B | H88: 42.7 | I88: 100 | J88: =2.88*2+1 -> 6.76 | K88: =((H88*I88)+J88)/I88 -> 42.7676 | L88: =K88*I88 -> 4276.76 | M88: 43 | N88: =(M88-K88)*I88 -> 23.24 | O88: =N88/L88 -> 0.0054340201
C89: 86 | D89: 07/30/2021 | E89: #VALUE! | F89: USD | G89: A | H89: 163.8 | I89: 50 | J89: =2.88*2+1 -> 6.76 | K89: =((H89*I89)+J89)/I89 -> 163.9352 | L89: =K89*I89 -> 8196.76 | M89: 164.3 | N89: =(M89-K89)*I89 -> 18.24 | O89: =N89/L89 -> 0.0022252695
C90: 87 | E90: #VALUE! | F90: USD | G90: B | H90: 44.3 | I90: 100 | J90: =2.88*2+1 -> 6.76 | K90: =((H90*I90)+J90)/I90 -> 44.3676 | L90: =K90*I90 -> 4436.76 | M90: 44.5 | N90: =(M90-K90)*I90 -> 13.24 | O90: =N90/L90 -> 0.0029841596
C91: 88 | E91: #VALUE! | F91: USD | G91: A | H91: 148.9 | I91: 100 | J91: =2.88*2+1 -> 6.76 | K91: =((H91*I91)+J91)/I91 -> 148.9676 | L91: =K91*I91 -> 14896.76 | M91: 149.25 | N91: =(M91-K91)*I91 -> 28.24 | O91: =N91/L91 -> 0.0018957142
C92: 89 | D92: 08/02/2021 | E92: #VALUE! | F92: USD | G92: A | H92: 3328 | I92: 10 | J92: =2.88*2+1 -> 6.76 | K92: =((H92*I92)+J92)/I92 -> 3328.676 | L92: =K92*I92 -> 33286.76 | M92: 3332 | N92: =(M92-K92)*I92 -> 33.24 | O92: =N92/L92 -> 0.00099859524
C93: 90 | D93: 08/03/2021 | E93: #VALUE! | F93: USD | G93: C | H93: 41.8 | I93: 100 | J93: =2.88*2+1 -> 6.76 | K93: =((H93*I93)+J93)/I93 -> 41.8676 | L93: =K93*I93 -> 4186.76 | M93: 42.2 | N93: =(M93-K93)*I93 -> 33.24 | O93: =N93/L93 -> 0.0079393135
C94: 91 | E94: #VALUE! | F94: USD | G94: A | H94: 79 | I94: 100 | J94: =2.88*2+1 -> 6.76 | K94: =((H94*I94)+J94)/I94 -> 79.0676 | L94: =K94*I94 -> 7906.76 | M94: 79.6 | N94: =(M94-K94)*I94 -> 53.24 | O94: =N94/L94 -> 0.0067334787
C95: 92 | D95: 08/04/2021 | E95: #VALUE! | F95: USD | G95: B | H95: 45.4 | I95: 100 | J95: =2.88*2+1 -> 6.76 | K95: =((H95*I95)+J95)/I95 -> 45.4676 | L95: =K95*I95 -> 4546.76 | M95: 45.6 | N95: =(M95-K95)*I95 -> 13.24 | O95: =N95/L95 -> 0.0029119637
C96: 93 | E96: #VALUE! | F96: USD | G96: A | H96: 147.8 | I96: 100 | J96: =2.88*2+1 -> 6.76 | K96: =((H96*I96)+J96)/I96 -> 147.8676 | L96: =K96*I96 -> 14786.76 | M96: 148.6 | N96: =(M96-K96)*I96 -> 73.24 | O96: =N96/L96 -> 0.0049530796
C97: 94 | D97: 08/13/2021 | E97: #VALUE! | F97: USD | G97: B | H97: 39.4 | I97: 50 | J97: =2.88*2+1 -> 6.76 | K97: =((H97*I97)+J97)/I97 -> 39.5352 | L97: =K97*I97 -> 1976.76 | M97: 40 | N97: =(M97-K97)*I97 -> 23.24 | O97: =N97/L97 -> 0.011756612
C98: 95 | D98: 08/17/2021 | E98: #VALUE! | F98: USD | G98: B | H98: 66.1 | I98: 100 | J98: =2.88*2+1 -> 6.76 | K98: =((H98*I98)+J98)/I98 -> 66.1676 | L98: =K98*I98 -> 6616.76 | M98: 66.5 | N98: =(M98-K98)*I98 -> 33.24 | O98: =N98/L98 -> 0.0050236067
C99: 96 | D99: 08/18/2021 | E99: #VALUE! | F99: USD | G99: A | H99: 3220 | I99: 4 | J99: =2.88*2+1 -> 6.76 | K99: =((H99*I99)+J99)/I99 -> 3221.69 | L99: =K99*I99 -> 12886.76 | M99: 3230 | N99: =(M99-K99)*I99 -> 33.24 | O99: =N99/L99 -> 0.0025793916
C100: 97 | D100: 08/19/2021 | E100: #VALUE! | F100: USD | G100: A | H100: 161.6 | I100: 50 | J100: =2.88*2+1 -> 6.76 | K100: =((H100*I100)+J100)/I100 -> 161.7352 | L100: =K100*I100 -> 8086.76 | M100: 162.4 | N100: =(M100-K100)*I100 -> 33.24 | O100: =N100/L100 -> 0.0041104225
C101: 98 | E101: #VALUE! | F101: USD | G101: A | H101: 3218 | I101: 4 | J101: =2.88*2+1 -> 6.76 | K101: =((H101*I101)+J101)/I101 -> 3219.69 | L101: =K101*I101 -> 12878.76 | P101: 3202 | Q101: =(P101-K101)*I101 -> -70.76 | R101: =Q101/L101 -> -0.0054943178
C102: 99 | E102: #VALUE! | F102: USD | G102: A | H102: 161.8 | I102: 50 | J102: =2.88*2+1 -> 6.76 | K102: =((H102*I102)+J102)/I102 -> 161.9352 | L102: =K102*I102 -> 8096.76 | P102: 160.5 | Q102: =(P102-K102)*I102 -> -71.76 | R102: =Q102/L102 -> -0.0088628044
...

Sheet Fee and Margin
C2: Forex SGD to USD | D2: 0.75
C4: Cash Balance | D4: ='SG Portfolio'!D11 -> -33411.634 | E4: USD | I4: 0.07 | J4: Margin Interest Rate
C5: Equity Balance | D5: =D4+D10 -> 25005.558 | E5: USD | I5: =IF(D4<0,-D4*I4/360,0) -> 6.4967067 | J5: Daily Interest
C6: Margin Call | D6: =(D11*F25+D12*F26+D13*F27)-D5 -> -7864.1984 | E6: USD
C7: Force Selling | D7: =(D11*G25+D12*G26+D13*G27)-D5 -> -11302.662 | E7: USD
C9: Investment Portfolio | D9: Market Value | E9: Initial Margin | F9: Cash Equivalent | J9: Brokerage Fee | K9: Foreign Exchange Fee
D10: =SUM(D11:D13) -> 58417.192 | E10: =SUM(E11:E13) -> 20088.375 | F10: =D10-E10 -> 38328.817 | I10: HKEx | J10: 0.0006 | K10: =0.1%+0.002%+0.0027%+0.005% -> 0.001097
C11: Grade A | D11: ='SG Portfolio'!E17+'SG Portfolio'!H17 -> 42558.192 | E11: =D11*E25 -> 12158.875 | F11: =D11-E11 -> 30399.317 | I11: US | J11: 2.88 | K11: 2.21e-05
C12: Grade B | D12: ='SG Portfolio'!E18+'SG Portfolio'!H18 -> 15859 | E12: =D12*E26 -> 7929.5 | F12: =D12-E12 -> 7929.5
C13: Grade C | D13: ='SG Portfolio'!E19+'SG Portfolio'!H19 -> 0 | E13: =D13*E27 -> 0 | F13: =D13-E13 -> 0
C16: Initial Credit | D16: 150000 | E16: SGD USD | F16: =D16*D2 -> 112500
C17: Tradable Balance | D17: =D4+F10 -> 4917.1822 | E17: USD SGD | F17: =D17/D2 -> 6556.2429
D18: Buy A | E18: Buy B | F18: Buy C
C19: USD | D19: =D20*D2 -> 17210.138 | E19: =D17*L24 -> 9834.3644 | F19: =D17*M24 -> 4917.1822
C20: SGD | D20: =IF(D17*K24>(D4/D2+D16),(D4/D2+D16),D17/D2*K24) -> 22946.85 | E20: =E19/$D$2 -> 13112.486 | F20: =F19/$D$2 -> 6556.2429
C23: Grade of Investment | D23: Financing Quantum | E23: Margin Factor | J23: Purchase Deposit | K23: Grade A | L23: Grade B | M23: Grade C
E24: IM Factor | F24: MM Factor | G24: FM Factor | J24: Cash | K24: 3.5 | L24: 2 | M24: 1
C25: A | D25: 0.7 | E25: 0.2857 | F25: 0.2308 | G25: 0.1667 | J25: Grade A | K25: 2.5 | L25: 1.428 | M25: 0.714
C26: B | D26: 0.5 | E26: 0.5 | F26: 0.4615 | G26: 0.4167 | J26: Grade B | K26: 1.75 | L26: 1 | M26: 0.5
C27: C | D27: 0 | E27: 1 | F27: 1 | G27: 1 | J27: Grade C | K27: 0 | L27: 0 | M27: 0
C30: Strategy
F31: Buy A | G31: Buy B | H31: Buy C
C32: F | D32: 下注比率 | E32: =(E34*E33-E35)/E33 -> 0.3037037 | F32: =$E$32*D19 -> 5226.7826 | G32: =$E$32*E19 -> 2986.7329 | H32: =$E$32*F19 -> 1493.3664
C33: B | D33: 赔率 | E33: 1.35
C34: P | D34: 估算胜率 | E34: 0.6
C35: Q | D35: 失败概率 | E35: =1-E34 -> 0.4
C36: G | D36: 目标 (止盈) | E36: 100 | F36: =$E$36/F32 -> 0.019132229 | G36: =$E$36/G32 -> 0.0334814 | H36: =$E$36/H32 -> 0.066962801
C37: L | D37: 目标 (止损) | E37: =E36/E33 -> 74.074074 | F37: =-$E$37/F32 -> -0.014172021 | G37: =-$E$37/G32 -> -0.024801037 | H37: =-$E$37/H32 -> -0.049602075
C40: 胜率估算
D41: 基本胜率 | E41: 0.5
D42: 最高增率 | E42: 0.1
C44: 比重 | D44: 涨跌 | E44: -0.03 | F44: -0.02 | G44: -0.01 | H44: 0 | I44: 0.01 | J44: 0.02 | K44: 0.03
C45: 0.3 | D45: 大盘 | E45: -1 | F45: -0.75 | G45: 0.5 | H45: 0.25 | I45: 0.5 | J45: 0.75 | K45: 1
E46: =$E$42*$C$45*E45 -> -0.03 | F46: =$E$42*$C$45*F45 -> -0.0225 | G46: =$E$42*$C$45*G45 -> 0.015 | H46: =$E$42*$C$45*H45 -> 0.0075 | I46: =$E$42*$C$45*I45 -> 0.015 | J46: =$E$42*$C$45*J45 -> 0.0225 | K46: =$E$42*$C$45*K45 -> 0.03
C47: 0.4 | D47: 个股 | E47: 1 | F47: 0.5 | G47: 0.25 | H47: 0 | I47: 0.25 | J47: 1 | K47: 0.75
E48: =$E$42*$C$47*E47 -> 0.04 | F48: =$E$42*$C$47*F47 -> 0.02 | G48: =$E$42*$C$47*G47 -> 0.01 | H48: =$E$42*$C$47*H47 -> 0 | I48: =$E$42*$C$47*I47 -> 0.01 | J48: =$E$42*$C$47*J47 -> 0.04 | K48: =$E$42*$C$47*K47 -> 0.03
C49: 0.3 | D49: 个股振幅 | E49: 0.01 | F49: 0.02 | G49: 0.03 | H49: 0.04 | I49: 0.05 | J49: 0.06 | K49: 0.07
E50: 0 | F50: 0.5 | G50: 1 | H50: 0.75 | I50: 0.5 | J50: 0.25 | K50: 0
E51: =$E$42*$C$49*E50 -> 0 | F51: =$E$42*$C$49*F50 -> 0.015 | G51: =$E$42*$C$49*G50 -> 0.03 | H51: =$E$42*$C$49*H50 -> 0.0225 | I51: =$E$42*$C$49*I50 -> 0.015 | J51: =$E$42*$C$49*J50 -> 0.0075 | K51: =$E$42*$C$49*K50 -> 0

Sheet IndoStock
E1: Return | F1: Realized Gain
B2: Cash in | C2: 25000000 | E2: =F2/C2 -> -0.0094 | F2: =K11 -> -235000
B3: Investment | C3: =I8+I9 -> 4815000 | D3: =C3/C2 -> 0.1926
B4: Balance | C4: =C2-C3 -> 20185000 | D4: =C4/C2 -> 0.8074
B7: Stock Name | C7: Market | D7: Currency | E7: Buy Price | F7: Quantity | G7: Fee | H7: Average Price | I7: Total | J7: Current Price | K7: Gain/Loss | M7: Date
B8: #VALUE! | C8: IDX | D8: IDR | E8: 4560 | F8: =5*100 -> 500 | G8: =25000*2 -> 50000 | H8: =((E8*F8)+G8)/F8 -> 4660 | I8: =H8*F8 -> 2330000 | J8: 4550 | K8: =(J8-H8)*F8 -> -55000 | L8: =K8/I8 -> -0.02360515 | M8: 44014 | N8: Open
B9: #VALUE! | C9: IDX | D9: IDR | E9: 4870 | F9: =5*100 -> 500 | G9: =25000*2 -> 50000 | H9: =((E9*F9)+G9)/F9 -> 4970 | I9: =H9*F9 -> 2485000 | J9: 4610 | K9: =(J9-H9)*F9 -> -180000 | L9: =K9/I9 -> -0.072434608 | M9: 44014 | N9: Open
G11: =SUM(G8:G10) -> 100000 | K11: =SUM(K8:K10) -> -235000
B15: #VALUE! | C15: IDX | D15: IDR | E15: =E8 -> 4560 | F15: =F8 -> 500 | G15: =G8 -> 50000 | H15: =((E15*F15)+G15)/F15 -> 4660 | I15: =H15*F15 -> 2330000 | J15: 4560 | K15: =(J15-H15)*F15 -> -50000 | L15: =K15/I15 -> -0.021459227 | M15: 1st
B16: =E16/E15 -> 0.8004386 | C16: IDX | D16: IDR | E16: 3650 | F16: 800 | G16: =G15 -> 50000 | H16: =((E16*F16)+G16)/F16 -> 3712.5 | I16: =H16*F16 -> 2970000 | M16: 2nd
B17: =E17/E16 -> 0.79452055 | C17: IDX | D17: IDR | E17: 2900 | F17: =F16*2 -> 1600 | G17: =G16 -> 50000 | H17: =((E17*F17)+G17)/F17 -> 2931.25 | I17: =H17*F17 -> 4690000 | M17: 3rd
C18: IDX | D18: IDR | E18: =(E15*F15+E16*F16+E17*F17)/SUM(F15:F17) -> 3393.1034 | F18: =SUM(F15:F17) -> 2900 | G18: =SUM(G15:G17) -> 150000 | H18: =((E18*F18)+G18)/F18 -> 3444.8276 | I18: =H18*F18 -> 9990000 | J18: =E17 -> 2900 | K18: =(J18-H18)*F18 -> -1580000 | L18: =K18/I18 -> -0.15815816 | M18: Total
B21: #VALUE! | C21: IDX | D21: IDR | E21: =E9 -> 4870 | F21: =F9 -> 500 | G21: =G9 -> 50000 | H21: =((E21*F21)+G21)/F21 -> 4970 | I21: =H21*F21 -> 2485000 | J21: =J9 -> 4610 | K21: =(J21-H21)*F21 -> -180000 | L21: =K21/I21 -> -0.072434608 | M21: 1st
B22: =E22/E21 -> 0.80082136 | C22: IDX | D22: IDR | E22: 3900 | F22: 800 | G22: =G21 -> 50000 | H22: =((E22*F22)+G22)/F22 -> 3962.5 | I22: =H22*F22 -> 3170000 | M22: 2nd
B23: =E23/E22 -> 0.79487179 | C23: IDX | D23: IDR | E23: 3100 | F23: =F22*2 -> 1600 | G23: =G22 -> 50000 | H23: =((E23*F23)+G23)/F23 -> 3131.25 | I23: =H23*F23 -> 5010000 | M23: 3rd
C24: IDX | D24: IDR | E24: =(E21*F21+E22*F22+E23*F23)/SUM(F21:F23) -> 3625.8621 | F24: =SUM(F21:F23) -> 2900 | G24: =SUM(G21:G23) -> 150000 | H24: =((E24*F24)+G24)/F24 -> 3677.5862 | I24: =H24*F24 -> 10665000 | J24: =E23 -> 3100 | K24: =(J24-H24)*F24 -> -1675000 | L24: =K24/I24 -> -0.15705579 | M24: Total
B27: Worst | C27: Total Investment | E27: =SUM(E28:E29) -> 20655000 | F27: =E27/$C$2 -> 0.8262
B28: Scenario | C28: 1 | D28: =B15 -> #VALUE! | E28: =I18 -> 9990000 | F28: =E28/$E$27 -> 0.48366013
C29: 2 | D29: =B21 -> #VALUE! | E29: =I24 -> 10665000 | F29: =E29/$E$27 -> 0.51633987
C31: P/L | E31: =K18+K24 -> -3255000 | F31: =E31/E27 -> -0.15758896
C33: Cash Balance | E33: =C2-E27 -> 4345000 | F33: =E33/$C$2 -> 0.1738

Sheet US Index Contents
E3: S&P 500 | F3: Nasdaq | G3: DJI
D4: Information technology | E4: 0.276 | F4: 0.4839 | G4: 0.1756
D5: Health care | E5: 0.1344 | F5: 0.1021 | G5: 0.1
D6: Consumer discretionary | E6: 0.127 | F6: 0.1943 | G6: 0.1449
D7: Communication services | E7: 0.1079 | F7: 0.0072 | G7: 0.05
D8: Financials | E8: 0.1034 | F8: 0.0721 | G8: 0.05
D9: Industrials | E9: 0.0847 | F9: 0.0685 | G9: 0.2219
D10: Consumer staples | E10: 0.0655 | F10: 0.0551 | G10: 0.1025
D11: Utilities | E11: 0.0273 | F11: 0.0081 | G11: 0.01
D12: Materials | E12: 0.0264 | F12: 0.0032 | G12: 0.0091
D13: Real estate | E13: 0.0241 | G13: 0.0217
D14: Energy | E14: 0.0233 | F14: 0.0055 | G14: 0.1143
E15: =SUM(E4:E14) -> 1 | F15: =SUM(F4:F14) -> 1 | G15: =SUM(G4:G14) -> 1

Sheet Lost Return Ratio
C5: Lost | E5: Return | G5: Ratio
C6: 0.05 | E6: 0.053 | G6: =E6/C6 -> 1.06
C7: 0.1 | E7: 0.11 | G7: =E7/C7 -> 1.1
C8: 0.15 | E8: 0.18 | G8: =E8/C8 -> 1.2
C9: 0.2 | E9: 0.25 | G9: =E9/C9 -> 1.25
C10: 0.25 | E10: 0.33 | G10: =E10/C10 -> 1.32
C11: 0.3 | E11: 0.43 | G11: =E11/C11 -> 1.4333333
C12: 0.4 | E12: 0.67 | G12: =E12/C12 -> 1.675
C13: 0.5 | E13: 1 | G13: =E13/C13 -> 2

Sheet SG Watchlist
D3: No. | E3: Stock Name | F3: Price | G3: 52 wks high | H3: 52 wks low | I3: PE | J3: PB | K3: MA5 | L3: MA10 | M3: MA30 | N3: MA60 | O3: Good Price | P3: L/R Trade
D5: 1 | E5: #VALUE! | F5: {=_FV(E5,"Price")} -> 310.7 | G5: {=_FV(E5,"52 week high",TRUE)} -> 349.67 | H5: {=_FV(E5,"52 week low",TRUE)} -> 231.1 | I5: {=_FV(E5,"P/E",TRUE)} -> 33.0562 | K5: 230.38 | L5: 231.16 | M5: 236.92 | N5: 228.14 | O5: =IF(AND(F5<K5,F5<L5,F5<M5,F5<N5),"Yes","No") -> No
D6: 2 | E6: #VALUE! | F6: {=_FV(E6,"Price")} -> 223.59 | G6: {=_FV(E6,"52 week high",TRUE)} -> 384.33 | H6: {=_FV(E6,"52 week low",TRUE)} -> 185.82 | I6: {=_FV(E6,"P/E",TRUE)} -> 16.2107 | K6: 261.57 | L6: 259.95 | M6: 264.76 | N6: 266.65 | O6: =IF(AND(F6<K6,F6<L6,F6<M6,F6<N6),"Yes","No") -> Yes
D7: 3 | E7: #VALUE! | F7: {=_FV(E7,"Price")} -> 378.51 | G7: {=_FV(E7,"52 week high",TRUE)} -> 700.9894 | H7: {=_FV(E7,"52 week low",TRUE)} -> 329.82 | I7: {=_FV(E7,"P/E",TRUE)} -> 35.449 | K7: 506.39 | L7: 523.67 | M7: 539.18 | N7: 532.14 | O7: =IF(AND(F7<K7,F7<L7,F7<M7,F7<N7),"Yes","No") -> Yes
D8: 4 | E8: #VALUE! | F8: {=_FV(E8,"Price")} -> 175.6 | G8: {=_FV(E8,"52 week high",TRUE)} -> 182.94 | H8: {=_FV(E8,"52 week low",TRUE)} -> 118.86 | I8: {=_FV(E8,"P/E",TRUE)} -> 28.2588 | K8: 119.79 | L8: 121.61 | M8: 129.42 | N8: 130.16 | O8: =IF(AND(F8<K8,F8<L8,F8<M8,F8<N8),"Yes","No") -> No
D9: 5 | E9: #VALUE! | F9: {=_FV(E9,"Price")} -> 450.01 | G9: {=_FV(E9,"52 week high",TRUE)} -> 699.54 | H9: {=_FV(E9,"52 week low",TRUE)} -> 407.94 | I9: {=_FV(E9,"P/E",TRUE)} -> 44.6944 | K9: 435.45 | L9: 448.07 | M9: 471.11 | N9: 477.07 | O9: =IF(AND(F9<K9,F9<L9,F9<M9,F9<N9),"Yes","No") -> No
O10: =IF(AND(F10<K10,F10<L10,F10<M10,F10<N10),"Yes","No") -> No
D11: 6 | E11: #VALUE! | F11: {=_FV(E11,"Price")} -> 1091.84 | G11: {=_FV(E11,"52 week high",TRUE)} -> 1243.49 | H11: {=_FV(E11,"52 week low",TRUE)} -> 546.98 | I11: {=_FV(E11,"P/E",TRUE)} -> 221.8457 | K11: 624.8 | L11: 653.98 | M11: 758.87 | N11: 753.41 | O11: =IF(AND(F11<K11,F11<L11,F11<M11,F11<N11),"Yes","No") -> No
D12: 7 | E12: #VALUE! | F12: {=_FV(E12,"Price")} -> 282.19 | G12: {=_FV(E12,"52 week high",TRUE)} -> 346.47 | H12: {=_FV(E12,"52 week low",TRUE)} -> 127 | I12: {=_FV(E12,"P/E",TRUE)} -> 73.3655 | K12: 491.2 | L12: 513.8 | M12: 548.7 | N12: 539.41 | O12: =IF(AND(F12<K12,F12<L12,F12<M12,F12<N12),"Yes","No") -> Yes
D13: 8 | E13: #VALUE! | F13: {=_FV(E13,"Price")} -> 120.24 | G13: {=_FV(E13,"52 week high",TRUE)} -> 164.4599 | H13: {=_FV(E13,"52 week low",TRUE)} -> 72.5 | I13: {=_FV(E13,"P/E",TRUE)} -> 46.714 | K13: 77.25 | L13: 80.45 | M13: 86.15 | N13: 89.56 | O13: =IF(AND(F13<K13,F13<L13,F13<M13,F13<N13),"Yes","No") -> No
D14: 9 | E14: #VALUE! | F14: {=_FV(E14,"Price")} -> 158.45 | G14: {=_FV(E14,"52 week high",TRUE)} -> 193.58 | H14: {=_FV(E14,"52 week low",TRUE)} -> 122.165 | I14: {=_FV(E14,"P/E",TRUE)} -> 18.1595 | O14: =IF(AND(F14<K14,F14<L14,F14<M14,F14<N14),"Yes","No") -> No
D15: 10 | E15: #VALUE! | F15: {=_FV(E15,"Price")} -> 106.33 | G15: {=_FV(E15,"52 week high",TRUE)} -> 145 | H15: {=_FV(E15,"52 week low",TRUE)} -> 97.62 | I15: {=_FV(E15,"P/E",TRUE)} -> 25.6167 | O15: =IF(AND(F15<K15,F15<L15,F15<M15,F15<N15),"Yes","No") -> No
D16: 11 | E16: #VALUE! | F16: {=_FV(E16,"Price")} -> 79.86 | G16: {=_FV(E16,"52 week high",TRUE)} -> 98.45 | H16: {=_FV(E16,"52 week low",TRUE)} -> 65.67 | I16: {=_FV(E16,"P/E",TRUE)} -> 12.1791 | O16: =IF(AND(F16<K16,F16<L16,F16<M16,F16<N16),"Yes","No") -> No
D17: 12 | E17: #VALUE! | F17: {=_FV(E17,"Price")} -> 694.83 | G17: {=_FV(E17,"52 week high",TRUE)} -> 895.93 | H17: {=_FV(E17,"52 week low",TRUE)} -> 558.77 | I17: {=_FV(E17,"P/E",TRUE)} -> 42.5649 | O17: =IF(AND(F17<K17,F17<L17,F17<M17,F17<N17),"Yes","No") -> No
D18: 13 | E18: #VALUE! | F18: {=_FV(E18,"Price")} -> 51.51 | G18: {=_FV(E18,"52 week high",TRUE)} -> 68.49 | H18: {=_FV(E18,"52 week low",TRUE)} -> 43.625 | I18: {=_FV(E18,"P/E",TRUE)} -> 10.6038 | K18: 60.76 | L18: 60.9 | M18: 59.82 | N18: 55.78 | O18: =IF(AND(F18<K18,F18<L18,F18<M18,F18<N18),"Yes","No") -> Yes
D19: 14 | E19: #VALUE! | F19: {=_FV(E19,"Price")} -> 69.82 | G19: {=_FV(E19,"52 week high",TRUE)} -> 194.99 | H19: {=_FV(E19,"52 week low",TRUE)} -> 50.08 | I19: {=_FV(E19,"P/E",TRUE)} -> 0 | O19: =IF(AND(F19<K19,F19<L19,F19<M19,F19<N19),"Yes","No") -> No
D21: 15 | E21: #VALUE! | F21: {=_FV(E21,"Price")} -> 21.25 | G21: {=_FV(E21,"52 week high",TRUE)} -> 72.2 | H21: {=_FV(E21,"52 week low",TRUE)} -> 17.27 | I21: {=_FV(E21,"P/E",TRUE)} -> #VALUE! | O21: =IF(AND(F21<K21,F21<L21,F21<M21,F21<N21),"Yes","No") -> No
D22: 16 | E22: #VALUE! | F22: {=_FV(E22,"Price")} -> 17.33 | G22: {=_FV(E22,"52 week high",TRUE)} -> 75.15 | H22: {=_FV(E22,"52 week low",TRUE)} -> 13.01 | I22: {=_FV(E22,"P/E",TRUE)} -> 0 | O22: =IF(AND(F22<K22,F22<L22,F22<M22,F22<N22),"Yes","No") -> No
D23: 17 | E23: #VALUE! | F23: {=_FV(E23,"Price")} -> 39.12 | G23: {=_FV(E23,"52 week high",TRUE)} -> 73.34 | H23: {=_FV(E23,"52 week low",TRUE)} -> 31.3 | I23: {=_FV(E23,"P/E",TRUE)} -> 0 | O23: =IF(AND(F23<K23,F23<L23,F23<M23,F23<N23),"Yes","No") -> No
D24: 18 | E24: #VALUE! | F24: {=_FV(E24,"Price")} -> 37.59 | G24: {=_FV(E24,"52 week high",TRUE)} -> 65.94 | H24: {=_FV(E24,"52 week low",TRUE)} -> 33.94 | I24: {=_FV(E24,"P/E",TRUE)} -> #VALUE! | O24: =IF(AND(F24<K24,F24<L24,F24<M24,F24<N24),"Yes","No") -> No
D25: 19 | E25: #VALUE! | F25: {=_FV(E25,"Price")} -> 34.77 | G25: {=_FV(E25,"52 week high",TRUE)} -> 61.5 | H25: {=_FV(E25,"52 week low",TRUE)} -> 28.2777 | I25: {=_FV(E25,"P/E",TRUE)} -> 0 | O25: =IF(AND(F25<K25,F25<L25,F25<M25,F25<N25),"Yes","No") -> No
D27: 20 | E27: #VALUE! | F27: {=_FV(E27,"Price")} -> 138.72 | G27: {=_FV(E27,"52 week high",TRUE)} -> 191.67 | H27: {=_FV(E27,"52 week low",TRUE)} -> 128.38 | I27: {=_FV(E27,"P/E",TRUE)} -> 80.624 | O27: =IF(AND(F27<K27,F27<L27,F27<M27,F27<N27),"Yes","No") -> No
D28: 21 | E28: #VALUE! | F28: {=_FV(E28,"Price")} -> 128.04 | G28: {=_FV(E28,"52 week high",TRUE)} -> 148.93 | H28: {=_FV(E28,"52 week low",TRUE)} -> 117.58 | I28: {=_FV(E28,"P/E",TRUE)} -> 57.6207 | K28: 130.58 | L28: 132.49 | M28: 139.75 | N28: 140.55 | O28: =IF(AND(F28<K28,F28<L28,F28<M28,F28<N28),"Yes","No") -> Yes
D29: 22 | E29: #VALUE! | F29: {=_FV(E29,"Price")} -> 80.01 | G29: {=_FV(E29,"52 week high",TRUE)} -> 99.459 | H29: {=_FV(E29,"52 week low",TRUE)} -> 56.4 | I29: {=_FV(E29,"P/E",TRUE)} -> 23.2263 | O29: =IF(AND(F29<K29,F29<L29,F29<M29,F29<N29),"Yes","No") -> No
D30: 23 | E30: #VALUE! | F30: {=_FV(E30,"Price")} -> 64.8 | G30: {=_FV(E30,"52 week high",TRUE)} -> 71.7081 | H30: {=_FV(E30,"52 week low",TRUE)} -> 50.49 | I30: {=_FV(E30,"P/E",TRUE)} -> 13.7298 | O30: =IF(AND(F30<K30,F30<L30,F30<M30,F30<N30),"Yes","No") -> No
D31: 24 | E31: #VALUE! | F31: {=_FV(E31,"Price")} -> 158.16 | G31: {=_FV(E31,"52 week high",TRUE)} -> 168.039 | H31: {=_FV(E31,"52 week low",TRUE)} -> 127.94 | I31: {=_FV(E31,"P/E",TRUE)} -> 36.797 | O31: =IF(AND(F31<K31,F31<L31,F31<M31,F31<N31),"Yes","No") -> No
D32: 25 | E32: #VALUE! | F32: {=_FV(E32,"Price")} -> 314.28 | G32: {=_FV(E32,"52 week high",TRUE)} -> 420.61 | H32: {=_FV(E32,"52 week low",TRUE)} -> 298.4 | I32: {=_FV(E32,"P/E",TRUE)} -> 20.2537 | O32: =IF(AND(F32<K32,F32<L32,F32<M32,F32<N32),"Yes","No") -> No
D33: 26 | E33: #VALUE! | F33: {=_FV(E33,"Price")} -> 226.3 | G33: {=_FV(E33,"52 week high",TRUE)} -> 240.14 | H33: {=_FV(E33,"52 week low",TRUE)} -> 185.15 | I33: {=_FV(E33,"P/E",TRUE)} -> 22.2614 | O33: =IF(AND(F33<K33,F33<L33,F33<M33,F33<N33),"Yes","No") -> No
D34: 27 | E34: #VALUE! | F34: {=_FV(E34,"Price")} -> 146 | G34: {=_FV(E34,"52 week high",TRUE)} -> 152.57 | H34: {=_FV(E34,"52 week low",TRUE)} -> 132.01 | I34: {=_FV(E34,"P/E",TRUE)} -> 29.939 | K34: 130.15 | L34: 129.72 | M34: 137.34 | N34: 141.48 | O34: =IF(AND(F34<K34,F34<L34,F34<M34,F34<N34),"Yes","No") -> No
D35: 28 | E35: #VALUE! | F35: {=_FV(E35,"Price")} -> 98.11 | G35: {=_FV(E35,"52 week high",TRUE)} -> 210 | H35: {=_FV(E35,"52 week low",TRUE)} -> 73.12 | I35: {=_FV(E35,"P/E",TRUE)} -> 0 | O35: =IF(AND(F35<K35,F35<L35,F35<M35,F35<N35),"Yes","No") -> No
D36: 29 | E36: #VALUE! | F36: {=_FV(E36,"Price")} -> 156.5 | G36: {=_FV(E36,"52 week high",TRUE)} -> 195.825 | H36: {=_FV(E36,"52 week low",TRUE)} -> 133.54 | I36: {=_FV(E36,"P/E",TRUE)} -> 34.7138 | O36: =IF(AND(F36<K36,F36<L36,F36<M36,F36<N36),"Yes","No") -> No
D37: 30 | E37: #VALUE! | F37: {=_FV(E37,"Price")} -> 23.87 | G37: {=_FV(E37,"52 week high",TRUE)} -> 33.88 | H37: {=_FV(E37,"52 week low",TRUE)} -> 22.02 | I37: {=_FV(E37,"P/E",TRUE)} -> 8.6349 | O37: =IF(AND(F37<K37,F37<L37,F37<M37,F37<N37),"Yes","No") -> No
D38: 31 | E38: #VALUE! | F38: {=_FV(E38,"Price")} -> 314.28 | G38: {=_FV(E38,"52 week high",TRUE)} -> 420.61 | H38: {=_FV(E38,"52 week low",TRUE)} -> 298.4 | I38: {=_FV(E38,"P/E",TRUE)} -> 20.2537 | K38: 257.65 | L38: 257.3 | M38: 268.26 | N38: 268.9 | O38: =IF(AND(F38<K38,F38<L38,F38<M38,F38<N38),"Yes","No") -> No
D40: 31 | E40: #VALUE! | F40: {=_FV(E40,"Price")} -> 115.09 | G40: {=_FV(E40,"52 week high",TRUE)} -> 245.69 | H40: {=_FV(E40,"52 week low",TRUE)} -> 73.28 | I40: {=_FV(E40,"P/E",TRUE)} -> 30.6421 | K40: 232.7 | L40: 235.38 | M40: 253.47 | N40: 249.78 | O40: =IF(AND(F40<K40,F40<L40,F40<M40,F40<N40),"Yes","No") -> Yes
D41: 32 | E41: #VALUE! | F41: {=_FV(E41,"Price")} -> 59.77 | G41: {=_FV(E41,"52 week high",TRUE)} -> 92.69 | H41: {=_FV(E41,"52 week low",TRUE)} -> 41.56 | I41: {=_FV(E41,"P/E",TRUE)} -> 24.9394 | K41: 89.12 | L41: 92.08 | M41: 95.61 | N41: 91.71 | O41: =IF(AND(F41<K41,F41<L41,F41<M41,F41<N41),"Yes","No") -> Yes
D42: 33 | E42: #VALUE! | F42: {=_FV(E42,"Price")} -> 43.67 | G42: {=_FV(E42,"52 week high",TRUE)} -> 152.06 | H42: {=_FV(E42,"52 week low",TRUE)} -> 23.21 | I42: {=_FV(E42,"P/E",TRUE)} -> 53.7111 | O42: =IF(AND(F42<K42,F42<L42,F42<M42,F42<N42),"Yes","No") -> No
D43: 34 | E43: #VALUE! | F43: {=_FV(E43,"Price")} -> 23.45 | G43: {=_FV(E43,"52 week high",TRUE)} -> 42.04 | H43: {=_FV(E43,"52 week low",TRUE)} -> 14.29 | I43: {=_FV(E43,"P/E",TRUE)} -> 25.7941 | O43: =IF(AND(F43<K43,F43<L43,F43<M43,F43<N43),"Yes","No") -> No
D44: 35 | E44: #VALUE! | F44: {=_FV(E44,"Price")} -> 6 | G44: {=_FV(E44,"52 week high",TRUE)} -> 14.97 | H44: {=_FV(E44,"52 week low",TRUE)} -> 4.085 | I44: {=_FV(E44,"P/E",TRUE)} -> 5.5603 | O44: =IF(AND(F44<K44,F44<L44,F44<M44,F44<N44),"Yes","No") -> No
D45: 36 | E45: #VALUE! | F45: {=_FV(E45,"Price")} -> 1.97 | G45: {=_FV(E45,"52 week high",TRUE)} -> 39.01 | H45: {=_FV(E45,"52 week low",TRUE)} -> 1.2621 | I45: {=_FV(E45,"P/E",TRUE)} -> 0 | O45: =IF(AND(F45<K45,F45<L45,F45<M45,F45<N45),"Yes","No") -> No
D46: 37 | E46: #VALUE! | F46: {=_FV(E46,"Price")} -> 147.45 | G46: {=_FV(E46,"52 week high",TRUE)} -> 228.53 | H46: {=_FV(E46,"52 week low",TRUE)} -> 102.18 | I46: {=_FV(E46,"P/E",TRUE)} -> 31.8459 | O46: =IF(AND(F46<K46,F46<L46,F46<M46,F46<N46),"Yes","No") -> No
D47: 38 | E47: #VALUE! | F47: {=_FV(E47,"Price")} -> 93.82 | G47: {=_FV(E47,"52 week high",TRUE)} -> 120.84 | H47: {=_FV(E47,"52 week low",TRUE)} -> 68.62 | I47: {=_FV(E47,"P/E",TRUE)} -> 24.2009 | O47: =IF(AND(F47<K47,F47<L47,F47<M47,F47<N47),"Yes","No") -> No
D48: 39 | E48: #VALUE! | F48: {=_FV(E48,"Price")} -> 12.31 | G48: {=_FV(E48,"52 week high",TRUE)} -> 62.2 | H48: {=_FV(E48,"52 week low",TRUE)} -> 7.31 | I48: {=_FV(E48,"P/E",TRUE)} -> 0 | O48: =IF(AND(F48<K48,F48<L48,F48<M48,F48<N48),"Yes","No") -> No
D49: 40 | E49: #VALUE! | F49: {=_FV(E49,"Price")} -> 21.21 | G49: {=_FV(E49,"52 week high",TRUE)} -> 55.13 | H49: {=_FV(E49,"52 week low",TRUE)} -> 13.01 | I49: {=_FV(E49,"P/E",TRUE)} -> 0 | O49: =IF(AND(F49<K49,F49<L49,F49<M49,F49<N49),"Yes","No") -> No
D50: 41 | E50: #VALUE! | F50: {=_FV(E50,"Price")} -> 26.48 | G50: {=_FV(E50,"52 week high",TRUE)} -> 37.45 | H50: {=_FV(E50,"52 week low",TRUE)} -> 15.98 | I50: {=_FV(E50,"P/E",TRUE)} -> #VALUE! | O50: =IF(AND(F50<K50,F50<L50,F50<M50,F50<N50),"Yes","No") -> No
D51: 42 | E51: #VALUE! | F51: {=_FV(E51,"Price")} -> 27.13 | G51: {=_FV(E51,"52 week high",TRUE)} -> 56.45 | H51: {=_FV(E51,"52 week low",TRUE)} -> 18.01 | I51: {=_FV(E51,"P/E",TRUE)} -> 0 | O51: =IF(AND(F51<K51,F51<L51,F51<M51,F51<N51),"Yes","No") -> No
D52: 43 | E52: #VALUE! | F52: {=_FV(E52,"Price")} -> 9.94 | G52: {=_FV(E52,"52 week high",TRUE)} -> 39.39 | H52: {=_FV(E52,"52 week low",TRUE)} -> 7.4947 | I52: {=_FV(E52,"P/E",TRUE)} -> #VALUE! | O52: =IF(AND(F52<K52,F52<L52,F52<M52,F52<N52),"Yes","No") -> No
D53: 44 | E53: #VALUE! | F53: {=_FV(E53,"Price")} -> 28.54 | G53: {=_FV(E53,"52 week high",TRUE)} -> 129.24 | H53: {=_FV(E53,"52 week low",TRUE)} -> 14.93 | I53: {=_FV(E53,"P/E",TRUE)} -> #VALUE! | O53: =IF(AND(F53<K53,F53<L53,F53<M53,F53<N53),"Yes","No") -> No
... D62: 52 | E62: #VALUE! | F62: {=_FV(E62,"Price")} -> 188.16 | G62: {=_FV(E62,"52 week high",TRUE)} -> 260.48 | H62: {=_FV(E62,"52 week low",TRUE)} -> 167.58 | I62: {=_FV(E62,"P/E",TRUE)} -> 0 | O62: =IF(AND(F62<K62,F62<L62,F62<M62,F62<N62),"Yes","No") -> No
D63: 53 | E63: #VALUE! | F63: {=_FV(E63,"Price")} -> 444.98 | G63: {=_FV(E63,"52 week high",TRUE)} -> 479.99 | H63: {=_FV(E63,"52 week low",TRUE)} -> 324.2278 | I63: {=_FV(E63,"P/E",TRUE)} -> 19.5426 | K63: 333.71 | L63: 330.16 | M63: 325.95 | N63: 330.51 | O63: =IF(AND(F63<K63,F63<L63,F63<M63,F63<N63),"Yes","No") -> No
D64: 54 | E64: #VALUE! | F64: {=_FV(E64,"Price")} -> 78.54 | G64: {=_FV(E64,"52 week high",TRUE)} -> 98.27 | H64: {=_FV(E64,"52 week low",TRUE)} -> 61.45 | I64: {=_FV(E64,"P/E",TRUE)} -> 0 | O64: =IF(AND(F64<K64,F64<L64,F64<M64,F64<N64),"Yes","No") -> No
D65: 55 | E65: #VALUE! | F65: {=_FV(E65,"Price")} -> 19.4 | G65: {=_FV(E65,"52 week high",TRUE)} -> 31.52 | H65: {=_FV(E65,"52 week low",TRUE)} -> 14.94 | I65: {=_FV(E65,"P/E",TRUE)} -> 0 | O65: =IF(AND(F65<K65,F65<L65,F65<M65,F65<N65),"Yes","No") -> No
D66: 56 | E66: #VALUE! | F66: {=_FV(E66,"Price")} -> 20.54 | G66: {=_FV(E66,"52 week high",TRUE)} -> 33.95 | H66: {=_FV(E66,"52 week low",TRUE)} -> 14.9 | I66: {=_FV(E66,"P/E",TRUE)} -> 0 | O66: =IF(AND(F66<K66,F66<L66,F66<M66,F66<N66),"Yes","No") -> No
D67: 57 | E67: #VALUE! | F67: {=_FV(E67,"Price")} -> 166.35 | G67: {=_FV(E67,"52 week high",TRUE)} -> 174.76 | H67: {=_FV(E67,"52 week low",TRUE)} -> 92.86 | I67: {=_FV(E67,"P/E",TRUE)} -> 20.4493 | O67: =IF(AND(F67<K67,F67<L67,F67<M67,F67<N67),"Yes","No") -> No
D68: 58 | E68: #VALUE! | F68: {=_FV(E68,"Price")} -> 56.64 | G68: {=_FV(E68,"52 week high",TRUE)} -> 63.24 | H68: {=_FV(E68,"52 week low",TRUE)} -> 21.62 | I68: {=_FV(E68,"P/E",TRUE)} -> 27.5456 | O68: =IF(AND(F68<K68,F68<L68,F68<M68,F68<N68),"Yes","No") -> No
D69: 59 | E69: #VALUE! | F69: {=_FV(E69,"Price")} -> 82.81 | G69: {=_FV(E69,"52 week high",TRUE)} -> 91.505 | H69: {=_FV(E69,"52 week low",TRUE)} -> 52.1 | I69: {=_FV(E69,"P/E",TRUE)} -> 15.3983 | O69: =IF(AND(F69<K69,F69<L69,F69<M69,F69<N69),"Yes","No") -> No
D71: 60 | E71: #VALUE! | F71: {=_FV(E71,"Price")} -> 177.83 | G71: {=_FV(E71,"52 week high",TRUE)} -> 179.92 | H71: {=_FV(E71,"52 week low",TRUE)} -> 155.72 | I71: {=_FV(E71,"P/E",TRUE)} -> 22.7645 | O71: =IF(AND(F71<K71,F71<L71,F71<M71,F71<N71),"Yes","No") -> No
D72: 61 | E72: #VALUE! | F72: {=_FV(E72,"Price")} -> 119.99 | G72: {=_FV(E72,"52 week high",TRUE)} -> 142.6 | H72: {=_FV(E72,"52 week low",TRUE)} -> 105.36 | I72: {=_FV(E72,"P/E",TRUE)} -> 30.3482 | O72: =IF(AND(F72<K72,F72<L72,F72<M72,F72<N72),"Yes","No") -> No
D73: 62 | E73: #VALUE! | F73: {=_FV(E73,"Price")} -> 59.18 | G73: {=_FV(E73,"52 week high",TRUE)} -> 74.12 | H73: {=_FV(E73,"52 week low",TRUE)} -> 57.185 | I73: {=_FV(E73,"P/E",TRUE)} -> 11.993 | O73: =IF(AND(F73<K73,F73<L73,F73<M73,F73<N73),"Yes","No") -> No
D74: 63 | E74: #VALUE! | F74: {=_FV(E74,"Price")} -> 86.99 | G74: {=_FV(E74,"52 week high",TRUE)} -> 95.17 | H74: {=_FV(E74,"52 week low",TRUE)} -> 79.09 | I74: {=_FV(E74,"P/E",TRUE)} -> 8.1686 | O74: =IF(AND(F74<K74,F74<L74,F74<M74,F74<N74),"Yes","No") -> No
D75: 64 | E75: #VALUE! | F75: {=_FV(E75,"Price")} -> 81.21 | G75: {=_FV(E75,"52 week high",TRUE)} -> 91.4 | H75: {=_FV(E75,"52 week low",TRUE)} -> 69.4644 | I75: {=_FV(E75,"P/E",TRUE)} -> 16.6891 | O75: =IF(AND(F75<K75,F75<L75,F75<M75,F75<N75),"Yes","No") -> No
D76: 65 | E76: #VALUE! | F76: {=_FV(E76,"Price")} -> 693.4 | G76: {=_FV(E76,"52 week high",TRUE)} -> 697.01 | H76: {=_FV(E76,"52 week low",TRUE)} -> 451.6 | I76: {=_FV(E76,"P/E",TRUE)} -> 9.289 | K76: 462.54 | L76: 458.11 | M76: 478.46 | N76: 490.3 | O76: =IF(AND(F76<K76,F76<L76,F76<M76,F76<N76),"Yes","No") -> No
D77: 66 | E77: #VALUE! | F77: {=_FV(E77,"Price")} -> 53.28 | G77: {=_FV(E77,"52 week high",TRUE)} -> 61.71 | H77: {=_FV(E77,"52 week low",TRUE)} -> 35.76 | I77: {=_FV(E77,"P/E",TRUE)} -> 13.5663 | K77: 34.46 | L77: 34.12 | M77: 34.61 | N77: 35.77 | O77: =IF(AND(F77<K77,F77<L77,F77<M77,F77<N77),"Yes","No") -> No
D78: 67 | E78: #VALUE! | F78: {=_FV(E78,"Price")} -> 173.08 | G78: {=_FV(E78,"52 week high",TRUE)} -> 497.49 | H78: {=_FV(E78,"52 week low",TRUE)} -> 117.3411 | I78: {=_FV(E78,"P/E",TRUE)} -> 6.1237 | O78: =IF(AND(F78<K78,F78<L78,F78<M78,F78<N78),"Yes","No") -> No
D79: 68 | E79: #VALUE! | F79: {=_FV(E79,"Price")} -> 255.72 | G79: {=_FV(E79,"52 week high",TRUE)} -> 258.25 | H79: {=_FV(E79,"52 week low",TRUE)} -> 176.36 | I79: {=_FV(E79,"P/E",TRUE)} -> 28.3273 | O79: =IF(AND(F79<K79,F79<L79,F79<M79,F79<N79),"Yes","No") -> No
D80: 69 | E80: #VALUE! | F80: {=_FV(E80,"Price")} -> 65.38 | G80: {=_FV(E80,"52 week high",TRUE)} -> 66.06 | H80: {=_FV(E80,"52 week low",TRUE)} -> 48.26 | I80: {=_FV(E80,"P/E",TRUE)} -> 479.642 | O80: =IF(AND(F80<K80,F80<L80,F80<M80,F80<N80),"Yes","No") -> No
D81: 70 | E81: #VALUE! | F81: {=_FV(E81,"Price")} -> 437.32 | G81: {=_FV(E81,"52 week high",TRUE)} -> 543.85 | H81: {=_FV(E81,"52 week low",TRUE)} -> 347.88 | I81: {=_FV(E81,"P/E",TRUE)} -> 85.3359 | O81: =IF(AND(F81<K81,F81<L81,F81<M81,F81<N81),"Yes","No") -> No

Sheet ID Watchlist
D3: No. | E3: Stock Name | F3: Price | G3: 52 wks high | H3: 52 wks low | I3: PE | J3: PB | K3: MA5 | L3: MA10 | M3: MA20 | N3: MA50 | O3: Good Price
D5: 1 | E5: #VALUE! | F5: {=_FV(E5,"Price")} -> 6550 | G5: {=_FV(E5,"52 week high",TRUE)} -> 6775 | H5: {=_FV(E5,"52 week low",TRUE)} -> 4640 | I5: 11.3 | J5: {=_FV(E5,"Market cap",TRUE)} -> 271239800000000 | K5: 5550 | L5: 5635 | M5: 5721 | N5: 5225 | O5: =IF(AND(F5<K5,F5<L5,F5<M5,F5<N5),"Yes","No") -> No
D6: 2 | E6: #VALUE! | F6: {=_FV(E6,"Price")} -> 8375 | G6: {=_FV(E6,"52 week high",TRUE)} -> 8550 | H6: {=_FV(E6,"52 week low",TRUE)} -> 4560 | I6: 15.08 | J6: {=_FV(E6,"Market cap",TRUE)} -> 156928400000000 | K6: 6235 | L6: 6050 | M6: 5718 | N6: 5090 | O6: =IF(AND(F6<K6,F6<L6,F6<M6,F6<N6),"Yes","No") -> No
D7: 3 | E7: #VALUE! | F7: {=_FV(E7,"Price")} -> 4560 | G7: {=_FV(E7,"52 week high",TRUE)} -> 4700 | H7: {=_FV(E7,"52 week low",TRUE)} -> 3000 | I7: 17 | J7: {=_FV(E7,"Market cap",TRUE)} -> 455686200000000 | K7: 3340 | L7: 3304 | M7: 3148 | N7: 2872 | O7: =IF(AND(F7<K7,F7<L7,F7<M7,F7<N7),"Yes","No") -> No
D8: 4 | E8: #VALUE! | F8: {=_FV(E8,"Price")} -> 4690 | G8: {=_FV(E8,"52 week high",TRUE)} -> 4860 | H8: {=_FV(E8,"52 week low",TRUE)} -> 3500 | I8: 22 | J8: {=_FV(E8,"Market cap",TRUE)} -> 709705300000000 | K8: 4232 | L8: 4182 | M8: 4030 | N8: 3538 | O8: =IF(AND(F8<K8,F8<L8,F8<M8,F8<N8),"Yes","No") -> No
D10: 5 | E10: #VALUE! | F10: {=_FV(E10,"Price")} -> 170 | G10: {=_FV(E10,"52 week high",TRUE)} -> 224 | H10: {=_FV(E10,"52 week low",TRUE)} -> 165 | I10: 3.71 | J10: {=_FV(E10,"Market cap",TRUE)} -> 5475775000000 | K10: 228 | L10: 224 | M10: 215 | N10: 198 | O10: =IF(AND(F10<K10,F10<L10,F10<M10,F10<N10),"Yes","No") -> Yes
D11: 6 | E11: #VALUE! | F11: {=_FV(E11,"Price")} -> 26025 | G11: {=_FV(E11,"52 week high",TRUE)} -> 27750 | H11: {=_FV(E11,"52 week low",TRUE)} -> 18525 | I11: 11.26 | J11: {=_FV(E11,"Market cap",TRUE)} -> 99221590000000 | K11: 24225 | L11: 23268 | M11: 22151 | N11: 22218 | O11: =IF(AND(F11<K11,F11<L11,F11<M11,F11<N11),"Yes","No") -> No
D12: 7 | E12: #VALUE! | F12: {=_FV(E12,"Price")} -> 840 | G12: {=_FV(E12,"52 week high",TRUE)} -> 920 | H12: {=_FV(E12,"52 week low",TRUE)} -> 610 | I12: 187.13 | J12: {=_FV(E12,"Market cap",TRUE)} -> 13861000000000 | K12: 831 | L12: 817 | M12: 775 | N12: 676 | O12: =IF(AND(F12<K12,F12<L12,F12<M12,F12<N12),"Yes","No") -> No
D13: 8 | E13: #VALUE! | F13: {=_FV(E13,"Price")} -> 6675 | G13: {=_FV(E13,"52 week high",TRUE)} -> 11650 | H13: {=_FV(E13,"52 week low",TRUE)} -> 6150 | I13: 26.3 | J13: {=_FV(E13,"Market cap",TRUE)} -> 40186050000000 | K13: 11885 | L13: 11765 | M13: 11279 | N13: 10073 | O13: =IF(AND(F13<K13,F13<L13,F13<M13,F13<N13),"Yes","No") -> Yes

Sheet StockSelection
G1: =F5/G5 -> 8.7254605 | H1: =G1*15 -> 130.88191
D3: Class | E3: Stock | F3: Current Price | G3: PE | H3: 52wk High | I3: 52wk Low | J3: POEMS | K3: MarketBeat | L3: Forward PE | M3: EPS | N3: FPE Price | O3: Lowest Price | P3: Median Price | Q3: Upside | R3: Downside | S3: PE 5 yr Avg | T3: PE Multiple
D4: A | E4: #VALUE! | F4: {=_FV(E4,"Price")} -> 175.6 | G4: {=_FV(E4,"P/E",TRUE)} -> 28.2588 | H4: {=_FV(E4,"52 week high",TRUE)} -> 182.94 | I4: {=_FV(E4,"52 week low",TRUE)} -> 118.86 | J4: 157.97 | K4: 147.34 | L4: 28.68 | M4: 3.31 | N4: =L4*M4 -> 94.9308 | O4: =MIN(J4,K4,N4,P4) -> 94.9308 | P4: =AVERAGE(J4,K4,N4) -> 133.4136 | Q4: =(P4-F4)/F4 -> -0.24024146 | R4: =(O4-F4)/F4 -> -0.4593918 | S4: 19.15 | T4: =G4/S4 -> 1.4756554
E5: #VALUE! | F5: {=_FV(E5,"Price")} -> 158.45 | G5: {=_FV(E5,"P/E",TRUE)} -> 18.1595 | H5: {=_FV(E5,"52 week high",TRUE)} -> 193.58 | I5: {=_FV(E5,"52 week low",TRUE)} -> 122.165 | J5: 167.37 | K5: 166.6 | L5: 17.97 | M5: 4.58 | N5: =L5*M5 -> 82.3026 | O5: =MIN(J5,K5,N5,P5) -> 82.3026 | P5: =AVERAGE(J5,K5,N5) -> 138.75753 | Q5: =(P5-F5)/F5 -> -0.1242819 | R5: =(O5-F5)/F5 -> -0.48057684 | S5: 22.97 | T5: =G5/S5 -> 0.79057466
E6: #VALUE! | F6: {=_FV(E6,"Price")} -> 106.33 | G6: {=_FV(E6,"P/E",TRUE)} -> 25.6167 | H6: {=_FV(E6,"52 week high",TRUE)} -> 145 | I6: {=_FV(E6,"52 week low",TRUE)} -> 97.62 | J6: n/a | K6: 106.75 | L6: 31.03 | M6: =99.85/28.5 -> 3.5035088 | N6: =L6*M6 -> 108.71388 | O6: =MIN(K6,N6,P6) -> 106.75 | P6: =AVERAGE(K6,N6) -> 107.73194 | Q6: =(P6-F6)/F6 -> 0.013184789 | R6: =(O6-F6)/F6 -> 0.0039499671 | S6: 17.53 | T6: =G6/S6 -> 1.4613063
E7: #VALUE! | F7: {=_FV(E7,"Price")} -> 223.59 | G7: {=_FV(E7,"P/E",TRUE)} -> 16.2107 | H7: {=_FV(E7,"52 week high",TRUE)} -> 384.33 | I7: {=_FV(E7,"52 week low",TRUE)} -> 185.82 | J7: 368.9 | K7: 369.73 | L7: 26.32 | M7: 10.22 | N7: =L7*M7 -> 268.9904 | O7: =MIN(J7,K7,N7,P7) -> 268.9904 | P7: =AVERAGE(J7,K7,N7) -> 335.87347 | Q7: =(P7-F7)/F7 -> 0.50218465 | R7: =(O7-F7)/F7 -> 0.20305201 | S7: 32.65 | T7: =G7/S7 -> 0.49649923
E8: #VALUE! | F8: {=_FV(E8,"Price")} -> 3379.81 | G8: {=_FV(E8,"P/E",TRUE)} -> 52.2267 | H8: {=_FV(E8,"52 week high",TRUE)} -> 3773.0782 | I8: {=_FV(E8,"52 week low",TRUE)} -> 2671.45 | J8: 4196.39 | K8: 4112.06 | L8: 60.49 | M8: 42.64 | N8: =L8*M8 -> 2579.2936 | O8: =MIN(J8,K8,N8,P8) -> 2579.2936 | P8: =AVERAGE(J8,K8,N8) -> 3629.2479 | Q8: =(P8-F8)/F8 -> 0.073802334 | R8: =(O8-F8)/F8 -> -0.23685249 | S8: 136.98 | T8: =G8/S8 -> 0.38127245
E9: #VALUE! | F9: {=_FV(E9,"Price")} -> 450.01 | G9: {=_FV(E9,"P/E",TRUE)} -> 44.6944 | H9: {=_FV(E9,"52 week high",TRUE)} -> 699.54 | I9: {=_FV(E9,"52 week low",TRUE)} -> 407.94 | J9: 571.9 | K9: 557.13 | L9: 41.01 | M9: 10.94 | N9: =L9*M9 -> 448.6494 | O9: =MIN(J9,K9,N9,P9) -> 448.6494 | P9: =AVERAGE(J9,K9,N9) -> 525.89313 | Q9: =(P9-F9)/F9 -> 0.16862544 | R9: =(O9-F9)/F9 -> -0.0030234884 | S9: 50.83 | T9: =G9/S9 -> 0.87929176
E10: #VALUE! | F10: {=_FV(E10,"Price")} -> 146 | G10: {=_FV(E10,"P/E",TRUE)} -> 29.939 | H10: {=_FV(E10,"52 week high",TRUE)} -> 152.57 | I10: {=_FV(E10,"52 week low",TRUE)} -> 132.01 | J10: 157.64 | K10: 154.88 | L10: 25.54 | M10: 5.22 | N10: =L10*M10 -> 133.3188 | O10: =MIN(J10,K10,N10,P10) -> 133.3188 | P10: =AVERAGE(J10,K10,N10) -> 148.61293 | Q10: =(P10-F10)/F10 -> 0.017896804 | R10: =(O10-F10)/F10 -> -0.086857534 | S10: 25.04 | T10: =G10/S10 -> 1.195647
E11: #VALUE! | F11: {=_FV(E11,"Price")} -> 115.09 | G11: {=_FV(E11,"P/E",TRUE)} -> 30.6421 | H11: {=_FV(E11,"52 week high",TRUE)} -> 245.69 | I11: {=_FV(E11,"52 week low",TRUE)} -> 73.28 | J11: n/a | K11: 322.25 | L11: 19.23 | M11: =56.8/6.55 -> 8.6717557 | N11: =L11*M11 -> 166.75786 | O11: =MIN(K11,N11,P11) -> 166.75786 | P11: =AVERAGE(K11,N11) -> 244.50393 | Q11: =(P11-F11)/F11 -> 1.1244585 | R11: =(O11-F11)/F11 -> 0.44893442 | S11: 36.32 | T11: =G11/S11 -> 0.84367015
E12: #VALUE! | F12: {=_FV(E12,"Price")} -> 79.86 | G12: {=_FV(E12,"P/E",TRUE)} -> 12.1791 | H12: {=_FV(E12,"52 week high",TRUE)} -> 98.45 | I12: {=_FV(E12,"52 week low",TRUE)} -> 65.67 | J12: 118.58 | K12: 114.31 | L12: 13.2 | M12: 3.63 | N12: =L12*M12 -> 47.916 | O12: =MIN(K12,N12,P12) -> 47.916 | P12: =AVERAGE(K12,N12) -> 81.113 | Q12: =(P12-F12)/F12 -> 0.015689957 | R12: =(O12-F12)/F12 -> -0.4 | S12: 37.32 | T12: =G12/S12 -> 0.32634244
E13: #VALUE! | F13: {=_FV(E13,"Price")} -> 147.45 | G13: {=_FV(E13,"P/E",TRUE)} -> 31.8459 | H13: {=_FV(E13,"52 week high",TRUE)} -> 228.53 | I13: {=_FV(E13,"52 week low",TRUE)} -> 102.18 | J13: n/a | K13: 273.27 | L13: 17.6 | M13: =67.1/6.55 -> 10.244275 | N13: =L13*M13 -> 180.29924 | O13: =MIN(K13,N13,P13) -> 180.29924 | P13: =AVERAGE(K13,N13) -> 226.78462 | Q13: =(P13-F13)/F13 -> 0.53804421 | R13: =(O13-F13)/F13 -> 0.22278221 | S13: 37.56 | T13: =G13/S13 -> 0.84786741
D15: B | E15: #VALUE! | F15: {=_FV(E15,"Price")} -> 120.24 | G15: {=_FV(E15,"P/E",TRUE)} -> 46.714 | H15: {=_FV(E15,"52 week high",TRUE)} -> 164.4599 | I15: {=_FV(E15,"52 week low",TRUE)} -> 72.5 | J15: 104.92 | K15: 97.24 | L15: 40.87 | M15: 2.1 | N15: =L15*M15 -> 85.827 | O15: 62 | P15: =AVERAGE(J15,K15,N15) -> 95.995667 | Q15: =(P15-F15)/F15 -> -0.20163285 | R15: =(O15-F15)/F15 -> -0.4843646 | S15: 102.49 | T15: =G15/S15 -> 0.45579081
E16: #VALUE! | F16: {=_FV(E16,"Price")} -> 69.82 | G16: {=_FV(E16,"P/E",TRUE)} -> 0 | H16: {=_FV(E16,"52 week high",TRUE)} -> 194.99 | I16: {=_FV(E16,"52 week low",TRUE)} -> 50.08 | J16: 295.81 | K16: 243.53 | L16: 0 | M16: 0 | N16: =L16*M16 -> 0 | O16: =I16 -> 50.08 | P16: =AVERAGE(J16,K16) -> 269.67 | Q16: =(P16-F16)/F16 -> 2.8623604 | R16: =(O16-F16)/F16 -> -0.28272701 | S16: 0 | T16: 0
E17: #VALUE! | F17: {=_FV(E17,"Price")} -> 59.77 | G17: {=_FV(E17,"P/E",TRUE)} -> 24.9394 | H17: {=_FV(E17,"52 week high",TRUE)} -> 92.69 | I17: {=_FV(E17,"52 week low",TRUE)} -> 41.56 | J17: n/a | K17: 99.47 | L17: 38.71 | M17: =32.7/6.55 -> 4.9923664 | N17: =L17*M17 -> 193.2545 | O17: 67 | P17: =AVERAGE(K17,N17) -> 146.36225 | Q17: =(P17-F17)/F17 -> 1.4487578 | R17: =(O17-F17)/F17 -> 0.12096369 | S17: 47.57 | T17: =G17/S17 -> 0.5242674
D19: C | E19: #VALUE! | F19: {=_FV(E19,"Price")} -> 21.21 | G19: {=_FV(E19,"P/E",TRUE)} -> 0 | H19: {=_FV(E19,"52 week high",TRUE)} -> 55.13 | I19: {=_FV(E19,"52 week low",TRUE)} -> 13.01 | J19: n/a | K19: 50.78 | L19: 0 | M19: 0 | N19: =L19*M19 -> 0 | O19: 20 | P19: =K19 -> 50.78 | Q19: =(P19-F19)/F19 -> 1.3941537 | R19: =(O19-F19)/F19 -> -0.057048562 | S19: 0 | T19: 0
E20: #VALUE! | F20: {=_FV(E20,"Price")} -> 27.13 | G20: {=_FV(E20,"P/E",TRUE)} -> 0 | H20: {=_FV(E20,"52 week high",TRUE)} -> 56.45 | I20: {=_FV(E20,"52 week low",TRUE)} -> 18.01 | J20: n/a | K20: 53.4 | L20: 0 | M20: 0 | N20: =L20*M20 -> 0 | O20: 22 | P20: =K20 -> 53.4 | Q20: =(P20-F20)/F20 -> 0.96830077 | R20: =(O20-F20)/F20 -> -0.18908957 | S20: 0 | T20: 0
E21: #VALUE! | F21: {=_FV(E21,"Price")} -> 71.18 | G21: {=_FV(E21,"P/E",TRUE)} -> 0 | H21: {=_FV(E21,"52 week high",TRUE)} -> 90.57 | I21: {=_FV(E21,"52 week low",TRUE)} -> 49.67 | J21: n/a | K21: 149.73 | L21: 1062.88 | M21: 0 | N21: =L21*M21 -> 0 | O21: =I21 -> 49.67 | P21: =K21 -> 149.73 | Q21: =(P21-F21)/F21 -> 1.1035403 | R21: =(O21-F21)/F21 -> -0.30219163 | S21: 0 | T21: 0
F24: USD | G24: SGD
E25: Available Cash | F25: ='SG Portfolio'!D4 -> 23110 | G25: =F25/'Fee and Margin'!$D$2 -> 30813.333
E26: Available Margin | F26: =G26*'Fee and Margin'!$D$2*F31*'Fee and Margin'!D25+G26*'Fee and Margin'!$D$2*F32*'Fee and Margin'!D26+G26*'Fee and Margin'!$D$2*F33*'Fee and Margin'!D27 -> 64687.5 | G26: ='Fee and Margin'!D16 -> 150000
E27: Total | F27: =F25+F26 -> 87797.5 | G27: =F27/'Fee and Margin'!$D$2 -> 117063.33
E30: Class | F30: Allocation | G30: Capital | H30: Target Gain | I30: True Gain | J30: Stock Picks | K30: Used | L30: Reserve
E31: A | F31: 0.5 | G31: =F31*$F$27 -> 43898.75 | H31: 0.05 | I31: =H31*G31/($F$25*F31) -> 0.18995565 | J31: 3 | K31: ='SG Portfolio'!E17 -> 39065.198 | L31: =G31-K31 -> 4833.5519
E32: B | F32: 0.45 | G32: =F32*$F$27 -> 39508.875 | H32: 0.1 | I32: =H32*G32/($F$25*F32) -> 0.37991129 | J32: 1 | K32: ='SG Portfolio'!#REF! -> #REF! | L32: =G32-K32 -> #REF!
E33: C | F33: 0.05 | G33: =F33*$F$27 -> 4389.875 | H33: 0.15 | I33: =H33*G33/($F$25*F33) -> 0.56986694 | J33: 1 | K33: ='SG Portfolio'!#REF! -> #REF! | L33: =G33-K33 -> #REF!
E34: Total | F34: =SUM(F31:F33) -> 1 | G34: =SUM(G31:G33) -> 87797.5 | H34: =$F$31*H31+$F$32*H32+$F$33*H33 -> 0.0775 | I34: =$F$31*I31+$F$32*I32+$F$33*I33 -> 0.29443125 | J34: =SUM(J31:J33) -> 5 | K34: =SUM(K31:K33) -> #REF! | L34: =SUM(L31:L33) -> #REF!
I35: =I34*F25 -> 6804.3062
E39: Long Term Holdings | F39: Allocation | G39: Total Investment | H39: Category | I39: Current Allocation | J39: Over Allocation | K39: Candidates
E40: US Stocks | F40: 0.618 | G40: =$G$49*F40 -> 27599.426 | I40: =SUM(I41:I43) -> 34629.015 | J40: =SUM(J41:J43) -> 7029.5889
E41: US1 | F41: =$F$40/3 -> 0.206 | G41: =$G$40/3 -> 9199.8087 | H41: Big Tech | I41: ='SG Portfolio'!K216 -> 32749.64 | J41: =I41-G41 -> 23549.831 | K41: AAPL, AMZN, MSFT, GOOG, ADBE, NFLX, FB, PYPL
E42: US2 | F42: =$F$40/3 -> 0.206 | G42: =$G$40/3 -> 9199.8087 | H42: Value | I42: ='SG Portfolio'!K214 -> 1879.375 | J42: =I42-G42 -> -7320.4337 | K42: WMT, HD, LOW, MMM, MA, V, MS, JPM, GS, BRK, FDX
E43: US3 | F43: =$F$40/3 -> 0.206 | G43: =$G$40/3 -> 9199.8087 | H43: Growth | I43: 0 | J43: =I43-G43 -> -9199.8087 | K43: AMD, QCOM, AYX, TDOC, MU
E44: China Stocks | F44: =1-F40 -> 0.382 | G44: =$G$49*F44 -> 17059.839 | I44: =SUM(I45:I47) -> #REF! | J44: =SUM(J45:J47) -> #REF!
E45: CN1 | F45: =$F$44/3 -> 0.12733333 | G45: =$G$44/3 -> 5686.6131 | H45: Ecommerce | I45: ='SG Portfolio'!#REF! -> #REF! | J45: =I45-G45 -> #REF! | K45: BABA, JD
E46: CN2 | F46: =$F$44/3 -> 0.12733333 | G46: =$G$44/3 -> 5686.6131 | H46: EV | I46: =+'SG Portfolio'!K212 -> 7212.52 | J46: =I46-G46 -> 1525.9069 | K46: NIO, XPEV
E47: CN3 | F47: =$F$44/3 -> 0.12733333 | G47: =$G$44/3 -> 5686.6131 | H47: Low PE Tech | I47: ='SG Portfolio'!#REF!+'SG Portfolio'!#REF!+'SG Portfolio'!K210+'SG Portfolio'!#REF! -> #REF! | J47: =I47-G47 -> #REF! | K47: BIDU, LU, China Mobile, Xiaomi, ZhongAn
E49: Total | F49: =F40+F44 -> 1 | G49: ='SG Portfolio'!D3*1.5 -> 44659.266 | I49: =SUM(I41:I43,I45:I47) -> #REF! | J49: =I49-G49 -> #REF!

Sheet AAPL Analysis
B2: #VALUE!
C3: 2021 | D3: 2020 | H3: 2019 | L3: 2018 | P3: 2017 | T3: 2016 | X3: AVG
C4: Current | D4: Q4 | E4: Q3 | F4: Q2 | G4: Q1 | H4: Q4 | I4: Q3 | J4: Q2 | K4: Q1 | L4: Q4 | M4: Q3 | N4: Q2 | O4: Q1 | P4: Q4 | Q4: Q3 | R4: Q2 | S4: Q1 | T4: Q4 | U4: Q3 | V4: Q2 | W4: Q1
B5: Stock Price | C5: {=_FV(B2,"Price")} -> 175.6 | D5: 132.49 | E5: 108.51 | F5: 105.73 | G5: 72.89 | H5: 72.68 | I5: 61.38 | J5: 52.37 | K5: 49.14 | L5: 38.46 | M5: 53.18 | N5: 46.07 | O5: 39.86 | P5: 40.65 | Q5: 40.46 | R5: 35.46 | S5: 34.11 | T5: 27.38 | U5: 26.71 | V5: 24.38 | W5: 21.8
B6: Outstanding Shares | C6: {=_FV(B2,"Shares outstanding",TRUE)/1000000} -> 16319.44 | D6: 17114 | E6: 17528 | F6: 17419 | G6: 17619 | H6: 17818 | I6: 18596 | J6: 18406 | K6: 18803 | L6: 19093 | M6: 20000 | N6: 19706 | O6: 20274 | P6: 20631 | Q6: 21007 | R6: 20934 | S6: 21047 | T6: 21312 | U6: 22001 | V6: 21891 | W6: 22164 | X6: =AVERAGE(D6:W6) -> 19668.15
B7: Market Cap | C7: =C5*C6/1000 -> 2865.6937 | D7: =D5*D6/1000 -> 2267.4339 | E7: =E5*E6/1000 -> 1901.9633 | F7: =F5*F6/1000 -> 1841.7109 | G7: =G5*G6/1000 -> 1284.2489 | H7: =H5*H6/1000 -> 1295.0122 | I7: =I5*I6/1000 -> 1141.4225 | J7: =J5*J6/1000 -> 963.92222 | ... W7: =W5*W6/1000 -> 483.1752
B9: Revenue | D9: 294.14 | E9: 274.52 | F9: 273.86 | G9: 267.98 | H9: 267.68 | I9: 260.17 | J9: 259.03 | K9: 258.49 | L9: 261.61 | M9: 265.6 | N9: 255.27 | O9: 247.42 | P9: 239.18 | Q9: 229.23 | R9: 223.51 | S9: 220.46 | T9: 218.12 | U9: 215.64 | V9: 220.29 | W9: 227.54
D10: =(D9-E9)/E9 -> 0.071470203 | E10: =(E9-F9)/F9 -> 0.0024099905 | F10: =(F9-G9)/G9 -> 0.021941936 | G10: =(G9-H9)/H9 -> 0.0011207412 | H10: =(H9-I9)/I9 -> 0.028865742 | I10: =(I9-J9)/J9 -> 0.0044010346 | J10: =(J9-K9)/K9 -> 0.0020890557 | K10: =(K9-L9)/L9 -> -0.01192615 | ... V10: =(V9-W9)/W9 -> -0.03186253 | X10: =AVERAGE(D10:V10) -> 0.013899242
B11: Gross Profit | D11: 114.07 | E11: 104.96 | F11: 104.58 | G11: 102.13 | H11: 101.58 | I11: 98.39 | J11: 98.16 | K11: 98.36 | L11: 99.96 | M11: 101.84 | N11: 97.69 | O11: 94.75 | P11: 91.92 | Q11: 88.19 | R11: 86.07 | S11: 84.69 | T11: 84.02 | U11: 84.26 | V11: 87 | W11: 90.57
B12: Cash on Hand | D12: 76.83 | E12: 90.94 | F12: 93.03 | G12: 94.05 | H12: 107.16 | I12: 100.56 | J12: 94.61 | K12: 80.09 | L12: 86.43 | M12: 66.3 | N12: 70.97 | O12: 87.94 | P12: 77.15 | Q12: 74.18 | R12: 76.76 | S12: 67.1 | T12: 60.45 | U12: 67.16 | V12: 61.76 | W12: 55.28
B13: Gross Margin | D13: 0.3878 | E13: 0.3823 | F13: 0.3819 | G13: 0.3811 | H13: 0.3795 | I13: 0.3782 | J13: 0.379 | K13: 0.3805 | L13: 0.3821 | M13: 0.3834 | N13: 0.3827 | O13: 0.383 | P13: 0.3843 | Q13: 0.3847 | R13: 0.3851 | S13: 0.3841 | T13: 0.3852 | U13: 0.3908 | V13: 0.3949 | W13: 0.3981 | X13: =AVERAGE(D13:W13) -> 0.384435
B14: Operating Margin | D14: 0.2524 | E14: 0.2415 | F14: 0.2452 | G14: 0.2448 | H14: 0.2471 | I14: 0.2457 | J14: 0.2487 | K14: 0.2534 | L14: 0.2598 | M14: 0.2669 | N14: 0.266 | O14: 0.267 | P14: 0.2687 | Q14: 0.2676 | R14: 0.2684 | S14: 0.2691 | T14: 0.2715 | U14: 0.2784 | V14: 0.2855 | W14: 0.2939 | X14: =AVERAGE(D14:W14) -> 0.26208
B15: Net Margin | D15: 0.2173 | E15: 0.2091 | F15: 0.2133 | G15: 0.2135 | H15: 0.2149 | I15: 0.2124 | J15: 0.215 | K15: 0.2212 | L15: 0.2272 | M15: 0.2241 | N15: 0.2198 | O15: 0.2155 | P15: 0.2112 | Q15: 0.2109 | R15: 0.2087 | S15: 0.2074 | T15: 0.2073 | U15: 0.2119 | V15: 0.217 | W15: 0.2227 | X15: =AVERAGE(D15:W15) -> 0.21502
B17: Current Ratio | D17: 1.16 | E17: 1.36 | F17: 1.47 | G17: 1.5 | H17: 1.6 | I17: 1.54 | J17: 1.5 | K17: 1.32 | L17: 1.3 | M17: 1.13 | N17: 1.31 | O17: 1.46 | P17: 1.24 | Q17: 1.28 | R17: 1.39 | S17: 1.39 | T17: 1.23 | U17: 1.35 | V17: 1.31 | W17: 1.28
B18: Debt/Equity Ratio | D18: 4.35 | E18: 3.96 | F18: 3.39 | G18: 3.09 | H18: 2.8 | I18: 2.74 | J18: 2.34 | K18: 2.23 | L18: 2.17 | M18: 2.41 | N18: 2.04 | O18: 1.9 | P18: 1.9 | Q18: 1.8 | R18: 1.61 | S18: 1.49 | T18: 1.5 | U18: 1.51 | V18: 1.42 | W18: 1.34
B19: PE Ratio | C19: {=_FV(B2,"P/E",TRUE)} -> 28.2588 | D19: 35.71 | E19: 35.19 | F19: 27.52 | G19: 19.73 | H19: 22.89 | I19: 18.61 | J19: 16.52 | K19: 15.58 | L19: 12.6 | M19: 18.4 | N19: 16.24 | O19: 15.61 | P19: 16.69 | Q19: 16.02 | R19: 15.53 | S19: 15.88 | T19: 13.05 | U19: 12.8 | V19: 10.42 | W19: 11.25 | X19: =AVERAGE(D19:W19) -> 18.312
B20: P/S Ratio | D20: 7.82 | E20: 7.41 | F20: 5.92 | G20: 4.25 | H20: 4.98 | I20: 3.98 | J20: 3.59 | K20: 3.48 | L20: 2.9 | M20: 4.17 | N20: 3.59 | O20: 3.38 | P20: 3.55 | Q20: 3.4 | R20: 3.27 | S20: 3.33 | T20: 2.73 | U20: 2.73 | V20: 2.28 | W20: 2.52 | X20: =AVERAGE(D20:W20) -> 3.964
B21: P/B Ratio | D21: 34.24 | E21: 30.97 | F21: 21.87 | G21: 14.17 | H21: 14.46 | I21: 11.36 | J21: 9.28 | K21: 8.26 | L21: 6.23 | M21: 10.24 | N21: 7.68 | O21: 6.47 | P21: 5.98 | Q21: 5.78 | R21: 5.43 | S21: 5.35 | T21: 4.41 | U21: 4.56 | V21: 3.87 | W21: 4.3 | X21: =AVERAGE(D21:W21) -> 10.7455
B22: EPS | D22: 3.71 | E22: 3.28 | F22: 3.3 | G22: 3.2 | H22: 3.18 | I22: 2.97 | J22: 2.95 | K22: 2.99 | L22: 3.05 | M22: 2.98 | N22: 2.76 | O22: 2.59 | P22: 2.44 | Q22: 2.3 | R22: 2.21 | S22: 2.15 | T22: 2.1 | U22: 2.08 | V22: 2.15 | W22: 2.25
B23: ROE | D23: 0.9059 | E23: 0.7515 | F23: 0.7066 | G23: 0.6449 | H23: 0.6018 | I23: 0.5382 | J23: 0.5213 | K23: 0.5129 | L23: 0.5092 | M23: 0.4868 | N23: 0.435 | O23: 0.3997 | P23: 0.3737 | Q23: 0.3629 | R23: 0.354 | S23: 0.3509 | T23: 0.3494 | U23: 0.3559 | V23: 0.3789 | W23: 0.4024 | X23: =AVERAGE(D23:W23) -> 0.497095
B25: #VALUE! | C25: {=_FV(B25,"Price")} -> 14354.902 | D25: 12888 | E25: 11052 | F25: 10905 | G25: 9000 | H25: 8991 | I25: 8151 | J25: 8174 | K25: 7953 | L25: 6907 | M25: 8336 | N25: 7795 | O25: 7402 | P25: 7324 | Q25: 6885 | R25: 6557 | S25: 6343 | T25: 5829 | U25: 5752 | V25: 5254 | W25: 5347
C26: 25.1 | D26: 23.8 | W26: 20.02
M29: Historical Ex Correction
C30: Current | D30: Entry | E30: Exit | F30: AVG 3yr | G30: Median | H30: F/W PE | I30: Lowest
B31: P/E Ratio | C31: ='AAPL Analysis'!C19 -> 28.2588 | D31: =D32/'AAPL Analysis'!D22 -> #REF! | E31: =E32/'AAPL Analysis'!D22 -> 36.38814 | F31: =AVERAGE('AAPL Analysis'!D19:O19) -> 21.216667 | G31: =G32/'AAPL Analysis'!D22 -> 24.733333 | H31: 28.25 | I31: =G19 -> 19.73 | M31: Date | N31: Stock Price | O31: Correction | P31: Days
B32: Stock Price | C32: ='AAPL Analysis'!C5 -> 175.6 | D32: =#REF! -> #REF! | E32: 135 | F32: =F31*'AAPL Analysis'!D22 -> 78.713833 | G32: =AVERAGE(H32,F32) -> 91.760667 | H32: =H31*'AAPL Analysis'!$D$22 -> 104.8075 | I32: =I31*'AAPL Analysis'!$D$22 -> 73.1983 | M32: 43376 | N32: 56.38
C33: =(C32-D32)/D32 -> #REF! | D33: =(D32-C32)/C32 -> #REF! | E33: =(E32-D32)/D32 -> #REF! | F33: =(F32-$D$32)/$D$32 -> #REF! | G33: =(G32-$D$32)/$D$32 -> #REF! | H33: =(H32-$D$32)/$D$32 -> #REF! | I33: =(I32-$D$32)/$D$32 -> #REF! | M33: 43468 | N33: 34.67 | O33: =(N33-N32)/N32 -> -0.38506563 | P33: =M33-M32 -> 92
E34: =(E32-C32)/C32 -> -0.23120729 | M34: 43874 | N34: 80.59 | P34: =M34-M33 -> 406
M35: 43913 | N35: 55.66 | O35: =(N35-N34)/N34 -> -0.30934359 | P35: =M35-M34 -> 39
B36: Intrinsic Value (Projected FCF) | C36: 59.17 | M36: 44075 | N36: 133.75 | P36: =M36-M35 -> 162
B37: Stock Price | C37: =C32 -> 175.6 | D37: =D32 -> #REF! | E37: =E32 -> 135 | F37: =F32 -> 78.713833 | G37: =G32 -> 91.760667 | H37: =H32 -> 104.8075 | I37: =I32 -> 73.1983 | M37: 44097 | N37: 106.77 | O37: =(N37-N36)/N36 -> -0.20171963 | P37: =M37-M36 -> 22
B38: Price to IV | C38: =C37/$C$36 -> 2.9677201 | D38: =D37/$C$36 -> #REF! | E38: =E37/$C$36 -> 2.2815616 | F38: =F37/$C$36 -> 1.3302997 | G38: =G37/$C$36 -> 1.5507971 | H38: =H37/$C$36 -> 1.7712946 | I38: =I37/$C$36 -> 1.2370847 | M38: 44221 | N38: 142.7 | P38: =M38-M37 -> 124
B39: Range in past 10 yr | M39: =TODAY() -> 44649 | N39: =C5 -> 175.6 | O39: =(N39-N38)/N38 -> 0.23055361 | P39: =M39-M38 -> 428
B40: Min | C40: 0.66 | D40: =C40*$C$36 -> 39.0522 | F40: PE | G40: =D40/$D$22 -> 10.526199 | N40: =N38*(1+O40) -> 98.55667 | O40: =MEDIAN(O33,O35,O37) -> -0.30934359
B41: Med | C41: 1.45 | D41: =C41*$C$36 -> 85.7965 | F41: PE | G41: =D41/$D$22 -> 23.125741
B42: Max | C42: 19 | D42: =C42*$C$36 -> 1124.23 | F42: PE | G42: =D42/$D$22 -> 303.02695
B43: Industry Median | C43: 1.43 | D43: =C43*$C$36 -> 84.6131 | F43: PE | G43: =D43/$D$22 -> 22.806765
B46: Intrinsic Value (DCF, FCF Based) | C46: 170.34
B47: Stock Price | C47: =C32 -> 175.6 | D47: =D32 -> #REF! | E47: =E32 -> 135 | F47: =F32 -> 78.713833 | G47: =G32 -> 91.760667 | H47: =H32 -> 104.8075 | I47: =I32 -> 73.1983
B48: Margin of Safety | C48: =($C$46-C47)/$C$46 -> -0.030879418 | D48: =($C$46-D47)/$C$46 -> #REF! | E48: =($C$46-E47)/$C$46 -> 0.20746742 | F48: =($C$46-F47)/$C$46 -> 0.53790165 | G48: =($C$46-G47)/$C$46 -> 0.46130876 | H48: =($C$46-H47)/$C$46 -> 0.38471586 | I48: =($C$46-I47)/$C$46 -> 0.5702812
B51: Intrinsic Value (DCF, Earning Based) | C51: 143.8
B52: Stock Price | C52: =C32 -> 175.6 | D52: =D32 -> #REF! | E52: =E32 -> 135 | F52: =F32 -> 78.713833 | G52: =G32 -> 91.760667 | H52: =H32 -> 104.8075 | I52: =I32 -> 73.1983
B53: Margin of Safety | C53: =($C$51-C52)/$C$51 -> -0.22114047 | D53: =($C$51-D52)/$C$51 -> #REF! | E53: =($C$51-E52)/$C$51 -> 0.061196106 | F53: =($C$51-F52)/$C$51 -> 0.4526159 | G53: =($C$51-G52)/$C$51 -> 0.36188688 | H53: =($C$51-H52)/$C$51 -> 0.27115786 | I53: =($C$51-I52)/$C$51 -> 0.49097149
B54: Range in past 10 yr
B55: Current | C55: =C52/$C$51 -> 1.2211405
B56: Min | C56: 0.35 | D56: =C56*$C$51 -> 50.33
B57: Med | C57: 0.57 | D57: =C57*$C$51 -> 81.966
B58: Max | C58: 1.75 | D58: =C58*$C$51 -> 251.65
B59: Industry Median | C59: 1.37 | D59: =C59*$C$51 -> 197.006

Sheet JD Bet
F3: Buy Price | G3: Quantity | H3: Fee | I3: Average Price | J3: Investment | K3: Current Price | L3: Gain/Loss | M3: P/L % | N3: SellPrice | O3: Proceeds | P3: Gain/Loss | Q3: P/L % | R3: BuyDate | S3: SellDate | T3: Holding | U3: Tradable Balance | V3: Margin Call | W3: Force Selling
C4: #VALUE! | D4: NASDAQ | E4: USD | F4: 86 | G4: 100 | H4: =8.88*2+1 -> 18.76 | I4: =((F4*G4)+H4)/G4 -> 86.1876 | J4: =I4*G4 -> 8618.76 | K4: {=_FV(C4,"Price")} -> 59.77 | L4: =(K4-I4)*G4 -> -2641.76 | M4: =L4/J4 -> -0.30651277 | N4: 70 | O4: =N4*G4 -> 7000 | P4: =(N4-I4)*G4 -> -1618.76 | Q4: =P4/J4 -> -0.1878182 | R4: 04/01/2021
C5: =F5/F4 -> 0.92209302 | D5: NASDAQ | E5: USD | F5: 79.3 | G5: 50 | H5: 2.88 | I5: =((F5*G5)+H5)/G5 -> 79.3576 | J5: =I5*G5 -> 3967.88 | K5: =K4 -> 59.77 | L5: =(K5-I5)*G5 -> -979.38 | M5: =L5/J5 -> -0.24682702 | N5: 63.5 | O5: =N5*G5 -> 3175 | P5: =(N5-I5)*G5 -> -792.88 | Q5: =P5/J5 -> -0.19982459 | R5: 04/15/2021
C6: =F6/F5 -> 0.85119798 | D6: NASDAQ | E6: USD | F6: 67.5 | G6: 0 | H6: 0 | I6: =((F6*G6)+H6)/G6 -> #DIV/0! | J6: =I6*G6 -> #DIV/0! | K6: =K4 -> 59.77 | L6: =(K6-I6)*G6 -> #DIV/0! | M6: =L6/J6 -> #DIV/0! | N6: 69 | O6: =N6*G6 -> 0 | P6: =(N6-I6)*G6 -> #DIV/0! | Q6: =P6/J6 -> #DIV/0!
C7: =F7/F6 -> 0.99111111 | D7: NASDAQ | E7: USD | F7: 66.9 | G7: 0 | H7: 0 | I7: =((F7*G7)+H7)/G7 -> #DIV/0! | J7: =I7*G7 -> #DIV/0! | K7: =K4 -> 59.77 | L7: =(K7-I7)*G7 -> #DIV/0! | M7: =L7/J7 -> #DIV/0! | N7: 69 | O7: =N7*G7 -> 0 | P7: =(N7-I7)*G7 -> #DIV/0! | Q7: =P7/J7 -> #DIV/0!
C8: =F8/F7 -> 0.68759342 | D8: NASDAQ | E8: USD | F8: 46 | I8: =((F8*G8)+H8)/G8 -> #DIV/0! | J8: =I8*G8 -> #DIV/0! | K8: =#REF! -> #REF! | L8: =(K8-I8)*G8 -> #REF! | M8: =L8/J8 -> #REF! | N8: =#REF! -> #REF! | O8: =N8*G8 -> #REF! | P8: =(N8-I8)*G8 -> #REF! | Q8: =P8/J8 -> #REF!
C9: =F9/F8 -> 0.80434783 | D9: NASDAQ | E9: USD | F9: 37 | I9: =((F9*G9)+H9)/G9 -> #DIV/0! | J9: =I9*G9 -> #DIV/0! | K9: =K8 -> #REF! | L9: =(K9-I9)*G9 -> #REF! | M9: =L9/J9 -> #REF! | N9: =K9 -> #REF! | O9: =N9*G9 -> #REF! | P9: =(N9-I9)*G9 -> #REF! | Q9: =P9/J9 -> #REF!
D11: NASDAQ | E11: USD | F11: =(F4*G4+F5*G5+F6*G6+F7*G7+F8*G8+F9*G9)/G11 -> 83.766667 | G11: =SUM(G4:G9) -> 150 | H11: =SUM(H4:H9) -> 21.64 | I11: =((F11*G11)+H11)/G11 -> 83.910933 | J11: =I11*G11 -> 12586.64 | K11: =K4 -> 59.77 | L11: =(K11-I11)*G11 -> -3621.14 | M11: =L11/J11 -> -0.28769711 | U11: =(('SG Portfolio'!$D$4+'SG Portfolio'!$D$5)-('SG Portfolio'!$E$17+'SG Portfolio'!$E$18+'SG Portfolio'!$E$19))+('SG Portfolio'!$E$17+'SG Portfolio'!$H$17)*(1-'Fee and Margin'!$E$25)+('SG Portfolio'!$E$18+'SG Portfolio'!$H$18)*(1-'Fee and Margin'!$E$26)+('SG Portfolio'!$E$19+'SG Portfolio'!$H$19)*(1-'Fee and Margin'!$E$27) -> 4917.1822 | V11: =('SG Portfolio'!$E$17+'SG Portfolio'!$H$17)*'Fee and Margin'!$F$25+('SG Portfolio'!$E$18+'SG Portfolio'!$H$18)*'Fee and Margin'!$F$26+('SG Portfolio'!$E$19+'SG Portfolio'!$H$19)*'Fee and Margin'!$F$27-((('SG Portfolio'!$D$4+'SG Portfolio'!$D$5)-('SG Portfolio'!$E$17+'SG Portfolio'!$E$18+'SG Portfolio'!$E$19))+('SG Portfolio'!$E$17+'SG Portfolio'!$H$17+'SG Portfolio'!$E$18+'SG Portfolio'!$H$18+'SG Portfolio'!$E$19+'SG Portfolio'!$H$19)) -> -7864.1984 | W11: =('SG Portfolio'!$E$17+'SG Portfolio'!$H$17)*'Fee and Margin'!$G$25+('SG Portfolio'!$E$18+'SG Portfolio'!$H$18)*'Fee and Margin'!$G$26+('SG Portfolio'!$E$19+'SG Portfolio'!$H$19)*'Fee and Margin'!$G$27-((('SG Portfolio'!$D$4+'SG Portfolio'!$D$5)-('SG Portfolio'!$E$17+'SG Portfolio'!$E$18+'SG Portfolio'!$E$19))+('SG Portfolio'!$E$17+'SG Portfolio'!$H$17+'SG Portfolio'!$E$18+'SG Portfolio'!$H$18+'SG Portfolio'!$E$19+'SG Portfolio'!$H$19)) -> -11302.662
D12: NASDAQ | E12: USD | F12: =$F$11 -> 83.766667 | G12: =$G$11 -> 150 | H12: =$H$11 -> 21.64 | I12: =((F12*G12)+H12)/G12 -> 83.910933 | J12: =I12*G12 -> 12586.64 | K12: ='AAPL Analysis'!H32 -> 104.8075 | L12: =(K12-I12)*G12 -> 3134.485 | M12: =L12/J12 -> 0.2490327 | U12: =(('SG Portfolio'!$D$4+'SG Portfolio'!$D$5)-('SG Portfolio'!$E$17+'SG Portfolio'!$E$18+'SG Portfolio'!$E$19))+('SG Portfolio'!$E$17+'SG Portfolio'!$H$17)*(1-'Fee and Margin'!$E$25)+('SG Portfolio'!$E$18+'SG Portfolio'!$H$18)*(1-'Fee and Margin'!$E$26)+('SG Portfolio'!$E$19+'SG Portfolio'!$H$19)*(1-'Fee and Margin'!$E$27) -> 4917.1822 | V12: =('SG Portfolio'!$E$17+'SG Portfolio'!$H$17)*'Fee and Margin'!$F$25+('SG Portfolio'!$E$18+'SG Portfolio'!$H$18)*'Fee and Margin'!$F$26+('SG Portfolio'!$E$19+'SG Portfolio'!$H$19)*'Fee and Margin'!$F$27-((('SG Portfolio'!$D$4+'SG Portfolio'!$D$5)-('SG Portfolio'!$E$17+'SG Portfolio'!$E$18+'SG Portfolio'!$E$19))+('SG Portfolio'!$E$17+'SG Portfolio'!$H$17+'SG Portfolio'!$E$18+'SG Portfolio'!$H$18+'SG Portfolio'!$E$19+'SG Portfolio'!$H$19)) -> -7864.1984 | W12: =('SG Portfolio'!$E$17+'SG Portfolio'!$H$17)*'Fee and Margin'!$G$25+('SG Portfolio'!$E$18+'SG Portfolio'!$H$18)*'Fee and Margin'!$G$26+('SG Portfolio'!$E$19+'SG Portfolio'!$H$19)*'Fee and Margin'!$G$27-((('SG Portfolio'!$D$4+'SG Portfolio'!$D$5)-('SG Portfolio'!$E$17+'SG Portfolio'!$E$18+'SG Portfolio'!$E$19))+('SG Portfolio'!$E$17+'SG Portfolio'!$H$17+'SG Portfolio'!$E$18+'SG Portfolio'!$H$18+'SG Portfolio'!$E$19+'SG Portfolio'!$H$19)) -> -11302.662
D13: NASDAQ | E13: USD | F13: =$F$11 -> 83.766667 | G13: =$G$11 -> 150 | H13: =$H$11 -> 21.64 | I13: =((F13*G13)+H13)/G13 -> 83.910933 | J13: =I13*G13 -> 12586.64 | K13: =F6 -> 67.5 | L13: =(K13-I13)*G13 -> -2461.64 | M13: =L13/J13 -> -0.19557563 | U13: =(('SG Portfolio'!$D$4+'SG Portfolio'!$D$5)-('SG Portfolio'!$E$17+'SG Portfolio'!$E$18+'SG Portfolio'!$E$19))+('SG Portfolio'!$E$17+'SG Portfolio'!$H$17)*(1-'Fee and Margin'!$E$25)+('SG Portfolio'!$E$18+'SG Portfolio'!$H$18)*(1-'Fee and Margin'!$E$26)+('SG Portfolio'!$E$19+'SG Portfolio'!$H$19)*(1-'Fee and Margin'!$E$27) -> 4917.1822 | V13: =('SG Portfolio'!$E$17+'SG Portfolio'!$H$17)*'Fee and Margin'!$F$25+('SG Portfolio'!$E$18+'SG Portfolio'!$H$18)*'Fee and Margin'!$F$26+('SG Portfolio'!$E$19+'SG Portfolio'!$H$19)*'Fee and Margin'!$F$27-((('SG Portfolio'!$D$4+'SG Portfolio'!$D$5)-('SG Portfolio'!$E$17+'SG Portfolio'!$E$18+'SG Portfolio'!$E$19))+('SG Portfolio'!$E$17+'SG Portfolio'!$H$17+'SG Portfolio'!$E$18+'SG Portfolio'!$H$18+'SG Portfolio'!$E$19+'SG Portfolio'!$H$19)) -> -7864.1984 | W13: =('SG Portfolio'!$E$17+'SG Portfolio'!$H$17)*'Fee and Margin'!$G$25+('SG Portfolio'!$E$18+'SG Portfolio'!$H$18)*'Fee and Margin'!$G$26+('SG Portfolio'!$E$19+'SG Portfolio'!$H$19)*'Fee and Margin'!$G$27-((('SG Portfolio'!$D$4+'SG Portfolio'!$D$5)-('SG Portfolio'!$E$17+'SG Portfolio'!$E$18+'SG Portfolio'!$E$19))+('SG Portfolio'!$E$17+'SG Portfolio'!$H$17+'SG Portfolio'!$E$18+'SG Portfolio'!$H$18+'SG Portfolio'!$E$19+'SG Portfolio'!$H$19)) -> -11302.662
D14: NASDAQ | E14: USD | F14: =$F$11 -> 83.766667 | G14: =$G$11 -> 150 | H14: =$H$11 -> 21.64 | I14: =((F14*G14)+H14)/G14 -> 83.910933 | J14: =I14*G14 -> 12586.64 | K14: ='AAPL Analysis'!G32 -> 91.760667 | L14: =(K14-I14)*G14 -> 1177.46 | M14: =L14/J14 -> 0.093548397 | U14: =(('SG Portfolio'!$D$4+'SG Portfolio'!$D$5)-('SG Portfolio'!$E$17+'SG Portfolio'!$E$18+'SG Portfolio'!$E$19))+('SG Portfolio'!$E$17+'SG Portfolio'!$H$17)*(1-'Fee and Margin'!$E$25)+('SG Portfolio'!$E$18+'SG Portfolio'!$H$18)*(1-'Fee and Margin'!$E$26)+('SG Portfolio'!$E$19+'SG Portfolio'!$H$19)*(1-'Fee and Margin'!$E$27) -> 4917.1822 | V14: =('SG Portfolio'!$E$17+'SG Portfolio'!$H$17)*'Fee and Margin'!$F$25+('SG Portfolio'!$E$18+'SG Portfolio'!$H$18)*'Fee and Margin'!$F$26+('SG Portfolio'!$E$19+'SG Portfolio'!$H$19)*'Fee and Margin'!$F$27-((('SG Portfolio'!$D$4+'SG Portfolio'!$D$5)-('SG Portfolio'!$E$17+'SG Portfolio'!$E$18+'SG Portfolio'!$E$19))+('SG Portfolio'!$E$17+'SG Portfolio'!$H$17+'SG Portfolio'!$E$18+'SG Portfolio'!$H$18+'SG Portfolio'!$E$19+'SG Portfolio'!$H$19)) -> -7864.1984 | W14: =('SG Portfolio'!$E$17+'SG Portfolio'!$H$17)*'Fee and Margin'!$G$25+('SG Portfolio'!$E$18+'SG Portfolio'!$H$18)*'Fee and Margin'!$G$26+('SG Portfolio'!$E$19+'SG Portfolio'!$H$19)*'Fee and Margin'!$G$27-((('SG Portfolio'!$D$4+'SG Portfolio'!$D$5)-('SG Portfolio'!$E$17+'SG Portfolio'!$E$18+'SG Portfolio'!$E$19))+('SG Portfolio'!$E$17+'SG Portfolio'!$H$17+'SG Portfolio'!$E$18+'SG Portfolio'!$H$18+'SG Portfolio'!$E$19+'SG Portfolio'!$H$19)) -> -11302.662
D15: NASDAQ | E15: USD | F15: =$F$11 -> 83.766667 | G15: =$G$11 -> 150 | H15: =$H$11 -> 21.64 | I15: =((F15*G15)+H15)/G15 -> 83.910933 | J15: =I15*G15 -> 12586.64 | K15: =F8 -> 46 | L15: =(K15-I15)*G15 -> -5686.64 | M15: =L15/J15 -> -0.45179969 | U15: =(('SG Portfolio'!$D$4+'SG Portfolio'!$D$5)-('SG Portfolio'!$E$17+'SG Portfolio'!$E$18+'SG Portfolio'!$E$19))+('SG Portfolio'!$E$17+'SG Portfolio'!$H$17)*(1-'Fee and Margin'!$E$25)+('SG Portfolio'!$E$18+'SG Portfolio'!$H$18)*(1-'Fee and Margin'!$E$26)+('SG Portfolio'!$E$19+'SG Portfolio'!$H$19)*(1-'Fee and Margin'!$E$27) -> 4917.1822 | V15: =('SG Portfolio'!$E$17+'SG Portfolio'!$H$17)*'Fee and Margin'!$F$25+('SG Portfolio'!$E$18+'SG Portfolio'!$H$18)*'Fee and Margin'!$F$26+('SG Portfolio'!$E$19+'SG Portfolio'!$H$19)*'Fee and Margin'!$F$27-((('SG Portfolio'!$D$4+'SG Portfolio'!$D$5)-('SG Portfolio'!$E$17+'SG Portfolio'!$E$18+'SG Portfolio'!$E$19))+('SG Portfolio'!$E$17+'SG Portfolio'!$H$17+'SG Portfolio'!$E$18+'SG Portfolio'!$H$18+'SG Portfolio'!$E$19+'SG Portfolio'!$H$19)) -> -7864.1984 | W15: =('SG Portfolio'!$E$17+'SG Portfolio'!$H$17)*'Fee and Margin'!$G$25+('SG Portfolio'!$E$18+'SG Portfolio'!$H$18)*'Fee and Margin'!$G$26+('SG Portfolio'!$E$19+'SG Portfolio'!$H$19)*'Fee and Margin'!$G$27-((('SG Portfolio'!$D$4+'SG Portfolio'!$D$5)-('SG Portfolio'!$E$17+'SG Portfolio'!$E$18+'SG Portfolio'!$E$19))+('SG Portfolio'!$E$17+'SG Portfolio'!$H$17+'SG Portfolio'!$E$18+'SG Portfolio'!$H$18+'SG Portfolio'!$E$19+'SG Portfolio'!$H$19)) -> -11302.662
D16: NASDAQ | E16: USD | F16: =$F$11 -> 83.766667 | G16: =$G$11 -> 150 | H16: =$H$11 -> 21.64 | I16: =((F16*G16)+H16)/G16 -> 83.910933 | J16: =I16*G16 -> 12586.64 | K16: ='AAPL Analysis'!F32 -> 78.713833 | L16: =(K16-I16)*G16 -> -779.565 | M16: =L16/J16 -> -0.06193591 | U16: =(('SG Portfolio'!$D$4+'SG Portfolio'!$D$5)-('SG Portfolio'!$E$17+'SG Portfolio'!$E$18+'SG Portfolio'!$E$19))+('SG Portfolio'!$E$17+'SG Portfolio'!$H$17)*(1-'Fee and Margin'!$E$25)+('SG Portfolio'!$E$18+'SG Portfolio'!$H$18)*(1-'Fee and Margin'!$E$26)+('SG Portfolio'!$E$19+'SG Portfolio'!$H$19)*(1-'Fee and Margin'!$E$27) -> 4917.1822 | V16: =('SG Portfolio'!$E$17+'SG Portfolio'!$H$17)*'Fee and Margin'!$F$25+('SG Portfolio'!$E$18+'SG Portfolio'!$H$18)*'Fee and Margin'!$F$26+('SG Portfolio'!$E$19+'SG Portfolio'!$H$19)*'Fee and Margin'!$F$27-((('SG Portfolio'!$D$4+'SG Portfolio'!$D$5)-('SG Portfolio'!$E$17+'SG Portfolio'!$E$18+'SG Portfolio'!$E$19))+('SG Portfolio'!$E$17+'SG Portfolio'!$H$17+'SG Portfolio'!$E$18+'SG Portfolio'!$H$18+'SG Portfolio'!$E$19+'SG Portfolio'!$H$19)) -> -7864.1984 | W16: =('SG Portfolio'!$E$17+'SG Portfolio'!$H$17)*'Fee and Margin'!$G$25+('SG Portfolio'!$E$18+'SG Portfolio'!$H$18)*'Fee and Margin'!$G$26+('SG Portfolio'!$E$19+'SG Portfolio'!$H$19)*'Fee and Margin'!$G$27-((('SG Portfolio'!$D$4+'SG Portfolio'!$D$5)-('SG Portfolio'!$E$17+'SG Portfolio'!$E$18+'SG Portfolio'!$E$19))+('SG Portfolio'!$E$17+'SG Portfolio'!$H$17+'SG Portfolio'!$E$18+'SG Portfolio'!$H$18+'SG Portfolio'!$E$19+'SG Portfolio'!$H$19)) -> -11302.662
D17: NASDAQ | E17: USD | F17: =$F$11 -> 83.766667 | G17: =$G$11 -> 150 | H17: =$H$11 -> 21.64 | I17: =((F17*G17)+H17)/G17 -> 83.910933 | J17: =I17*G17 -> 12586.64 | K17: ='AAPL Analysis'!I32 -> 73.1983 | L17: =(K17-I17)*G17 -> -1606.895 | M17: =L17/J17 -> -0.12766672 | U17: =(('SG Portfolio'!$D$4+'SG Portfolio'!$D$5)-('SG Portfolio'!$E$17+'SG Portfolio'!$E$18+'SG Portfolio'!$E$19))+('SG Portfolio'!$E$17+'SG Portfolio'!$H$17)*(1-'Fee and Margin'!$E$25)+('SG Portfolio'!$E$18+'SG Portfolio'!$H$18)*(1-'Fee and Margin'!$E$26)+('SG Portfolio'!$E$19+'SG Portfolio'!$H$19)*(1-'Fee and Margin'!$E$27) -> 4917.1822 | V17: =('SG Portfolio'!$E$17+'SG Portfolio'!$H$17)*'Fee and Margin'!$F$25+('SG Portfolio'!$E$18+'SG Portfolio'!$H$18)*'Fee and Margin'!$F$26+('SG Portfolio'!$E$19+'SG Portfolio'!$H$19)*'Fee and Margin'!$F$27-((('SG Portfolio'!$D$4+'SG Portfolio'!$D$5)-('SG Portfolio'!$E$17+'SG Portfolio'!$E$18+'SG Portfolio'!$E$19))+('SG Portfolio'!$E$17+'SG Portfolio'!$H$17+'SG Portfolio'!$E$18+'SG Portfolio'!$H$18+'SG Portfolio'!$E$19+'SG Portfolio'!$H$19)) -> -7864.1984 | W17: =('SG Portfolio'!$E$17+'SG Portfolio'!$H$17)*'Fee and Margin'!$G$25+('SG Portfolio'!$E$18+'SG Portfolio'!$H$18)*'Fee and Margin'!$G$26+('SG Portfolio'!$E$19+'SG Portfolio'!$H$19)*'Fee and Margin'!$G$27-((('SG Portfolio'!$D$4+'SG Portfolio'!$D$5)-('SG Portfolio'!$E$17+'SG Portfolio'!$E$18+'SG Portfolio'!$E$19))+('SG Portfolio'!$E$17+'SG Portfolio'!$H$17+'SG Portfolio'!$E$18+'SG Portfolio'!$H$18+'SG Portfolio'!$E$19+'SG Portfolio'!$H$19)) -> -11302.662
D19: NASDAQ | E19: USD | F19: =I11 -> 83.910933 | G19: 30 | H19: 8.88 | I19: =((F19*G19)+H19)/G19 -> 84.206933 | J19: =I19*G19 -> 2526.208 | K19: =K4 -> 59.77 | L19: =(K19-I19)*G19 -> -733.108 | M19: =L19/J19 -> -0.29020097 | N19: 280 | O19: =N19*G19 -> 8400 | P19: =(N19-I19)*G19 -> 5873.792 | Q19: =P19/J19 -> 2.3251419 | R19: 01/28/2021
D20: NASDAQ | E20: USD | F20: =I12 -> 83.910933 | G20: 30 | H20: 8.88 | I20: =((F20*G20)+H20)/G20 -> 84.206933 | J20: =I20*G20 -> 2526.208 | K20: =K4 -> 59.77 | L20: =(K20-I20)*G20 -> -733.108 | M20: =L20/J20 -> -0.29020097 | N20: 290 | O20: =N20*G20 -> 8700 | P20: =(N20-I20)*G20 -> 6173.792 | Q20: =P20/J20 -> 2.4438969 | R20: 01/28/2021
D21: NASDAQ | E21: USD | F21: =I13 -> 83.910933 | G21: 40 | H21: 8.88 | I21: =((F21*G21)+H21)/G21 -> 84.132933 | J21: =I21*G21 -> 3365.3173 | K21: =#REF! -> #REF! | L21: =(K21-I21)*G21 -> #REF! | M21: =L21/J21 -> #REF! | N21: 300 | O21: =N21*G21 -> 12000 | P21: =(N21-I21)*G21 -> 8634.6827 | Q21: =P21/J21 -> 2.5657856 | R21: 01/28/2021
D22: NASDAQ | E22: USD | F22: =I14 -> 83.910933 | I22: =((F22*G22)+H22)/G22 -> #DIV/0! | J22: =I22*G22 -> #DIV/0! | K22: =#REF! -> #REF! | L22: =(K22-I22)*G22 -> #REF! | M22: =L22/J22 -> #REF! | N22: 280 | O22: =N22*G22 -> 0 | P22: =(N22-I22)*G22 -> #DIV/0! | Q22: =P22/J22 -> #DIV/0! | R22: 01/28/2021
D23: NASDAQ | E23: USD | F23: =I15 -> 83.910933 | I23: =((F23*G23)+H23)/G23 -> #DIV/0! | J23: =I23*G23 -> #DIV/0! | K23: =K8 -> #REF! | L23: =(K23-I23)*G23 -> #REF! | M23: =L23/J23 -> #REF! | N23: 290 | O23: =N23*G23 -> 0 | P23: =(N23-I23)*G23 -> #DIV/0! | Q23: =P23/J23 -> #DIV/0! | R23: 01/28/2021
D24: NASDAQ | E24: USD | F24: =I16 -> 83.910933 | I24: =((F24*G24)+H24)/G24 -> #DIV/0! | J24: =I24*G24 -> #DIV/0! | K24: =#REF! -> #REF! | L24: =(K24-I24)*G24 -> #REF! | M24: =L24/J24 -> #REF! | N24: 300 | O24: =N24*G24 -> 0 | P24: =(N24-I24)*G24 -> #DIV/0! | Q24: =P24/J24 -> #DIV/0! | R24: 01/28/2021
G30: 5 Days | H30: Avg. Daily | I30: Avg. half hour | J30: High | K30: Low | L30: MA5 | M30: MA10 | N30: MA20 | O30: MA30 | P30: MA60
E31: Past Volume ('000) | G31: 42588 | H31: =G31/5 -> 8517.6 | I31: =H31/13 -> 655.2 | J31: 85.57 | K31: 79.75 | L31: 81.96 | M31: 82.52 | N31: 83.03 | O31: 85.94 | P31: 90.97
E32: Current | H32: 8313 | I32: =H32/13 -> 639.46154 | J32: 81.33 | K32: 79.75

Sheet JD Analysis
B2: #VALUE!
C3: 2021 | D3: 2020 | H3: 2019 | L3: 2018 | P3: 2017 | T3: 2016 | X3: AVG
C4: Current | D4: Q4 | E4: Q3 | F4: Q2 | G4: Q1 | H4: Q4 | I4: Q3 | J4: Q2 | K4: Q1 | L4: Q4 | M4: Q3 | N4: Q2 | O4: Q1 | P4: Q4 | Q4: Q3 | R4: Q2 | S4: Q1 | T4: Q4 | U4: Q3 | V4: Q2 | W4: Q1
B5: Stock Price | C5: {=_FV(B2,"Price")} -> 59.77 | D5: 87.9 | E5: 81.52 | F5: 63.79 | G5: 43.1 | H5: 35.23 | I5: 31.15 | J5: 29.91 | K5: 30.27 | L5: 20.93 | M5: 23.52 | N5: 35.86 | O5: 36.51 | P5: 41.42 | Q5: 37.52 | R5: 45.17 | S5: 35.07 | T5: 25.44 | U5: 25.95 | V5: 21.65 | W5: 25.56
B6: Outstanding Shares | C6: {=_FV(B2,"Shares outstanding",TRUE)/1000000/2} -> 782.4485 | D6: 1614 | E6: 1614 | F6: 1573 | G6: 1515 | H6: 1456 | I6: 1486 | J6: 1803 | K6: 1474 | L6: 1439 | M6: 1456 | N6: 1454 | O6: 1470 | P6: 1422 | Q6: 1386 | R6: 1423 | S6: 1444 | T6: 1402 | U6: 1440 | V6: 1382 | W6: 1371 | X6: =AVERAGE(E6:W6) -> 1474.2105
B7: Market Cap | C7: =C5*C6/1000 -> 46.766947 | D7: =D5*D6/1000 -> 141.8706 | E7: =E5*E6/1000 -> 131.57328 | F7: =F5*F6/1000 -> 100.34167 | G7: =G5*G6/1000 -> 65.2965 | H7: =H5*H6/1000 -> 51.29488 | I7: =I5*I6/1000 -> 46.2889 | J7: =J5*J6/1000 -> 53.92773 | ... W7: =W5*W6/1000 -> 35.04276
B9: Revenue | D9: 34.4 | E9: 25.16 | F9: 28.35 | G9: 20.94 | H9: 24.23 | I9: 19.22 | J9: 22.03 | K9: 17.94 | L9: 19.5 | M9: 15.39 | N9: 19.2 | O9: 15.74 | P9: 16.66 | Q9: 12.56 | R9: 13.59 | S9: 10.91 | T9: 11.52 | U9: 9.02 | V9: 9.93 | W9: 8.25
D10: =(D9-E9)/E9 -> 0.3672496 | E10: =(E9-F9)/F9 -> -0.11252205 | F10: =(F9-G9)/G9 -> 0.35386819 | G10: =(G9-H9)/H9 -> -0.13578209 | H10: =(H9-I9)/I9 -> 0.26066597 | I10: =(I9-J9)/J9 -> -0.12755334 | J10: =(J9-K9)/K9 -> 0.22798216 | K10: =(K9-L9)/L9 -> -0.08 | ... V10: =(V9-W9)/W9 -> 0.20363636 | X10: =AVERAGE(D10:V10) -> 0.095769534
B11: Gross Profit | D11: 0 | E11: 14.56 | F11: 13.43 | G11: 12.6 | H11: 12.13 | I11: 11.24 | J11: 10.77 | K11: 10.05 | L11: 9.59 | M11: 9.31 | N11: 8.92 | O11: 8.29 | P11: 7.81 | Q11: 7.15 | R11: 6.65 | S11: 6.25 | T11: 5.68 | U11: 5.24 | V11: 4.75 | W11: 4.24
B12: Cash on Hand | D12: 0 | E12: 18.66 | F12: 17.84 | G12: 10.61 | H12: 9.27 | I12: 8.29 | J12: 8.76 | K12: 6.09 | L12: 5.75 | M12: 6.24 | N12: 7.98 | O12: 7.95 | P12: 5.9 | Q12: 6.28 | R12: 6.79 | S12: 7.42 | T12: 6.17 | U12: 6.15 | V12: 6.53 | W12: 5.36
B13: Gross Margin | D13: 0 | E13: 0.1473 | F13: 0.1459 | G13: 0.1474 | H13: 0.1463 | I13: 0.1473 | J13: 0.1482 | K13: 0.145 | L13: 0.1428 | M13: 0.137 | N13: 0.1366 | O13: 0.1368 | P13: 0.1402 | Q13: 0.1503 | R13: 0.1508 | S13: 0.1557 | T13: 0.1516 | U13: 0.1495 | V13: 0.1445 | W13: 0.1389 | X13: =AVERAGE(D13:W13) -> 0.138105
B14: Operating Margin | D14: 0 | E14: 0.0179 | F14: 0.0198 | G14: 0.0168 | H14: 0.0156 | I14: 0.0141 | J14: 0.004 | K14: -0.0029 | L14: -0.0057 | M14: -0.0076 | N14: -0.0053 | O14: -0.0041 | P14: -0.0023 | Q14: 0.0017 | R14: -0.0013 | S14: -0.0013 | T14: -0.0082 | U14: -0.0255 | V14: -0.0284 | W14: -0.0327 | X14: =AVERAGE(D14:W14) -> -0.00177
B15: Net Margin | D15: 0 | E15: 0.0412 | F15: 0.0331 | G15: 0.95 | H15: 0.0211 | I15: 0.0073 | J15: 0.0125 | K15: 0.007 | L15: -0.0054 | M15: 0.0031 | N15: -0.0012 | O15: 0.0031 | P15: -0.0004 | Q15: -0.0025 | R15: -0.0092 | S15: -0.0093 | T15: -0.0146 | U15: -0.0435 | V15: -0.0447 | W15: -0.0496 | X15: =AVERAGE(D15:W15) -> 0.0449
B17: Current Ratio | D17: 0 | E17: 1.2 | F17: 1.19 | G17: 1.06 | H17: 0.99 | I17: 0.98 | J17: 0.91 | K17: 0.83 | L17: 0.87 | M17: 0.9 | N17: 0.99 | O17: 1.06 | P17: 0.97 | Q17: 1.12 | R17: 1.2 | S17: 1.06 | T17: 1.02 | U17: 1.05 | V17: 1.24 | W17: 1.29
B18: Debt/Equity Ratio | D18: 0 | E18: 1.37 | F18: 1.52 | G18: 2.04 | H18: 2.07 | I18: 2.16 | J18: 2.41 | K18: 2.16 | L18: 2.44 | M18: 2.31 | N18: 2.71 | O18: 2.39 | P18: 2.51 | Q18: 2.48 | R18: 2.57 | S18: 3.76 | T18: 3.69 | U18: 3.07 | V18: 2.46 | W18: 2.29
B19: PE Ratio | C19: {=_FV(B2,"P/E",TRUE)} -> 24.9394 | D19: 0 | E19: 29.85 | F19: 30.55 | G19: 75 | H19: 29.86 | I19: 80.6 | J19: 51.34 | K19: 97.26 | L19: 0 | M19: 183.73 | N19: 0 | O19: 311.46 | P19: 0 | Q19: 0 | R19: 0 | S19: 0 | T19: 0 | U19: 0 | V19: 0 | W19: 0 | X19: =AVERAGE(D19:W19) -> 44.4825
B20: P/S Ratio | D20: 0 | E20: 1.21 | F20: 0.99 | G20: 0.74 | H20: 0.66 | I20: 0.57 | J20: 0.64 | K20: 0.63 | L20: 0.45 | M20: 0.56 | N20: 0.86 | O20: 0.95 | P20: 1.05 | Q20: 1.13 | R20: 1.27 | S20: 1.1 | T20: 0.95 | U20: 1.03 | V20: 0.89 | W20: 1.19 | X20: =AVERAGE(D20:W20) -> 0.8435
B21: P/B Ratio | D21: 0 | E21: 5.38 | F21: 4.78 | G21: 4.98 | H21: 4.22 | I21: 3.85 | J21: 5.2 | K21: 4.4 | L21: 3.4 | M21: 4.05 | N21: 6.36 | O21: 6.83 | P21: 7.32 | Q21: 6.8 | R21: 7.47 | S21: 8.62 | T21: 7.25 | U21: 7.08 | V21: 4.9 | W21: 7.92 | X21: =AVERAGE(D21:W21) -> 5.5405
B22: EPS | D22: =C5/C19 -> 2.3966094 | E22: 2.6 | F22: 1.97 | G22: 0.54 | H22: 1.18 | I22: 0.35 | J22: 0.59 | K22: 0.31 | L22: -0.26 | M22: 0.14 | N22: -0.05 | O22: 0.13 | P22: -0.02 | Q22: -0.09 | R22: -0.3 | S22: -0.27 | T22: -0.39 | U22: -1.11 | V22: -1.07 | W22: -1.11
B23: ROE | D23: 0 | E23: 0.2413 | F23: 0.221 | G23: 0.0707 | H23: 0.1605 | I23: 0.0554 | J23: 0.0937 | K23: 0.0521 | L23: -0.0404 | M23: 0.0238 | N23: -0.0091 | O23: 0.0231 | P23: -0.0033 | Q23: -0.0184 | R23: -0.0712 | S23: -0.0696 | T23: -0.1052 | U23: -0.2947 | V23: -0.2778 | W23: -0.287 | X23: =AVERAGE(D23:W23) -> -0.011755
B25: #VALUE! | C25: {=_FV(B25,"Price")} -> 14354.902 | D25: 12888 | E25: 11052 | F25: 10905 | G25: 9000 | H25: 8991 | I25: 8151 | J25: 8174 | K25: 7953 | L25: 6907 | M25: 8336 | N25: 7795 | O25: 7402 | P25: 7324 | Q25: 6885 | R25: 6557 | S25: 6343 | T25: 5829 | U25: 5752 | V25: 5254 | W25: 5347
C26: 25.1 | D26: 23.8 | W26: 20.02
M29: Historical Ex Correction
C30: Current | D30: Entry | E30: Exit | F30: AVG 3yr | G30: Median | H30: F/W PE | I30: Lowest
B31: P/E Ratio | C31: ='JD Analysis'!C19 -> 24.9394 | D31: =D32/'JD Analysis'!D22 -> #REF! | E31: =E32/'JD Analysis'!D22 -> #REF! | F31: =AVERAGE('JD Analysis'!D19:O19) -> 74.1375 | G31: =G32/'JD Analysis'!D22 -> 56.52375 | H31: 38.91 | I31: =E19 -> 29.85 | M31: Date | N31: Stock Price | O31: Correction | P31: Days
B32: Stock Price | C32: ='JD Analysis'!C5 -> 59.77 | D32: ='SG Portfolio'!#REF! -> #REF! | E32: ='SG Portfolio'!#REF! -> #REF! | F32: =F31*'JD Analysis'!D22 -> 177.67863 | G32: =AVERAGE(H32,F32) -> 135.46535 | H32: =H31*'JD Analysis'!$D$22 -> 93.252071 | I32: =I31*'JD Analysis'!$D$22 -> 71.53879 | M32: 42946 | N32: 46.4
C33: =(C32-D32)/D32 -> #REF! | D33: =(D32-C32)/C32 -> #REF! | E33: =(E32-D32)/D32 -> #REF! | F33: =(F32-$D$32)/$D$32 -> #REF! | G33: =(G32-$D$32)/$D$32 -> #REF! | H33: =(H32-$D$32)/$D$32 -> #REF! | I33: =(I32-$D$32)/$D$32 -> #REF! | M33: 43065 | N33: 37.27 | O33: =(N33-N32)/N32 -> -0.19676724 | P33: =M33-M32 -> 119
E34: =(E32-C32)/C32 -> #REF! | M34: 43121 | N34: 50.5 | P34: =M34-M33 -> 56
M35: 43422 | N35: 19.27 | O35: =(N35-N34)/N34 -> -0.61841584 | P35: =M35-M34 -> 301
B36: Intrinsic Value (Projected FCF) | C36: 41.37 | M36: 44136 | N36: 92.49 | P36: =M36-M35 -> 714
B37: Stock Price | C37: =C32 -> 59.77 | D37: =D32 -> #REF! | E37: =E32 -> #REF! | F37: =F32 -> 177.67863 | G37: =G32 -> 135.46535 | H37: =H32 -> 93.252071 | I37: =I32 -> 71.53879 | M37: 44178 | N37: 81.53 | O37: =(N37-N36)/N36 -> -0.1184993 | P37: =M37-M36 -> 42
B38: Price to IV | C38: =C37/$C$36 -> 1.4447667 | D38: =D37/$C$36 -> #REF! | E38: =E37/$C$36 -> #REF! | F38: =F37/$C$36 -> 4.2948665 | G38: =G37/$C$36 -> 3.2744827 | H38: =H37/$C$36 -> 2.2540989 | I38: =I37/$C$36 -> 1.7292432 | M38: 44241 | N38: 106.09 | P38: =M38-M37 -> 63
B39: Range in past 10 yr | M39: =TODAY() -> 44649 | N39: =C5 -> 59.77 | O39: =(N39-N38)/N38 -> -0.43661043 | P39: =M39-M38 -> 408
B40: Min | C40: 1.02 | D40: =C40*$C$36 -> 42.1974 | F40: PE | G40: =D40/$D$22 -> 17.607125 | N40: =N38*(1+O40) -> 85.214963 | O40: =MEDIAN(O33,O35,O37) -> -0.19676724
B41: Med | C41: 1.39 | D41: =C41*$C$36 -> 57.5043 | F41: PE | G41: =D41/$D$22 -> 23.994023
B42: Max | C42: 2.45 | D42: =C42*$C$36 -> 101.3565 | F42: PE | G42: =D42/$D$22 -> 42.291623
B43: Industry Median | C43: 0.98 | D43: =C43*$C$36 -> 40.5426 | F43: PE | G43: =D43/$D$22 -> 16.916649
B46: Intrinsic Value (DCF, FCF Based) | C46: 58.31
B47: Stock Price | C47: =C32 -> 59.77 | D47: =D32 -> #REF! | E47: =E32 -> #REF! | F47: =F32 -> 177.67863 | G47: =G32 -> 135.46535 | H47: =H32 -> 93.252071 | I47: =I32 -> 71.53879
B48: Margin of Safety | C48: =($C$46-C47)/$C$46 -> -0.025038587 | D48: =($C$46-D47)/$C$46 -> #REF! | E48: =($C$46-E47)/$C$46 -> #REF! | F48: =($C$46-F47)/$C$46 -> -2.0471382 | G48: =($C$46-G47)/$C$46 -> -1.3231924 | H48: =($C$46-H47)/$C$46 -> -0.59924663 | I48: =($C$46-I47)/$C$46 -> -0.22687001
B51: Intrinsic Value (DCF, Earning Based) | C51: 67.76
B52: Stock Price | C52: =C32 -> 59.77 | D52: =D32 -> #REF! | E52: =E32 -> #REF! | F52: =F32 -> 177.67863 | G52: =G32 -> 135.46535 | H52: =H32 -> 93.252071 | I52: =I32 -> 71.53879
B53: Margin of Safety | C53: =($C$51-C52)/$C$51 -> 0.11791617 | D53: =($C$51-D52)/$C$51 -> #REF! | E53: =($C$51-E52)/$C$51 -> #REF! | F53: =($C$51-F52)/$C$51 -> -1.6221757 | G53: =($C$51-G52)/$C$51 -> -0.99919347 | H53: =($C$51-H52)/$C$51 -> -0.3762112 | I53: =($C$51-I52)/$C$51 -> -0.055767267
B54: Range in past 10 yr
B55: Current | C55: =C52/$C$51 -> 0.88208383
B56: Min | C56: 0 | D56: =C56*$C$51 -> 0
B57: Med | C57: 0 | D57: =C57*$C$51 -> 0
B58: Max | C58: 0 | D58: =C58*$C$51 -> 0
B59: Industry Median | C59: 0 | D59: =C59*$C$51 -> 0

Sheet FB Bet
F3: Buy Price | G3: Quantity | H3: Fee | I3: Average Price | J3: Investment | K3: Current Price | L3: Gain/Loss | M3: P/L % | N3: SellPrice | O3: Proceeds | P3: Gain/Loss | Q3: P/L % | R3: BuyDate | S3: SellDate | T3: Holding | U3: Tradable Balance | V3: Margin Call | W3: Force Selling
C4: #VALUE! | D4: NASDAQ | E4: USD | F4: 290 | G4: 0 | H4: 0 | I4: =((F4*G4)+H4)/G4 -> #DIV/0! | J4: =I4*G4 -> #DIV/0! | K4: {=_FV(C4,"Price")} -> 223.59 | L4: =(K4-I4)*G4 -> #DIV/0! | M4: =L4/J4 -> #DIV/0! | N4: 282 | O4: =N4*G4 -> 0 | P4: =(N4-I4)*G4 -> #DIV/0! | Q4: =P4/J4 -> #DIV/0! | R4: 01/28/2021
C5: =F5/K4 -> 1.2075674 | D5: NASDAQ | E5: USD | F5: 270 | G5: 0 | H5: 0 | I5: =((F5*G5)+H5)/G5 -> #DIV/0! | J5: =I5*G5 -> #DIV/0! | K5: =K4 -> 223.59 | L5: =(K5-I5)*G5 -> #DIV/0! | M5: =L5/J5 -> #DIV/0! | N5: =N4 -> 282 | O5: =N5*G5 -> 0 | P5: =(N5-I5)*G5 -> #DIV/0! | Q5: =P5/J5 -> #DIV/0! | R5: 03/12/2021
C6: =F6/F5 -> 0.94444444 | D6: NASDAQ | E6: USD | F6: 255 | I6: =((F6*G6)+H6)/G6 -> #DIV/0! | J6: =I6*G6 -> #DIV/0! | K6: =K4 -> 223.59 | L6: =(K6-I6)*G6 -> #DIV/0! | M6: =L6/J6 -> #DIV/0! | N6: =N4 -> 282 | O6: =N6*G6 -> 0 | P6: =(N6-I6)*G6 -> #DIV/0! | Q6: =P6/J6 -> #DIV/0! | R6: 01/28/2021
C7: =F7/F6 -> 0.96078431 | D7: NASDAQ | E7: USD | F7: 245 | I7: =((F7*G7)+H7)/G7 -> #DIV/0! | J7: =I7*G7 -> #DIV/0! | K7: =K4 -> 223.59 | L7: =(K7-I7)*G7 -> #DIV/0! | M7: =L7/J7 -> #DIV/0! | N7: =N4 -> 282 | O7: =N7*G7 -> 0 | P7: =(N7-I7)*G7 -> #DIV/0! | Q7: =P7/J7 -> #DIV/0! | R7: 01/28/2021
C8: =F8/F7 -> 0.95918367 | D8: NASDAQ | E8: USD | F8: 235 | I8: =((F8*G8)+H8)/G8 -> #DIV/0! | J8: =I8*G8 -> #DIV/0! | K8: =K4 -> 223.59 | L8: =(K8-I8)*G8 -> #DIV/0! | M8: =L8/J8 -> #DIV/0! | N8: =N4 -> 282 | O8: =N8*G8 -> 0 | P8: =(N8-I8)*G8 -> #DIV/0! | Q8: =P8/J8 -> #DIV/0! | R8: 01/28/2021
C9: =F9/F8 -> 0.93617021 | D9: NASDAQ | E9: USD | F9: 220 | I9: =((F9*G9)+H9)/G9 -> #DIV/0! | J9: =I9*G9 -> #DIV/0! | K9: =K5 -> 223.59 | L9: =(K9-I9)*G9 -> #DIV/0! | M9: =L9/J9 -> #DIV/0! | N9: =N5 -> 282 | O9: =N9*G9 -> 0 | P9: =(N9-I9)*G9 -> #DIV/0! | Q9: =P9/J9 -> #DIV/0! | R9: 01/28/2021
C10: =F10/F9 -> 0.90909091 | D10: NASDAQ | E10: USD | F10: 200 | I10: =((F10*G10)+H10)/G10 -> #DIV/0! | J10: =I10*G10 -> #DIV/0! | K10: =K9 -> 223.59 | L10: =(K10-I10)*G10 -> #DIV/0! | M10: =L10/J10 -> #DIV/0! | N10: =K10 -> 223.59 | O10: =N10*G10 -> 0 | P10: =(N10-I10)*G10 -> #DIV/0! | Q10: =P10/J10 -> #DIV/0! | R10: 01/28/2021
D12: NASDAQ | E12: USD | F12: =(F4*G4+F5*G5+F6*G6+F7*G7+F8*G8+F9*G9+F10*G10)/G12 -> #DIV/0! | G12: =SUM(G4:G10) -> 0 | H12: =SUM(H4:H10) -> 0 | I12: =((F12*G12)+H12)/G12 -> #DIV/0! | J12: =I12*G12 -> #DIV/0! | K12: =K4 -> 223.59 | L12: =(K12-I12)*G12 -> #DIV/0! | M12: =L12/J12 -> #DIV/0! | U12: =(('SG Portfolio'!$D$4+'SG Portfolio'!$D$5)-('SG Portfolio'!$E$17+'SG Portfolio'!$E$18+'SG Portfolio'!$E$19))+((J12+#REF!)+(L12+#REF!))*(1-'Fee and Margin'!$E$25)+('SG Portfolio'!$E$18+'SG Portfolio'!$H$18)*(1-'Fee and Margin'!$E$26)+('SG Portfolio'!$E$19+'SG Portfolio'!$H$19)*(1-'Fee and Margin'!$E$27) -> #DIV/0! | V12: =((J12+#REF!)+(L12+#REF!))*'Fee and Margin'!$F$25+('SG Portfolio'!$E$18+'SG Portfolio'!$H$18)*'Fee and Margin'!$F$26+('SG Portfolio'!$E$19+'SG Portfolio'!$H$19)*'Fee and Margin'!$F$27-((('SG Portfolio'!$D$4+'SG Portfolio'!$D$5)-('SG Portfolio'!$E$17+'SG Portfolio'!$E$18+'SG Portfolio'!$E$19))+((J12+#REF!)+(L12+#REF!)+'SG Portfolio'!$E$18+'SG Portfolio'!$H$18+'SG Portfolio'!$E$19+'SG Portfolio'!$H$19)) -> #DIV/0! | W12: =((J12+#REF!)+(L12+#REF!))*'Fee and Margin'!$G$25+('SG Portfolio'!$E$18+'SG Portfolio'!$H$18)*'Fee and Margin'!$G$26+('SG Portfolio'!$E$19+'SG Portfolio'!$H$19)*'Fee and Margin'!$G$27-((('SG Portfolio'!$D$4+'SG Portfolio'!$D$5)-('SG Portfolio'!$E$17+'SG Portfolio'!$E$18+'SG Portfolio'!$E$19))+((J12+#REF!)+(L12+#REF!)+'SG Portfolio'!$E$18+'SG Portfolio'!$H$18+'SG Portfolio'!$E$19+'SG Portfolio'!$H$19)) -> #DIV/0!
D13: NASDAQ | E13: USD | F13: =$F$12 -> #DIV/0! | G13: =$G$12 -> 0 | H13: =$H$12 -> 0 | I13: =((F13*G13)+H13)/G13 -> #DIV/0! | J13: =I13*G13 -> #DIV/0! | K13: 265 | L13: =(K13-I13)*G13 -> #DIV/0! | M13: =L13/J13 -> #DIV/0! | U13: =(('SG Portfolio'!$D$4+'SG Portfolio'!$D$5)-('SG Portfolio'!$E$17+'SG Portfolio'!$E$18+'SG Portfolio'!$E$19))+((J13+#REF!)+(L13+#REF!))*(1-'Fee and Margin'!$E$25)+('SG Portfolio'!$E$18+'SG Portfolio'!$H$18)*(1-'Fee and Margin'!$E$26)+('SG Portfolio'!$E$19+'SG Portfolio'!$H$19)*(1-'Fee and Margin'!$E$27) -> #DIV/0! | V13: =((J13+#REF!)+(L13+#REF!))*'Fee and Margin'!$F$25+('SG Portfolio'!$E$18+'SG Portfolio'!$H$18)*'Fee and Margin'!$F$26+('SG Portfolio'!$E$19+'SG Portfolio'!$H$19)*'Fee and Margin'!$F$27-((('SG Portfolio'!$D$4+'SG Portfolio'!$D$5)-('SG Portfolio'!$E$17+'SG Portfolio'!$E$18+'SG Portfolio'!$E$19))+((J13+#REF!)+(L13+#REF!)+'SG Portfolio'!$E$18+'SG Portfolio'!$H$18+'SG Portfolio'!$E$19+'SG Portfolio'!$H$19)) -> #DIV/0! | W13: =((J13+#REF!)+(L13+#REF!))*'Fee and Margin'!$G$25+('SG Portfolio'!$E$18+'SG Portfolio'!$H$18)*'Fee and Margin'!$G$26+('SG Portfolio'!$E$19+'SG Portfolio'!$H$19)*'Fee and Margin'!$G$27-((('SG Portfolio'!$D$4+'SG Portfolio'!$D$5)-('SG Portfolio'!$E$17+'SG Portfolio'!$E$18+'SG Portfolio'!$E$19))+((J13+#REF!)+(L13+#REF!)+'SG Portfolio'!$E$18+'SG Portfolio'!$H$18+'SG Portfolio'!$E$19+'SG Portfolio'!$H$19)) -> #DIV/0!
D14: NASDAQ | E14: USD | F14: =$F$12 -> #DIV/0! | G14: =$G$12 -> 0 | H14: =$H$12 -> 0 | I14: =((F14*G14)+H14)/G14 -> #DIV/0! | J14: =I14*G14 -> #DIV/0! | K14: ='FB Analysis'!H32 -> 239.2339 | L14: =(K14-I14)*G14 -> #DIV/0! | M14: =L14/J14 -> #DIV/0! | U14: =(('SG Portfolio'!$D$4+'SG Portfolio'!$D$5)-('SG Portfolio'!$E$17+'SG Portfolio'!$E$18+'SG Portfolio'!$E$19))+((J14+#REF!)+(L14+#REF!))*(1-'Fee and Margin'!$E$25)+('SG Portfolio'!$E$18+'SG Portfolio'!$H$18)*(1-'Fee and Margin'!$E$26)+('SG Portfolio'!$E$19+'SG Portfolio'!$H$19)*(1-'Fee and Margin'!$E$27) -> #DIV/0! | V14: =((J14+#REF!)+(L14+#REF!))*'Fee and Margin'!$F$25+('SG Portfolio'!$E$18+'SG Portfolio'!$H$18)*'Fee and Margin'!$F$26+('SG Portfolio'!$E$19+'SG Portfolio'!$H$19)*'Fee and Margin'!$F$27-((('SG Portfolio'!$D$4+'SG Portfolio'!$D$5)-('SG Portfolio'!$E$17+'SG Portfolio'!$E$18+'SG Portfolio'!$E$19))+((J14+#REF!)+(L14+#REF!)+'SG Portfolio'!$E$18+'SG Portfolio'!$H$18+'SG Portfolio'!$E$19+'SG Portfolio'!$H$19)) -> #DIV/0! | W14: =((J14+#REF!)+(L14+#REF!))*'Fee and Margin'!$G$25+('SG Portfolio'!$E$18+'SG Portfolio'!$H$18)*'Fee and Margin'!$G$26+('SG Portfolio'!$E$19+'SG Portfolio'!$H$19)*'Fee and Margin'!$G$27-((('SG Portfolio'!$D$4+'SG Portfolio'!$D$5)-('SG Portfolio'!$E$17+'SG Portfolio'!$E$18+'SG Portfolio'!$E$19))+((J14+#REF!)+(L14+#REF!)+'SG Portfolio'!$E$18+'SG Portfolio'!$H$18+'SG Portfolio'!$E$19+'SG Portfolio'!$H$19)) -> #DIV/0!
D15: NASDAQ | E15: USD | F15: =$F$12 -> #DIV/0! | G15: =$G$12 -> 0 | H15: =$H$12 -> 0 | I15: =((F15*G15)+H15)/G15 -> #DIV/0! | J15: =I15*G15 -> #DIV/0! | K15: 220 | L15: =(K15-I15)*G15 -> #DIV/0! | M15: =L15/J15 -> #DIV/0! | U15: =(('SG Portfolio'!$D$4+'SG Portfolio'!$D$5)-('SG Portfolio'!$E$17+'SG Portfolio'!$E$18+'SG Portfolio'!$E$19))+((J15+#REF!)+(L15+#REF!))*(1-'Fee and Margin'!$E$25)+('SG Portfolio'!$E$18+'SG Portfolio'!$H$18)*(1-'Fee and Margin'!$E$26)+('SG Portfolio'!$E$19+'SG Portfolio'!$H$19)*(1-'Fee and Margin'!$E$27) -> #DIV/0! | V15: =((J15+#REF!)+(L15+#REF!))*'Fee and Margin'!$F$25+('SG Portfolio'!$E$18+'SG Portfolio'!$H$18)*'Fee and Margin'!$F$26+('SG Portfolio'!$E$19+'SG Portfolio'!$H$19)*'Fee and Margin'!$F$27-((('SG Portfolio'!$D$4+'SG Portfolio'!$D$5)-('SG Portfolio'!$E$17+'SG Portfolio'!$E$18+'SG Portfolio'!$E$19))+((J15+#REF!)+(L15+#REF!)+'SG Portfolio'!$E$18+'SG Portfolio'!$H$18+'SG Portfolio'!$E$19+'SG Portfolio'!$H$19)) -> #DIV/0! | W15: =((J15+#REF!)+(L15+#REF!))*'Fee and Margin'!$G$25+('SG Portfolio'!$E$18+'SG Portfolio'!$H$18)*'Fee and Margin'!$G$26+('SG Portfolio'!$E$19+'SG Portfolio'!$H$19)*'Fee and Margin'!$G$27-((('SG Portfolio'!$D$4+'SG Portfolio'!$D$5)-('SG Portfolio'!$E$17+'SG Portfolio'!$E$18+'SG Portfolio'!$E$19))+((J15+#REF!)+(L15+#REF!)+'SG Portfolio'!$E$18+'SG Portfolio'!$H$18+'SG Portfolio'!$E$19+'SG Portfolio'!$H$19)) -> #DIV/0!
D16: NASDAQ | E16: USD | F16: =$F$12 -> #DIV/0! | G16: =$G$12 -> 0 | H16: =$H$12 -> 0 | I16: =((F16*G16)+H16)/G16 -> #DIV/0! | J16: =I16*G16 -> #DIV/0! | K16: 202 | L16: =(K16-I16)*G16 -> #DIV/0! | M16: =L16/J16 -> #DIV/0! | U16: =(('SG Portfolio'!$D$4+'SG Portfolio'!$D$5)-('SG Portfolio'!$E$17+'SG Portfolio'!$E$18+'SG Portfolio'!$E$19))+((J16+#REF!)+(L16+#REF!))*(1-'Fee and Margin'!$E$25)+('SG Portfolio'!$E$18+'SG Portfolio'!$H$18)*(1-'Fee and Margin'!$E$26)+('SG Portfolio'!$E$19+'SG Portfolio'!$H$19)*(1-'Fee and Margin'!$E$27) -> #DIV/0! | V16: =((J16+#REF!)+(L16+#REF!))*'Fee and Margin'!$F$25+('SG Portfolio'!$E$18+'SG Portfolio'!$H$18)*'Fee and Margin'!$F$26+('SG Portfolio'!$E$19+'SG Portfolio'!$H$19)*'Fee and Margin'!$F$27-((('SG Portfolio'!$D$4+'SG Portfolio'!$D$5)-('SG Portfolio'!$E$17+'SG Portfolio'!$E$18+'SG Portfolio'!$E$19))+((J16+#REF!)+(L16+#REF!)+'SG Portfolio'!$E$18+'SG Portfolio'!$H$18+'SG Portfolio'!$E$19+'SG Portfolio'!$H$19)) -> #DIV/0! | W16: =((J16+#REF!)+(L16+#REF!))*'Fee and Margin'!$G$25+('SG Portfolio'!$E$18+'SG Portfolio'!$H$18)*'Fee and Margin'!$G$26+('SG Portfolio'!$E$19+'SG Portfolio'!$H$19)*'Fee and Margin'!$G$27-((('SG Portfolio'!$D$4+'SG Portfolio'!$D$5)-('SG Portfolio'!$E$17+'SG Portfolio'!$E$18+'SG Portfolio'!$E$19))+((J16+#REF!)+(L16+#REF!)+'SG Portfolio'!$E$18+'SG Portfolio'!$H$18+'SG Portfolio'!$E$19+'SG Portfolio'!$H$19)) -> #DIV/0!
D17: NASDAQ | E17: USD | F17: =$F$12 -> #DIV/0! | G17: =$G$12 -> 0 | H17: =$H$12 -> 0 | I17: =((F17*G17)+H17)/G17 -> #DIV/0! | J17: =I17*G17 -> #DIV/0! | K17: 185 | L17: =(K17-I17)*G17 -> #DIV/0! | M17: =L17/J17 -> #DIV/0! | U17: =(('SG Portfolio'!$D$4+'SG Portfolio'!$D$5)-('SG Portfolio'!$E$17+'SG Portfolio'!$E$18+'SG Portfolio'!$E$19))+((J17+#REF!)+(L17+#REF!))*(1-'Fee and Margin'!$E$25)+('SG Portfolio'!$E$18+'SG Portfolio'!$H$18)*(1-'Fee and Margin'!$E$26)+('SG Portfolio'!$E$19+'SG Portfolio'!$H$19)*(1-'Fee and Margin'!$E$27) -> #DIV/0! | V17: =((J17+#REF!)+(L17+#REF!))*'Fee and Margin'!$F$25+('SG Portfolio'!$E$18+'SG Portfolio'!$H$18)*'Fee and Margin'!$F$26+('SG Portfolio'!$E$19+'SG Portfolio'!$H$19)*'Fee and Margin'!$F$27-((('SG Portfolio'!$D$4+'SG Portfolio'!$D$5)-('SG Portfolio'!$E$17+'SG Portfolio'!$E$18+'SG Portfolio'!$E$19))+((J17+#REF!)+(L17+#REF!)+'SG Portfolio'!$E$18+'SG Portfolio'!$H$18+'SG Portfolio'!$E$19+'SG Portfolio'!$H$19)) -> #DIV/0! | W17: =((J17+#REF!)+(L17+#REF!))*'Fee and Margin'!$G$25+('SG Portfolio'!$E$18+'SG Portfolio'!$H$18)*'Fee and Margin'!$G$26+('SG Portfolio'!$E$19+'SG Portfolio'!$H$19)*'Fee and Margin'!$G$27-((('SG Portfolio'!$D$4+'SG Portfolio'!$D$5)-('SG Portfolio'!$E$17+'SG Portfolio'!$E$18+'SG Portfolio'!$E$19))+((J17+#REF!)+(L17+#REF!)+'SG Portfolio'!$E$18+'SG Portfolio'!$H$18+'SG Portfolio'!$E$19+'SG Portfolio'!$H$19)) -> #DIV/0!
D18: NASDAQ | E18: USD | F18: =$F$12 -> #DIV/0! | G18: =$G$12 -> 0 | H18: =$H$12 -> 0 | I18: =((F18*G18)+H18)/G18 -> #DIV/0! | J18: =I18*G18 -> #DIV/0! | K18: ='FB Analysis'!I32 -> 174.72894 | L18: =(K18-I18)*G18 -> #DIV/0! | M18: =L18/J18 -> #DIV/0! | U18: =(('SG Portfolio'!$D$4+'SG Portfolio'!$D$5)-('SG Portfolio'!$E$17+'SG Portfolio'!$E$18+'SG Portfolio'!$E$19))+((J18+#REF!)+(L18+#REF!))*(1-'Fee and Margin'!$E$25)+('SG Portfolio'!$E$18+'SG Portfolio'!$H$18)*(1-'Fee and Margin'!$E$26)+('SG Portfolio'!$E$19+'SG Portfolio'!$H$19)*(1-'Fee and Margin'!$E$27) -> #DIV/0! | V18: =((J18+#REF!)+(L18+#REF!))*'Fee and Margin'!$F$25+('SG Portfolio'!$E$18+'SG Portfolio'!$H$18)*'Fee and Margin'!$F$26+('SG Portfolio'!$E$19+'SG Portfolio'!$H$19)*'Fee and Margin'!$F$27-((('SG Portfolio'!$D$4+'SG Portfolio'!$D$5)-('SG Portfolio'!$E$17+'SG Portfolio'!$E$18+'SG Portfolio'!$E$19))+((J18+#REF!)+(L18+#REF!)+'SG Portfolio'!$E$18+'SG Portfolio'!$H$18+'SG Portfolio'!$E$19+'SG Portfolio'!$H$19)) -> #DIV/0! | W18: =((J18+#REF!)+(L18+#REF!))*'Fee and Margin'!$G$25+('SG Portfolio'!$E$18+'SG Portfolio'!$H$18)*'Fee and Margin'!$G$26+('SG Portfolio'!$E$19+'SG Portfolio'!$H$19)*'Fee and Margin'!$G$27-((('SG Portfolio'!$D$4+'SG Portfolio'!$D$5)-('SG Portfolio'!$E$17+'SG Portfolio'!$E$18+'SG Portfolio'!$E$19))+((J18+#REF!)+(L18+#REF!)+'SG Portfolio'!$E$18+'SG Portfolio'!$H$18+'SG Portfolio'!$E$19+'SG Portfolio'!$H$19)) -> #DIV/0!
D20: NASDAQ | E20: USD | F20: =I12 -> #DIV/0! | G20: 30 | H20: 8.88 | I20: =((F20*G20)+H20)/G20 -> #DIV/0! | J20: =I20*G20 -> #DIV/0! | K20: =K4 -> 223.59 | L20: =(K20-I20)*G20 -> #DIV/0! | M20: =L20/J20 -> #DIV/0! | N20: 280 | O20: =N20*G20 -> 8400 | P20: =(N20-I20)*G20 -> #DIV/0! | Q20: =P20/J20 -> #DIV/0! | R20: 01/28/2021
D21: NASDAQ | E21: USD | F21: =I13 -> #DIV/0! | G21: 30 | H21: 8.88 | I21: =((F21*G21)+H21)/G21 -> #DIV/0! | J21: =I21*G21 -> #DIV/0! | K21: =K4 -> 223.59 | L21: =(K21-I21)*G21 -> #DIV/0! | M21: =L21/J21 -> #DIV/0! | N21: 290 | O21: =N21*G21 -> 8700 | P21: =(N21-I21)*G21 -> #DIV/0! | Q21: =P21/J21 -> #DIV/0! | R21: 01/28/2021
D22: NASDAQ | E22: USD | F22: =I14 -> #DIV/0! | G22: 40 | H22: 8.88 | I22: =((F22*G22)+H22)/G22 -> #DIV/0! | J22: =I22*G22 -> #DIV/0! | K22: =K5 -> 223.59 | L22: =(K22-I22)*G22 -> #DIV/0! | M22: =L22/J22 -> #DIV/0! | N22: 300 | O22: =N22*G22 -> 12000 | P22: =(N22-I22)*G22 -> #DIV/0! | Q22: =P22/J22 -> #DIV/0! | R22: 01/28/2021
D23: NASDAQ | E23: USD | F23: =I15 -> #DIV/0! | I23: =((F23*G23)+H23)/G23 -> #DIV/0! | J23: =I23*G23 -> #DIV/0! | K23: =K5 -> 223.59 | L23: =(K23-I23)*G23 -> #DIV/0! | M23: =L23/J23 -> #DIV/0! | N23: 280 | O23: =N23*G23 -> 0 | P23: =(N23-I23)*G23 -> #DIV/0! | Q23: =P23/J23 -> #DIV/0! | R23: 01/28/2021
D24: NASDAQ | E24: USD | F24: =I16 -> #DIV/0! | I24: =((F24*G24)+H24)/G24 -> #DIV/0! | J24: =I24*G24 -> #DIV/0! | K24: =K9 -> 223.59 | L24: =(K24-I24)*G24 -> #DIV/0! | M24: =L24/J24 -> #DIV/0! | N24: 290 | O24: =N24*G24 -> 0 | P24: =(N24-I24)*G24 -> #DIV/0! | Q24: =P24/J24 -> #DIV/0! | R24: 01/28/2021
D25: NASDAQ | E25: USD | F25: =I17 -> #DIV/0! | I25: =((F25*G25)+H25)/G25 -> #DIV/0! | J25: =I25*G25 -> #DIV/0! | K25: =K5 -> 223.59 | L25: =(K25-I25)*G25 -> #DIV/0! | M25: =L25/J25 -> #DIV/0! | N25: 300 | O25: =N25*G25 -> 0 | P25: =(N25-I25)*G25 -> #DIV/0! | Q25: =P25/J25 -> #DIV/0! | R25: 01/28/2021
G33: 5 Days | H33: Avg. Daily | I33: Avg. half hour | J33: High | K33: Low | L33: MA5 | M33: MA10 | N33: MA20 | O33: MA30 | P33: MA60
E34: Past Volume ('000) | G34: 93665 | H34: =G34/5 -> 18733 | I34: =H34/13 -> 1441 | J34: 322.93 | K34: 299.69 | L34: 313.32 | M34: 316.92 | N34: 309.83 | O34: 289.8 | P34: 266.82
E35: Current | H35: 18920 | I35: =H35/13 -> 1455.3846 | J35: 306.53 | K35: 299.69

Sheet FB Analysis
B2: #VALUE!
C3: 2021 | D3: 2020 | H3: 2019 | L3: 2018 | P3: 2017 | T3: 2016 | X3: AVG
C4: Current | D4: Q4 | E4: Q3 | F4: Q2 | G4: Q1 | H4: Q4 | I4: Q3 | J4: Q2 | K4: Q1 | L4: Q4 | M4: Q3 | N4: Q2 | O4: Q1 | P4: Q4 | Q4: Q3 | R4: Q2 | S4: Q1 | T4: Q4 | U4: Q3 | V4: Q2 | W4: Q1
B5: Stock Price | C5: {=_FV(B2,"Price")} -> 223.59 | D5: 273.16 | E5: 261.9 | F5: 227.07 | G5: 166.8 | H5: 205.25 | I5: 178.08 | J5: 193 | K5: 166.69 | L5: 131.09 | M5: 164.46 | N5: 194.32 | O5: 159.79 | P5: 176.46 | Q5: 170.87 | R5: 150.98 | S5: 142.05 | T5: 115.05 | U5: 128.27 | V5: 114.28 | W5: 114.1
B6: Outstanding Shares | C6: {=_FV(B2,"Shares outstanding",TRUE)/1000000} -> 2721.942 | D6: 2888 | E6: 2891 | F6: 2879 | G6: 2868 | H6: 2876 | I6: 2874 | J6: 2875 | K6: 2869 | L6: 2921 | M6: 2913 | N6: 2930 | O6: 2945 | P6: 2956 | Q6: 2956 | R6: 2951 | S6: 2944 | T6: 2925 | U6: 2931 | V6: 2921 | W6: 2905 | X6: =AVERAGE(D6:W6) -> 2910.9
B7: Market Cap | C7: =C5*C6/1000 -> 608.59901 | D7: =D5*D6/1000 -> 788.88608 | E7: =E5*E6/1000 -> 757.1529 | F7: =F5*F6/1000 -> 653.73453 | G7: =G5*G6/1000 -> 478.3824 | H7: =H5*H6/1000 -> 590.299 | I7: =I5*I6/1000 -> 511.80192 | J7: =J5*J6/1000 -> 554.875 | ... W7: =W5*W6/1000 -> 331.4605
B9: Revenue | D9: 85.97 | E9: 78.98 | F9: 75.16 | G9: 73.36 | H9: 70.7 | I9: 66.53 | J9: 62.6 | K9: 58.95 | L9: 55.84 | M9: 51.9 | N9: 48.5 | O9: 44.59 | P9: 40.65 | Q9: 36.49 | R9: 33.17 | S9: 30.29 | T9: 27.64 | U9: 24.67 | V9: 22.16 | W9: 19.77
D10: =(D9-E9)/E9 -> 0.088503419 | E10: =(E9-F9)/F9 -> 0.050824907 | F10: =(F9-G9)/G9 -> 0.024536532 | G10: =(G9-H9)/H9 -> 0.037623762 | H10: =(H9-I9)/I9 -> 0.062678491 | I10: =(I9-J9)/J9 -> 0.062779553 | J10: =(J9-K9)/K9 -> 0.061916879 | K10: =(K9-L9)/L9 -> 0.055694842 | ... V10: =(V9-W9)/W9 -> 0.12089024 | X10: =AVERAGE(D10:V10) -> 0.080778248
B11: Gross Profit | D11: 69.27 | E11: 64 | F11: 61.22 | G11: 29.94 | H11: 57.93 | I11: 54.46 | J11: 51.27 | K11: 48.71 | L11: 46.48 | M11: 43.73 | N11: 41.3 | O11: 38.37 | P11: 35.2 | Q11: 31.6 | R11: 28.74 | S11: 26.18 | T11: 23.85 | U11: 21.1 | V11: 18.86 | W11: 16.72
B12: Cash on Hand | D12: 61.95 | E12: 55.62 | F12: 58.24 | G12: 60.29 | H12: 54.86 | I12: 52.27 | J12: 48.6 | K12: 45.24 | L12: 41.11 | M12: 41.21 | N12: 42.31 | O12: 43.96 | P12: 41.71 | Q12: 38.29 | R12: 35.45 | S12: 32.31 | T12: 29.45 | U12: 26.14 | V12: 23.29 | W12: 20.62
B13: Gross Margin | D13: 0.8058 | E13: 0.8104 | F13: 0.8146 | G13: 0.8172 | H13: 0.8194 | I13: 0.8185 | J13: 0.8189 | K13: 0.8262 | L13: 0.8325 | M13: 0.8426 | N13: 0.8516 | O13: 0.8605 | P13: 0.8658 | Q13: 0.866 | R13: 0.8665 | S13: 0.8643 | T13: 0.8629 | U13: 0.8554 | V13: 0.8511 | W13: 0.8457 | X13: =AVERAGE(D13:W13) -> 0.839795
B14: Operating Margin | D14: 0.3801 | E14: 0.3641 | F14: 0.3712 | G14: 0.3621 | H14: 0.3393 | I14: 0.3449 | J14: 0.3441 | K14: 0.3865 | L14: 0.4462 | M14: 0.4711 | N14: 0.4905 | O14: 0.5007 | P14: 0.497 | Q14: 0.4773 | R14: 0.4646 | S14: 0.4538 | T14: 0.4496 | U14: 0.4224 | V14: 0.3954 | W14: 0.3694 | X14: =AVERAGE(D14:W14) -> 0.416515
B15: Net Margin | D15: 0.339 | E15: 0.32 | F15: 0.3129 | G15: 0.2857 | H15: 0.2615 | I15: 0.2708 | J15: 0.2726 | K15: 0.3317 | L15: 0.396 | M15: 0.3757 | N15: 0.3931 | O15: 0.4003 | P15: 0.3916 | Q15: 0.4169 | R15: 0.3958 | S15: 0.3802 | T15: 0.3686 | U15: 0.3316 | V15: 0.2912 | W15: 0.2475 | X15: =AVERAGE(D15:W15) -> 0.339135
B17: Current Ratio | D17: 5.05 | E17: 5.51 | F17: 6.02 | G17: 4.6 | H17: 4.4 | I17: 4.66 | J17: 4.47 | K17: 5.38 | L17: 7.19 | M17: 9 | N17: 10.67 | O17: 9.91 | P17: 12.92 | Q17: 13.37 | R17: 12.31 | S17: 12.61 | T17: 11.97 | U17: 11.69 | V17: 12.22 | W17: 13.16
B18: Debt/Equity Ratio | D18: 0.24 | E18: 0.24 | F18: 0.26 | G18: 0.31 | H18: 0.32 | I18: 0.32 | J18: 0.32 | K18: 0.27 | L18: 0.16 | M18: 0.15 | N18: 0.14 | O18: 0.15 | P18: 0.14 | Q18: 0.11 | R18: 0.11 | S18: 0.1 | T18: 0.1 | U18: 0.1 | V18: 0.11 | W18: 0.1
B19: PE Ratio | C19: {=_FV(B2,"P/E",TRUE)} -> 16.2107 | D19: =D5/D22 -> 27.072349 | E19: =E5/E22 -> 29.86317 | F19: =F5/F22 -> 27.759169 | G19: =G5/G22 -> 22.880658 | H19: =H5/H22 -> 31.920684 | I19: =I5/I22 -> 28.447284 | J19: =J5/J22 -> 32.711864 | K19: =K5/K22 -> 24.768202 | ... W19: =W5/W22 -> 66.725146 | X19: =AVERAGE(D19:W19) -> 32.794471
B20: P/S Ratio | D20: 9.16 | E20: 9.55 | F20: 8.68 | G20: 6.53 | H20: 8.34 | I20: 7.72 | J20: 8.92 | K20: 8.22 | L20: 6.87 | M20: 9.3 | N20: 11.8 | O20: 10.58 | P20: 12.82 | Q20: 13.79 | R20: 13.37 | S20: 13.74 | T20: 12.16 | U20: 15.1 | V20: 14.89 | W20: 16.56 | X20: =AVERAGE(D20:W20) -> 10.905
B21: P/B Ratio | D21: 6.15 | E21: 6.43 | F21: 5.92 | G21: 4.54 | H21: 5.84 | I21: 5.44 | J21: 6.25 | K21: 5.53 | L21: 4.55 | M21: 5.96 | N21: 7.17 | O21: 6.06 | P21: 7.02 | Q21: 7.09 | R21: 6.7 | S21: 6.72 | T21: 5.69 | U21: 6.95 | V21: 6.63 | W21: 7.03 | X21: =AVERAGE(D21:W21) -> 6.1835
B22: EPS | D22: 10.09 | E22: 8.77 | F22: 8.18 | G22: 7.29 | H22: 6.43 | I22: 6.26 | J22: 5.9 | K22: 6.73 | L22: 7.57 | M22: 6.63 | N22: 6.46 | O22: 6.04 | P22: 5.39 | Q22: 5.16 | R22: 4.47 | S22: 3.93 | T22: 3.49 | U22: 2.83 | V22: 2.24 | W22: 1.71
B23: ROE | D23: 0.2525 | E23: 0.2327 | F23: 0.229 | G23: 0.2154 | H23: 0.1997 | I23: 0.2039 | J23: 0.2009 | K23: 0.2367 | L23: 0.2751 | M23: 0.2502 | N23: 0.252 | O23: 0.2465 | P23: 0.2322 | Q23: 0.2349 | R23: 0.217 | S23: 0.2039 | T23: 0.1933 | U23: 0.1671 | V23: 0.1409 | W23: 0.1136 | X23: =AVERAGE(D23:W23) -> 0.214875
B25: #VALUE! | C25: {=_FV(B25,"Price")} -> 14354.902 | D25: 12888 | E25: 11052 | F25: 10905 | G25: 9000 | H25: 8991 | I25: 8151 | J25: 8174 | K25: 7953 | L25: 6907 | M25: 8336 | N25: 7795 | O25: 7402 | P25: 7324 | Q25: 6885 | R25: 6557 | S25: 6343 | T25: 5829 | U25: 5752 | V25: 5254 | W25: 5347
C26: 25.1 | D26: 23.8 | W26: 20.02
M29: Historical Ex Correction
C30: Current | D30: Entry | E30: Exit | F30: AVG 3yr | G30: Median | H30: F/W PE | I30: Lowest
B31: P/E Ratio | C31: ='FB Analysis'!C19 -> 16.2107 | D31: 0 | E31: =E32/'FB Analysis'!D22 -> #REF! | F31: =AVERAGE('FB Analysis'!D19:O19) -> 27.006804 | G31: =G32/'FB Analysis'!D22 -> 25.358402 | H31: 23.71 | I31: =L19 -> 17.317041 | M31: Date | N31: Stock Price | O31: Correction | P31: Days
B32: Stock Price | C32: ='FB Analysis'!C5 -> 223.59 | D32: 0 | E32: ='SG Portfolio'!#REF! -> #REF! | F32: =F31*'FB Analysis'!D22 -> 272.49865 | G32: =AVERAGE(H32,F32) -> 255.86628 | H32: =H31*'FB Analysis'!$D$22 -> 239.2339 | I32: =I31*'FB Analysis'!$D$22 -> 174.72894 | M32: 43306 | N32: 217.5
C33: =(C32-D32)/D32 -> #DIV/0! | D33: =(D32-C32)/C32 -> -1 | E33: =(E32-D32)/D32 -> #REF! | F33: =(F32-$D$32)/$D$32 -> #DIV/0! | G33: =(G32-$D$32)/$D$32 -> #DIV/0! | H33: =(H32-$D$32)/$D$32 -> #DIV/0! | I33: =(I32-$D$32)/$D$32 -> #DIV/0! | M33: 43458 | N33: 124.06 | O33: =(N33-N32)/N32 -> -0.4296092 | P33: =M33-M32 -> 152
